Workbook

Sheet Summary
A1: WealthPulse — Advisor & Leadership Dashboard Inventory
A2: Source: Azure DevOps board dump (wealthpulse board_202607081304.xlsx) · Prepared 08-Jul-2026
A4: Dashboards to create — by group
A5: Group | B5: Primary Dashboards / Pages | C5: KPIs | D5: Charts | E5: Tables | F5: Total Components
A6: Leadership (Epic-6) | B6: =COUNTIF('Dashboard Inventory'!$B$2:$B$11,"Leadership") -> 3 | C6: =SUMIF('Dashboard Inventory'!$B$2:$B$11,"Leadership",'Dashboard Inventory'!$G$2:$G$11) -> 13 | D6: =SUMIF('Dashboard Inventory'!$B$2:$B$11,"Leadership",'Dashboard Inventory'!$H$2:$H$11) -> 8 | E6: =SUMIF('Dashboard Inventory'!$B$2:$B$11,"Leadership",'Dashboard Inventory'!$I$2:$I$11) -> 4 | F6: =SUMIF('Dashboard Inventory'!$B$2:$B$11,"Leadership",'Dashboard Inventory'!$L$2:$L$11) -> 29
A7: Advisor (Epic-7) | B7: =COUNTIF('Dashboard Inventory'!$B$2:$B$11,"Advisor") -> 7 | C7: =SUMIF('Dashboard Inventory'!$B$2:$B$11,"Advisor",'Dashboard Inventory'!$G$2:$G$11) -> 20 | D7: =SUMIF('Dashboard Inventory'!$B$2:$B$11,"Advisor",'Dashboard Inventory'!$H$2:$H$11) -> 10 | E7: =SUMIF('Dashboard Inventory'!$B$2:$B$11,"Advisor",'Dashboard Inventory'!$I$2:$I$11) -> 7 | F7: =SUMIF('Dashboard Inventory'!$B$2:$B$11,"Advisor",'Dashboard Inventory'!$L$2:$L$11) -> 56
A8: TOTAL | B8: =SUM(B6:B7) -> 10 | C8: =SUM(C6:C7) -> 33 | D8: =SUM(D6:D7) -> 18 | E8: =SUM(E6:E7) -> 11 | F8: =SUM(F6:F7) -> 85
A10: How to read this workbook
A11: • Dashboard Inventory — one row per page/dashboard with ADO IDs, state, and a live component count (KPIs/Charts/Tables/Panels).
A12: • Component Detail — every KPI, chart, table, panel and filter within each page, with its logic/source and build status (filterable).
A13: • ADO Work Items — traceability of the Epic-6 / Epic-7 features, user stories, QA stories and open bugs behind these pages.
A14: • Counts on this sheet and the Inventory are formula-driven from Component Detail, so edits there flow through automatically.
A15: • 'TBD data' = component defined but blocked on data availability (e.g. satisfaction, review dates, NNM targets from Insigneo).
A18: Impact of the new Insigneo Gold-model logic - what leadership sees on the dashboards
A19: KPIs on these dashboards are DB-driven and their logic has already been updated in the database. Classification follows Aman's KPI-logic doc 'Category' column: only items marked 'Done' behave correctly today; everything else is not-ready. We group the not-ready items into 'Logic can be driven' (Aman can build/derive - expected in future) and 'Can't be achieved' (data not available in Insigneo).
A23: Impact category | B23: Meaning | C23: Leadership | D23: Advisor | E23: Total
A24: 1 - Done | B24: Behaves correctly after KPI logic updated in DB | C24: =COUNTIFS('Component Detail'!$A:$A,"Leadership",'Component Detail'!$L:$L,"1 - Done") -> 13 | D24: =COUNTIFS('Component Detail'!$A:$A,"Advisor",'Component Detail'!$L:$L,"1 - Done") -> 12 | E24: =C24+D24 -> 25
A25: 2 - Logic can be driven | B25: Aman to build/derive - expected in future | C25: =COUNTIFS('Component Detail'!$A:$A,"Leadership",'Component Detail'!$L:$L,"2 - Logic can be driven") -> 0 | D25: =COUNTIFS('Component Detail'!$A:$A,"Advisor",'Component Detail'!$L:$L,"2 - Logic can be driven") -> 1 | E25: =C25+D25 -> 1
A26: 3 - Can't be achieved | B26: No data possibility in Insigneo | C26: =COUNTIFS('Component Detail'!$A:$A,"Leadership",'Component Detail'!$L:$L,"3 - Can't be achieved") -> 0 | D26: =COUNTIFS('Component Detail'!$A:$A,"Advisor",'Component Detail'!$L:$L,"3 - Can't be achieved") -> 0 | E26: =C26+D26 -> 0
A27: N/A - UI/placeholder | B27: UI control / placeholder / framework | C27: =COUNTIFS('Component Detail'!$A:$A,"Leadership",'Component Detail'!$L:$L,"N/A - UI/placeholder") -> 0 | D27: =COUNTIFS('Component Detail'!$A:$A,"Advisor",'Component Detail'!$L:$L,"N/A - UI/placeholder") -> 0 | E27: =C27+D27 -> 0
A28: TOTAL | C28: =SUM(C24:C27) -> 13 | D28: =SUM(D24:D27) -> 13 | E28: =SUM(E24:E27) -> 26
A32: Count of Group | B32: Column Labels
A33: Row Labels | B33: Advisor | C33: Leadership | D33: Grand Total
A34: 1 - Done | B34: 12 | C34: 13 | D34: 25
A35: 2 - In Progress | B35: 9 | C35: 1 | D35: 10 | E35: 46216
A36: 2 - Logic can be driven | B36: 1 | D36: 1
A37: 3 - Data Not Available | B37: 15 | C37: 12 | D37: 27 | E37: 46225 | F37: 46220
A38: 4 - Partial achieved | C38: 1 | D38: 1
A39: 5 - Insights | B39: 13 | C39: 1 | D39: 14
A40: Grand Total | B40: 50 | C40: 28 | D40: 78

Sheet Component Detail
A1: Group | B1: Dashboard / Page | C1: Component Type | D1: Component Name | E1: Details / Columns | F1: Source / KPI Ref | G1: Status | H1: Tables identified to used | I1: KPI/Chart ID | J1: SQL Query (Insigneo Query col) | K1: Category (logic doc) | L1: Impact vs our dashboard | M1: Remark (category & reason) | N1: Status | O1: ETA | P1: Remarks
A2: Leadership | B2: Firm Dashboard (Leadership Home) | C2: Chart | D2: Revenue & Fee Rate Chart | E2: Composed chart: revenue vs fee compression by quarter | F2: SUM(net_fee) & (net_fee/AUM)*10000 | G2: Done | H2: fa_commission / transaction_blotter | I2: CHART-002 | J2: WITH ranked_trades AS ( SELECT *, ROW_NUMBER() OVER ( PARTITION BY trade_id ORDER BY CASE workflow_status WHEN 'Reconciled' THEN 2 WHEN 'Confirmed' THEN 1 ELSE 0 END DESC, load_time DESC ) AS rn FROM wealth_pulse_insigneo_model.silver.transaction_blotter WHERE workflow_status IN ('Confirmed', 'Reconciled') AND broker_month >= add_months(current_date(), -24) ) SELECT DATE(date_trunc('quarter', broker_month)) AS quarter, SUM(gross_comm) AS total_revenue, ROUND( (SUM(gross_comm) / NULLIF(SUM(investment_amount), 0)) * 10000, 2 ) AS fee_rate_bps FROM ranked_trades WHERE rn = 1 GROUP BY DATE(date_trunc('quarter', broker_month)) ORDER BY quarter; | K2: Done | L2: Phase 3 WIP | M2: Category: Done. Revenue & Fee Rate chart logic updated in DB. | N2: R&D | O2: 46225 | Q2: WITH latest_snapshot_per_quarter AS ( SELECT DATE_TRUNC('quarter', snapshot_date) AS quarter, MAX(snapshot_date) AS snapshot_date FROM wealth_pulse_insigneo_model.gold.positions GROUP BY DATE_TRUNC('quarter', snapshot_date) ), quarter_aum AS ( SELECT l.quarter, SUM(ABS(p.amount)) AS quarter_end_aum FROM wealth_pulse_insigneo_model.gold.positions p JOIN latest_snapshot_per_quarter l ON p.snapshot_date = l.snapshot_date GROUP BY l.quarter ), ranked_trades AS ( SELECT *, ROW_NUMBER() OVER ( PARTITION BY trade_id ORDER BY CASE workflow_status WHEN 'Reconciled' THEN 2 WHEN 'Confirmed' THEN 1 ELSE 0 END DESC, load_time DESC ) AS rn FROM wealth_pulse_insigneo_model.silver.transaction_blotter WHERE workflow_status IN ('Confirmed', 'Reconciled') ), quarter_revenue AS ( SELECT DATE_TRUNC('quarter', broker_month) AS quarter, SUM(gross_comm) AS total_revenue FROM ranked_trades WHERE rn = 1 GROUP BY DATE_TRUNC('quarter', broker_month) ) SELECT r.quarter, r.total_revenue, a.quarter_end_aum, ROUND( (r.total_revenue / NULLIF(a.quarter_end_aum, 0)) * 10000, 2 ) AS fee_rate_bps FROM quarter_revenue r LEFT JOIN quarter_aum a ON r.quarter = a.quarter ORDER BY r.quarter;
A3: Leadership | B3: Firm Dashboard (Leadership Home) | C3: KPI | D3: Firm AUM | E3: Total active client assets + Growth % | F3: SUM(fact_position.market_value) | G3: Done | I3: KPI-001 | J3: SELECT SUM(p.amount) AS total_aum FROM positions p JOIN financial_account a ON p.financial_account_id = a.financial_account_id WHERE p.snapshot_date BETWEEN DATEADD(DAY, 1 - DATEPART(WEEKDAY, '2026-01-01'), '2026-01-01') AND DATEADD(DAY, 7 - DATEPART(WEEKDAY, '2026-01-01'), '2026-01-01') AND a.account_status_indicator = 'O' AND a.is_active = 1 | K3: Done | L3: 1 - Done | M3: Category: Done. Total AUM logic updated in DB. | N3: Yes
A4: Leadership | B4: Firm Dashboard (Leadership Home) | C4: KPI | D4: Organic Growth Rate | E4: (NNA / Beginning AUM) × annualization; vs target % | F4: fact_transaction + fact_position | G4: Done | I4: KPI-019 | J4: WITH latest_snapshot AS ( SELECT MAX(snapshot_date) AS end_date FROM wealth_pulse_insigneo_model.gold.positions ), beginning_snapshot AS ( SELECT MAX(snapshot_date) AS start_date FROM wealth_pulse_insigneo_model.gold.positions WHERE snapshot_date < ( SELECT DATE_TRUNC('year', end_date) FROM latest_snapshot ) ), beginning_aum AS ( SELECT SUM(p.amount) AS beginning_aum FROM wealth_pulse_insigneo_model.gold.positions p JOIN wealth_pulse_insigneo_model.gold.financial_account fa ON p.financial_account_id = fa.financial_account_id WHERE p.snapshot_date = ( SELECT snapshot_date FROM beginning_snapshot ) AND fa.account_status_indicator = 'O' AND fa.is_active = 1 ), net_new_assets AS ( SELECT SUM( CASE WHEN t.transaction_code IN ('CONTRIBUTION','TRANSFER_IN','RFF','CSR') THEN ABS(t.amount) ELSE 0 END ) - SUM( CASE WHEN t.transaction_code IN ('DISTRIBUTION','TRANSFER_OUT','SFF','PCC') THEN ABS(t.amount) ELSE 0 END ) AS nna FROM wealth_pulse_insigneo_model.gold.transactions t JOIN wealth_pulse_insigneo_model.gold.financial_account fa ON t.financial_account_id = fa.financial_account_id CROSS JOIN latest_snapshot ls CROSS JOIN beginning_snapshot bs WHERE CAST(t.transaction_date AS DATE) BETWEEN bs.start_date AND ls.end_date AND fa.account_status_indicator = 'O' AND fa.is_active = 1 ) SELECT ROUND(nna.nna,2) AS net_new_assets, ROUND(ba.beginning_aum,2) AS beginning_aum, ROUND( ( nna.nna / NULLIF(ba.beginning_aum,0) ) * (12.0 / MONTH(ls.end_date)) * 100, 2 ) AS organic_growth_rate FROM net_new_assets nna CROSS JOIN beginning_aum ba CROSS JOIN latest_snapshot ls; | K4: Done | L4: 1 - Done | M4: Category: Done. Organic Growth updated in DB. | N4: Yes
A5: Leadership | B5: Advisor Intelligence Dashboard (Leadership View) | C5: Chart | D5: Metric Comparison - NNM Goal % | E5: Horizontal bar per advisor (TBD target) | F5: NNM Achieved/Target | G5: TBD data | H5: Goal % not available | I5: - | J5: - | K5: Data Not Available | L5: Phase 3 Cannot be Achieable | M5: Category: Data Not Available. NNM Goal % - target not available (backend config missing). | P5: Partially achieved not sure of goal %
A6: Leadership | B6: Firm Dashboard (Leadership Home) | C6: KPI | D6: Client Retention | E6: (Beginning AUM - Outflows)/Beginning AUM; assets departed, alert badge | F6: fact_position + fact_transaction | G6: Done | I6: KPI-020 | J6: WITH latest_snapshot AS ( SELECT MAX(snapshot_date) AS end_date FROM wealth_pulse_insigneo_model.gold.positions ), beginning_snapshot AS ( SELECT MAX(snapshot_date) AS start_date FROM wealth_pulse_insigneo_model.gold.positions WHERE snapshot_date < ( SELECT DATE_TRUNC('quarter', end_date) FROM latest_snapshot ) ), beginning_aum AS ( SELECT SUM(p.amount) AS beginning_aum FROM wealth_pulse_insigneo_model.gold.positions p JOIN wealth_pulse_insigneo_model.gold.financial_account fa ON p.financial_account_id = fa.financial_account_id CROSS JOIN beginning_snapshot bs WHERE p.snapshot_date = bs.start_date AND fa.account_status_indicator = 'O' AND fa.is_active = 1 ), outflows AS ( SELECT SUM(ABS(t.amount)) AS outflow_amount FROM wealth_pulse_insigneo_model.gold.transactions t JOIN wealth_pulse_insigneo_model.gold.financial_account fa ON t.financial_account_id = fa.financial_account_id CROSS JOIN latest_snapshot ls CROSS JOIN beginning_snapshot bs WHERE CAST(t.transaction_date AS DATE) BETWEEN bs.start_date AND ls.end_date AND t.transaction_code IN ( 'DISTRIBUTION', 'TRANSFER_OUT', 'SFF', 'PCC' ) AND fa.account_status_indicator = 'O' AND fa.is_active = 1 ) SELECT ROUND(ba.beginning_aum,2) AS beginning_aum, ROUND(COALESCE(o.outflow_amount,0),2) AS outflows, ROUND( ( ba.beginning_aum - COALESCE(o.outflow_amount,0) ) / NULLIF(ba.beginning_aum,0) * 100, 2 ) AS client_retention_rate FROM beginning_aum ba CROSS JOIN outflows o; | K6: Done | L6: 1 - Done | M6: Category: Done. Client Retention updated in DB. | N6: Yes
A7: Leadership | B7: Firm Dashboard (Leadership Home) | C7: Chart | D7: Firm AUM Growth Chart | E7: Monthly AUM trend for the year (all months on X-axis) | F7: SUM(market_value) GROUP BY month | G7: Done | I7: CHART-001 | J7: SELECT DATEFROMPARTS(YEAR(snapshot_date), MONTH(snapshot_date), 1) AS [month], SUM(amount) AS total_monthly_aum FROM positions WHERE snapshot_date >= DATEADD( MONTH, -23, DATEFROMPARTS(YEAR(GETDATE()), MONTH(GETDATE()), 1) ) GROUP BY DATEFROMPARTS(YEAR(snapshot_date), MONTH(snapshot_date), 1) ORDER BY [month]; | K7: Done | L7: 1 - Done | M7: Category: Done. 24-month AUM trend; validate window vs Insigneo (flagged 'Doubt'). | N7: Yes
A8: Leadership | B8: Advisor Intelligence Dashboard (Leadership View) | C8: Chart | D8: Metric Comparison - Satisfaction | E8: Horizontal bar per advisor (0-5) | F8: AVG satisfaction / proxy | G8: TBD data | H8: Satisfaction matric not available | I8: TABLE-LD-ADV-08 | J8: - | K8: Data Not Available | L8: Phase 3 Cannot be Achieable | M8: Category: Data Not Available. Satisfaction comparison bar - data not available. | P8: reference query Not available
A9: Leadership | B9: Firm Dashboard (Leadership Home) | C9: Chart | D9: Retention Trend Chart | E9: Retention % per quarter, current quarter highlighted | F9: (Beginning AUM-Outflows)/Beginning AUM | G9: Done | I9: KPI-020 | J9: - | K9: Done | L9: 1 - Done | M9: Category: Done. Quarterly retention trend updated in DB. | N9: Yes | P9: Query tobe shared
A10: Advisor | B10: Advisor Home Dashboard | C10: Chart | D10: Allocation vs Target Analytics | E10: Current vs target allocation by asset class + over/under indicators | F10: asset class value/AUM vs model | G10: Done | H10: dim_model_portfolio | I10: CHART-006 | J10: WITH latest_snapshot AS ( SELECT MAX(snapshot_date) AS snapshot_date FROM wealth_pulse_insigneo_model.gold.positions ), current_allocation AS ( SELECT s.asset_class, SUM(ABS(p.amount)) AS market_value FROM wealth_pulse_insigneo_model.gold.positions p INNER JOIN wealth_pulse_insigneo_model.gold.securities s ON p.cusip = s.cusip AND s.is_active = 1 JOIN wealth_pulse_insigneo_model.gold.financial_account f ON f.financial_account_id = p.financial_account_id AND f.is_active = 1 AND f.account_status_indicator = 'O' CROSS JOIN latest_snapshot ls WHERE p.snapshot_date = ls.snapshot_date GROUP BY s.asset_class ), total_mv AS ( SELECT SUM(market_value) AS total_market_value FROM current_allocation ), model_target AS ( SELECT SUM(d.target_equity_pct * d.total_aum_in_model) / NULLIF(SUM(d.total_aum_in_model),0) AS target_equity_pct, SUM(d.target_fi_pct * d.total_aum_in_model) / NULLIF(SUM(d.total_aum_in_model),0) AS target_fi_pct, SUM(d.target_alt_pct * d.total_aum_in_model) / NULLIF(SUM(d.total_aum_in_model),0) AS target_alt_pct, SUM(d.target_cash_pct * d.total_aum_in_model) / NULLIF(SUM(d.total_aum_in_model),0) AS target_cash_pct FROM wealth_pulse_insigneo_model.silver.account_model_mapping amm INNER JOIN wealth_pulse_insigneo_model.gold.dim_model_portfolio d ON amm.model_id = d.model_id ) SELECT ca.asset_class, ROUND( (ca.market_value / tm.total_market_value) * 100, 2 ) AS current_pct, CASE WHEN ca.asset_class = 'Equity' THEN mt.target_equity_pct WHEN ca.asset_class = 'Fixed Income' THEN mt.target_fi_pct WHEN ca.asset_class = 'Alternative Investments' THEN mt.target_alt_pct WHEN ca.asset_class = 'Cash & Cash Equivalent' THEN mt.target_cash_pct ELSE 0 END AS target_pct FROM current_allocation ca CROSS JOIN total_mv tm CROSS JOIN model_target mt ORDER BY current_pct DESC; | K10: Data Not Available | L10: Phase 3 WIP | M10: Category: Data Not Available. Allocation-vs-Target - needs model target allocation, not in Insigneo.
A11: Leadership | B11: Firm Dashboard (Leadership Home) | C11: Panel | D11: Firm AUM Drilldown | E11: Top 5 advisor AUM, avg AUM/advisor, avg HH/advisor, NNA QTD, Market appreciation QTD | F11: On-click drilldown | G11: Done | I11: KPI-054 | J11: SELECT SUM(p.amount) / NULLIF(COUNT(DISTINCT a.investment_professional_number), 0) AS aum_per_advisor FROM positions p JOIN financial_account a ON p.financial_account_id = a.financial_account_id WHERE CAST(p.snapshot_date AS DATE) BETWEEN DATEADD(DAY, 1 - DATEPART(WEEKDAY, '2026-01-01'), '2026-01-01') AND DATEADD(DAY, 7 - DATEPART(WEEKDAY, '2026-01-01'), '2026-01-01') AND a.account_status_indicator = 'O' AND a.is_active = 1 | K11: Done | L11: 1 - Done | M11: Category: Done. Drilldown metrics (avg AUM/HH per advisor, NNA, market appreciation) updated in DB.
A12: Leadership | B12: Firm Dashboard (Leadership Home) | C12: Panel | D12: Retention Drilldown | E12: Assets departed, households departed, revenue lost, advisor-wise attrition | F12: On-click drilldown | G12: Done | I12: KPI-065 | J12: WITH latest_snapshot AS ( SELECT MAX(snapshot_date) AS end_date FROM wealth_pulse_insigneo_model.gold.positions ), beginning_snapshot AS ( SELECT MAX(snapshot_date) AS start_date FROM wealth_pulse_insigneo_model.gold.positions WHERE snapshot_date < (SELECT DATE_TRUNC('year', end_date) FROM latest_snapshot) ), departed_households AS ( SELECT * FROM ( SELECT hd.house_hold_name, fa.investment_professional_number, MAX(fa.date_account_closed) AS close_date, COUNT( CASE WHEN fa.account_status_indicator <> 'C' THEN 1 END ) AS open_accounts FROM wealth_pulse_insigneo_model.gold.household_details hd JOIN wealth_pulse_insigneo_model.gold.financial_account fa ON hd.financial_account_id = fa.financial_account_id WHERE fa.is_active = 1 GROUP BY hd.house_hold_name, fa.investment_professional_number ) x CROSS JOIN latest_snapshot ls CROSS JOIN beginning_snapshot bs WHERE open_accounts = 0 AND close_date BETWEEN bs.start_date AND ls.end_date ), last_snapshot AS ( SELECT dh.house_hold_name, MAX(p.snapshot_date) AS snapshot_date FROM departed_households dh JOIN wealth_pulse_insigneo_model.gold.household_details hd ON dh.house_hold_name = hd.house_hold_name JOIN wealth_pulse_insigneo_model.gold.positions p ON hd.financial_account_id = p.financial_account_id WHERE p.snapshot_date < CAST(dh.close_date AS DATE) GROUP BY dh.house_hold_name ), household_aum AS ( SELECT dh.investment_professional_number, dh.house_hold_name, SUM(p.amount) AS aum_lost FROM departed_households dh JOIN last_snapshot ls ON dh.house_hold_name = ls.house_hold_name JOIN wealth_pulse_insigneo_model.gold.household_details hd ON dh.house_hold_name = hd.house_hold_name JOIN wealth_pulse_insigneo_model.gold.positions p ON hd.financial_account_id = p.financial_account_id AND p.snapshot_date = ls.snapshot_date GROUP BY dh.investment_professional_number, dh.house_hold_name ) SELECT investment_professional_number AS advisor, COUNT(*) AS hh_departed, ROUND(SUM(aum_lost),2) AS aum_lost FROM household_aum GROUP BY investment_professional_number ORDER BY aum_lost DESC; | K12: Done | L12: 1 - Done | M12: Category: Done. Assets/HH departed & revenue-lost updated in DB.
A13: Leadership | B13: Advisor Intelligence Dashboard (Leadership View) | C13: KPI | D13: Top AUM Growth | E13: Advisor with highest AUM growth % (name, current AUM) | F13: KPI-058 Advisor Growth Rate | G13: Done | I13: KPI-058 | J13: WITH snapshot_refs AS ( SELECT ( SELECT MAX(snapshot_date) FROM wealth_pulse_insigneo_model.gold.positions ) AS current_snapshot, ( SELECT MAX(snapshot_date) FROM wealth_pulse_insigneo_model.gold.positions WHERE snapshot_date <= ADD_MONTHS( ( SELECT MAX(snapshot_date) FROM wealth_pulse_insigneo_model.gold.positions ), -12 ) ) AS prior_snapshot ), current_aum AS ( SELECT fa.investment_professional_number, SUM(p.amount) AS current_aum FROM wealth_pulse_insigneo_model.gold.positions p JOIN wealth_pulse_insigneo_model.gold.financial_account fa ON p.financial_account_id = fa.financial_account_id CROSS JOIN snapshot_refs s WHERE p.snapshot_date = s.current_snapshot AND fa.account_status_indicator = 'O' AND fa.is_active = 1 GROUP BY fa.investment_professional_number ), prior_aum AS ( SELECT fa.investment_professional_number, SUM(p.amount) AS prior_aum FROM wealth_pulse_insigneo_model.gold.positions p JOIN wealth_pulse_insigneo_model.gold.financial_account fa ON p.financial_account_id = fa.financial_account_id CROSS JOIN snapshot_refs s WHERE p.snapshot_date = s.prior_snapshot AND fa.account_status_indicator = 'O' AND fa.is_active = 1 GROUP BY fa.investment_professional_number ), advisor_growth AS ( SELECT c.investment_professional_number, c.current_aum, COALESCE(p.prior_aum,0) AS prior_aum, ROUND( ( (c.current_aum - p.prior_aum) / NULLIF(p.prior_aum,0) ) * 100, 2 ) AS growth_pct FROM current_aum c LEFT JOIN prior_aum p ON c.investment_professional_number = p.investment_professional_number ) SELECT fa.rep_id AS advisor_id, fa.record_assigned_name AS advisor_name, ROUND(ag.current_aum,2) AS current_aum, ag.growth_pct FROM advisor_growth ag JOIN wealth_pulse_insigneo_model.gold.financial_advisor fa ON ag.investment_professional_number = fa.rep_id ORDER BY growth_pct DESC, current_aum DESC LIMIT 1; | K13: Done | L13: 1 - Done | M13: Category: Done. Top AUM Growth card updated in DB.
A14: Leadership | B14: Advisor Intelligence Dashboard (Leadership View) | C14: KPI | D14: Most Net New Money | E14: Advisor with highest inflow; % vs target | F14: KPI-016 Net New Assets | G14: Done | I14: KPI-016 | J14: WITH latest_snapshot AS ( SELECT MAX(snapshot_date) AS end_date FROM wealth_pulse_insigneo_model.gold.positions ), date_filter AS ( SELECT end_date, DATE_TRUNC('year', end_date) AS start_date FROM latest_snapshot ), advisor_nnm AS ( SELECT fa.investment_professional_number, SUM( CASE WHEN t.transaction_code IN ('CONTRIBUTION','TRANSFER_IN','RFF','CSR') THEN ABS(t.amount) ELSE 0 END ) - SUM( CASE WHEN t.transaction_code IN ('DISTRIBUTION','TRANSFER_OUT','SFF','PCC') THEN ABS(t.amount) ELSE 0 END ) AS net_new_money FROM wealth_pulse_insigneo_model.gold.transactions t INNER JOIN wealth_pulse_insigneo_model.gold.financial_account fa ON t.financial_account_id = fa.financial_account_id WHERE CAST(t.transaction_date AS DATE) BETWEEN (SELECT start_date FROM date_filter) AND (SELECT end_date FROM date_filter) AND fa.account_status_indicator = 'O' AND fa.is_active = 1 GROUP BY fa.investment_professional_number ), advisor_aum AS ( SELECT p.investment_professional_number, SUM(p.amount) AS current_aum FROM wealth_pulse_insigneo_model.gold.positions p WHERE p.snapshot_date = ( SELECT end_date FROM latest_snapshot ) GROUP BY p.investment_professional_number ) SELECT fa.rep_id as investment_professional_number, fa.record_assigned_name as advisor_name, ROUND(n.net_new_money,2) AS net_new_money, ROUND(a.current_aum,2) AS current_aum, ROUND( CASE WHEN a.current_aum > 0 THEN (n.net_new_money / a.current_aum) * 100 ELSE 0 END, 2 ) AS net_new_money_pct FROM advisor_nnm n JOIN advisor_aum a ON n.investment_professional_number = a.investment_professional_number JOIN wealth_pulse_insigneo_model.gold.financial_advisor fa ON n.investment_professional_number = fa.rep_id ORDER BY net_new_money_pct DESC, current_aum DESC LIMIT 1; | K14: Done | L14: 1 - Done | M14: Category: Done. Most Net New Money updated in DB.
A15: Leadership | B15: Advisor Intelligence Dashboard (Leadership View) | C15: KPI | D15: Best Client Retention | E15: Advisor retaining highest client assets (trailing 12M) | F15: KPI-020 Client Retention Rate | G15: Done | I15: KPI-020 | J15: - | K15: Done | L15: 1 - Done | M15: Category: Done. Best Client Retention updated in DB. | N15: Yes | P15: Query tobe shared
A16: Advisor | B16: Household Management Dashboard | C16: Chart | D16: AUM by Segment | E16: AUM split UHNW / HNW / Mass Affluent (% contribution) | F16: segment_override else segment | G16: Done | H16: person_account, categorize it based on the net_worth | I16: KPI-069 | J16: WITH client_segment AS ( SELECT DISTINCT pfm.financial_account_id, CASE WHEN pa.entity_name IS NOT NULL AND TRIM(pa.entity_name) <> '' THEN 'Corporate' WHEN pa.maximum_net_worth >= 1000000 THEN 'HNW' WHEN pa.maximum_net_worth >= 10000000 THEN 'UHNW' WHEN pa.maximum_net_worth IS NOT NULL THEN 'Mass Affluent' WHEN pa.maximum_annual_income >= 1000000 THEN 'UHNW (Estimated)' WHEN pa.maximum_annual_income >= 250000 THEN 'HNW (Estimated)' ELSE 'Mass Affluent' END AS client_segment FROM wealth_pulse_insigneo_model.gold.person_financial_mapping pfm JOIN wealth_pulse_insigneo_model.gold.person_account pa ON pfm.person_account_id = pa.person_account_id ) SELECT cs.client_segment, ROUND(SUM(p.amount), 2) AS total_aum FROM wealth_pulse_insigneo_model.gold.positions p INNER JOIN wealth_pulse_insigneo_model.gold.financial_account fa ON p.financial_account_id = fa.financial_account_id AND fa.is_active = 1 LEFT JOIN client_segment cs ON p.financial_account_id = cs.financial_account_id WHERE p.snapshot_date = ( SELECT MAX(snapshot_date) AS snapshot_date FROM wealth_pulse_insigneo_model.gold.positions ) AND fa.account_status_indicator = 'O' GROUP BY cs.client_segment | K16: Data Not Available | L16: Phase 3 WIP | M16: Category: Data Not Available. AUM by Segment - client segment not in Insigneo.
A17: Leadership | B17: Advisor Intelligence Dashboard (Leadership View) | C17: Chart | D17: AUM Trend by Advisor | E17: Multi-line chart, one line per advisor, monthly; top 5 default | F17: SUM(market_value) GROUP BY advisor_id, month | G17: Done | I17: CHART-021 | J17: WITH latest_snapshot AS ( SELECT MAX(snapshot_date) AS max_snapshot_date FROM wealth_pulse_insigneo_model.gold.positions ), monthly_last_snapshot AS ( SELECT DATE(date_trunc('month', p.snapshot_date)) AS month, MAX(p.snapshot_date) AS last_snapshot_date FROM wealth_pulse_insigneo_model.gold.positions p CROSS JOIN latest_snapshot l WHERE p.snapshot_date >= add_months( DATE(date_trunc('month', l.max_snapshot_date)), -11 ) GROUP BY DATE(date_trunc('month', p.snapshot_date)) ) SELECT m.month, fp.investment_professional_number, SUM(ABS(fp.amount)) AS aum FROM monthly_last_snapshot m JOIN wealth_pulse_insigneo_model.gold.positions fp ON fp.snapshot_date = m.last_snapshot_date JOIN wealth_pulse_insigneo_model.gold.financial_account f ON fp.financial_account_id = f.financial_account_id WHERE f.account_status_indicator = 'O' AND f.is_active = 1 GROUP BY m.month, fp.investment_professional_number ORDER BY fp.investment_professional_number, m.month, aum DESC; | K17: Done | L17: 1 - Done | M17: Category: Done. AUM trend by advisor; validate vs Insigneo (flagged 'Doubt').
A18: Leadership | B18: Advisor Intelligence Dashboard (Leadership View) | C18: Chart | D18: Metric Comparison - YTD Growth % | E18: Horizontal bar per advisor | F18: KPI-058 | G18: Done | I18: KPI-058 | J18: WITH current_aum AS ( SELECT a.investment_professional_number, SUM(p.amount) AS aum FROM positions p JOIN financial_account a ON p.financial_account_id = a.financial_account_id WHERE CAST(p.snapshot_date AS DATE) BETWEEN DATEADD(DAY, 1 - DATEPART(WEEKDAY, '2026-01-01'), '2026-01-01') AND DATEADD(DAY, 7 - DATEPART(WEEKDAY, '2026-01-01'), '2026-01-01') AND a.account_status_indicator = 'O' AND a.is_active = 1 GROUP BY a.investment_professional_number ), prior_aum AS ( SELECT a.investment_professional_number, SUM(p.amount) AS aum FROM positions p JOIN financial_account a ON p.financial_account_id = a.financial_account_id WHERE CAST(p.snapshot_date AS DATE) BETWEEN DATEADD(YEAR, -1, DATEADD(DAY, 1 - DATEPART(WEEKDAY, '2026-01-01'), '2026-01-01')) AND DATEADD(YEAR, -1, DATEADD(DAY, 7 - DATEPART(WEEKDAY, '2026-01-01'), '2026-01-01')) AND a.account_status_indicator = 'O' AND a.is_active = 1 GROUP BY a.investment_professional_number ) SELECT c.investment_professional_number, (c.aum - COALESCE(pr.aum, 0)) / NULLIF(pr.aum, 0) * 100 AS growth_rate FROM current_aum c LEFT JOIN prior_aum pr ON c.investment_professional_number = pr.investment_professional_number | K18: Done | L18: 1 - Done | M18: Category: Done. YTD Growth comparison bar updated in DB.
A19: Leadership | B19: Advisor Intelligence Dashboard (Leadership View) | C19: Chart | D19: Metric Comparison - Retention % | E19: Horizontal bar per advisor | F19: KPI-020 | G19: Done | I19: KPI-020 | J19: - | K19: Done | L19: 1 - Done | M19: Category: Done. Retention comparison bar updated in DB. | N19: Yes | P19: Query tobe shared
A20: Advisor | B20: Household Management Dashboard | C20: Chart | D20: Household Count by Segment | E20: Household count per segment | F20: grouped count by segment | G20: Done | H20: person_Account->financial_account->household | I20: KPI-069 | J20: WITH latest_snapshot AS ( SELECT MAX(snapshot_date) AS snapshot_date FROM wealth_pulse_insigneo_model.gold.positions ), client_segment AS ( SELECT t.house_hold_name, CASE WHEN MAX( CASE WHEN t.entity_name IS NOT NULL AND TRIM(t.entity_name) <> '' THEN 1 ELSE 0 END ) = 1 THEN 'Corporate' WHEN SUM(t.maximum_net_worth) >= 10000000 THEN 'UHNW' WHEN SUM(t.maximum_net_worth) >= 1000000 THEN 'HNW' WHEN SUM(t.maximum_net_worth) IS NOT NULL THEN 'Mass Affluent' WHEN SUM(t.maximum_annual_income) >= 1000000 THEN 'UHNW (Estimated)' WHEN SUM(t.maximum_annual_income) >= 250000 THEN 'HNW (Estimated)' ELSE 'Mass Affluent' END AS client_segment FROM ( SELECT DISTINCT hd.house_hold_name, pa.person_account_id, pa.entity_name, pa.maximum_net_worth, pa.maximum_annual_income FROM wealth_pulse_insigneo_model.gold.positions p JOIN wealth_pulse_insigneo_model.gold.household_details hd ON p.financial_account_id = hd.financial_account_id JOIN wealth_pulse_insigneo_model.gold.person_financial_mapping pfm ON p.financial_account_id = pfm.financial_account_id JOIN wealth_pulse_insigneo_model.gold.person_account pa ON pfm.person_account_id = pa.person_account_id JOIN wealth_pulse_insigneo_model.gold.financial_account fa ON p.financial_account_id = fa.financial_account_id WHERE p.snapshot_date = ( SELECT snapshot_date FROM latest_snapshot ) AND fa.account_status_indicator = 'O' AND fa.is_active = 1 ) t GROUP BY t.house_hold_name ), household_aum AS ( SELECT hd.house_hold_name, SUM(p.amount) AS household_aum FROM wealth_pulse_insigneo_model.gold.positions p JOIN wealth_pulse_insigneo_model.gold.household_details hd ON p.financial_account_id = hd.financial_account_id JOIN wealth_pulse_insigneo_model.gold.financial_account fa ON p.financial_account_id = fa.financial_account_id WHERE p.snapshot_date = ( SELECT snapshot_date FROM latest_snapshot ) AND fa.account_status_indicator = 'O' AND fa.is_active = 1 GROUP BY hd.house_hold_name ) SELECT cs.client_segment, COUNT(DISTINCT ha.house_hold_name) AS household_count, ROUND(SUM(ha.household_aum),2) AS aum, ROUND( SUM(ha.household_aum) * 100.0 / SUM(SUM(ha.household_aum)) OVER (), 2 ) AS segment_aum_pct FROM household_aum ha JOIN client_segment cs ON ha.house_hold_name = cs.house_hold_name GROUP BY cs.client_segment ORDER BY aum DESC; | K20: Data Not Available | L20: Phase 3 WIP | M20: Category: Data Not Available. Household Count by Segment - client segment not in Insigneo.
A21: Advisor | B21: Portfolio Analytics Dashboard | C21: Chart | D21: Sector Exposure - Equity Only (CHART-009) | E21: Horizontal bars, sector % of equity AUM, sorted desc | F21: fact_position equity assets | G21: Done | H21: gold-securities after data dump | I21: CHART-009 | J21: WITH latest_snapshot AS ( SELECT MAX(snapshot_date) AS snapshot_date FROM wealth_pulse_insigneo_model.gold.positions ) SELECT s.sector, ROUND( SUM(ABS(p.amount)) * 100.0 / NULLIF(SUM(SUM(ABS(p.amount))) OVER (), 0), 1 ) AS pct FROM wealth_pulse_insigneo_model.gold.positions p JOIN wealth_pulse_insigneo_model.gold.household_details hd ON p.financial_account_id = hd.financial_account_id JOIN wealth_pulse_insigneo_model.gold.financial_account fa ON p.financial_account_id = fa.financial_account_id JOIN wealth_pulse_insigneo_model.gold.securities s ON p.cusip = s.cusip WHERE hd.house_hold_name = 'AURORA' AND p.snapshot_date = ( SELECT snapshot_date FROM latest_snapshot ) AND fa.account_status_indicator = 'O' AND fa.is_active = 1 AND s.asset_class = 'Equity' AND s.sector IS NOT NULL GROUP BY s.sector ORDER BY pct DESC; | K21: Data Not Available | L21: Phase 3 Done | M21: Category: Data Not Available. Sector Exposure - security sector not in Insigneo.
A22: Leadership | B22: Firm Dashboard (Leadership Home) | C22: KPI | D22: Firm Health (composite) | E22: Growth %, Advisor Performance %, Revenue, Retention combined health view | F22: Derived from Organic Growth / Revenue / Retention KPIs | G22: Done | H22: previous KPIs | I22: CHART-003 | J22: WITH latest_snapshot AS ( SELECT MAX(snapshot_date) AS max_snapshot_date FROM wealth_pulse_insigneo_model.gold.positions ), /* Organic Growth Rate - Beginning AUM */ beg AS ( SELECT SUM(p.amount) AS beg_aum FROM wealth_pulse_insigneo_model.gold.positions p JOIN wealth_pulse_insigneo_model.gold.financial_account a ON p.financial_account_id = a.financial_account_id CROSS JOIN latest_snapshot l WHERE p.snapshot_date = ( SELECT MAX(snapshot_date) FROM wealth_pulse_insigneo_model.gold.positions WHERE snapshot_date < DATE_TRUNC( 'year', l.max_snapshot_date ) ) AND a.account_status_indicator = 'O' AND a.is_active = 1 ), /* Organic Growth Rate - NNA YTD */ nna AS ( SELECT SUM( CASE WHEN t.transaction_code IN ('CONTRIBUTION','TRANSFER_IN','RFF','CSR') THEN ABS(t.amount) ELSE 0 END ) - SUM( CASE WHEN t.transaction_code IN ('DISTRIBUTION','TRANSFER_OUT','SFF','PCC') THEN ABS(t.amount) ELSE 0 END ) AS nna FROM wealth_pulse_insigneo_model.gold.transactions t CROSS JOIN latest_snapshot l WHERE CAST(t.transaction_date AS DATE) BETWEEN DATE_TRUNC('year', l.max_snapshot_date) AND l.max_snapshot_date ), elapsed_months AS ( SELECT MONTH(max_snapshot_date) AS months_elapsed FROM latest_snapshot ), organic_growth AS ( SELECT ( nna.nna / NULLIF(beg.beg_aum,0) ) * ( 12.0 / elapsed_months.months_elapsed ) * 100 AS organic_growth_rate FROM beg CROSS JOIN nna CROSS JOIN elapsed_months ), /* Ring 2 - % Advisors with Positive NNA */ advisor_nna AS ( SELECT a.investment_professional_number, SUM( CASE WHEN t.transaction_code IN ('CONTRIBUTION','TRANSFER_IN','RFF','CSR') THEN ABS(t.amount) ELSE 0 END ) - SUM( CASE WHEN t.transaction_code IN ('DISTRIBUTION','TRANSFER_OUT','SFF','PCC') THEN ABS(t.amount) ELSE 0 END ) AS advisor_nna FROM wealth_pulse_insigneo_model.gold.transactions t JOIN wealth_pulse_insigneo_model.gold.financial_account a ON t.financial_account_id = a.financial_account_id CROSS JOIN latest_snapshot l WHERE CAST(t.transaction_date AS DATE) BETWEEN DATE_TRUNC('year', l.max_snapshot_date) AND l.max_snapshot_date GROUP BY a.investment_professional_number ), positive_nna_advisors AS ( SELECT COUNT( CASE WHEN advisor_nna > 0 THEN 1 END ) * 100.0 / NULLIF(COUNT(*),0) AS pct_advisors_positive FROM advisor_nna ), /* Ring 3 - Revenue Run Rate */ revenue_run_rate AS ( SELECT SUM(fc.gross_comm) * 4.0 AS annualized_revenue FROM wealth_pulse_insigneo_model.gold.fa_commission fc CROSS JOIN latest_snapshot l WHERE fc.broker_month >= DATE_TRUNC( 'quarter', l.max_snapshot_date ) AND fc.broker_month <= l.max_snapshot_date ), /* Ring 4 - Client Retention */ client_retention AS ( SELECT f.investment_professional_number, COUNT(DISTINCT h.house_hold_name) AS household_count, COUNT( DISTINCT CASE WHEN f.account_status_indicator = 'O' THEN f.financial_account_id END ) * 100.0 / NULLIF( COUNT(DISTINCT f.financial_account_id), 0 ) AS retention_pct FROM wealth_pulse_insigneo_model.gold.household_details h JOIN wealth_pulse_insigneo_model.gold.financial_account f ON f.financial_account_id = h.financial_account_id WHERE f.is_active = 1 GROUP BY f.investment_professional_number ) SELECT og.organic_growth_rate, p.pct_advisors_positive, r.annualized_revenue, c.retention_pct FROM organic_growth og CROSS JOIN positive_nna_advisors p CROSS JOIN revenue_run_rate r CROSS JOIN client_retention c; | K22: Data Not Available | L22: Phase 3 Done | M22: Category: Data Not Available. Firm-Health ring scorecard needs advisor-performance/satisfaction signals; underlying Growth/Revenue/Retention are Done. | N22: Yes
A23: Leadership | B23: Household Insights Dashboard (Leadership View) | C23: KPI | D23: Total Households | E23: Count of unique active households | F23: COUNT DISTINCT household_id | G23: Done | I23: KPI-008 | J23: - | K23: (with new derived table) | L23: 2 - In Progress | M23: Category: (with new derived table). Total Households via new derived table. | N23: Yes
A24: Leadership | B24: Firm Dashboard (Leadership Home) | C24: KPI | D24: Estimated Revenue & Fee Rate | E24: Current revenue, Fee Rate (bps), QoQ change, revenue impact from fee change | F24: fact_billing_event.net_fee / AUM | G24: Done | H24: chatgpt | I24: KPI-046 | J24: WITH latest_snapshot AS ( SELECT MAX(snapshot_date) AS latest_date FROM wealth_pulse_insigneo_model.gold.positions ), current_year_revenue AS ( SELECT SUM(fc.gross_comm) AS ytd_revenue, MONTH(MAX(fc.broker_month)) AS completed_months FROM wealth_pulse_insigneo_model.gold.fa_commission fc JOIN wealth_pulse_insigneo_model.gold.financial_account fa ON fc.financial_account_id = fa.financial_account_id CROSS JOIN latest_snapshot lm WHERE fc.broker_month BETWEEN DATE_TRUNC('year', lm.latest_date) AND lm.latest_date AND fa.account_status_indicator='O' AND fa.is_active=1 ), previous_year_revenue AS ( SELECT SUM(fc.gross_comm) AS ytd_revenue FROM wealth_pulse_insigneo_model.gold.fa_commission fc JOIN wealth_pulse_insigneo_model.gold.financial_account fa ON fc.financial_account_id = fa.financial_account_id CROSS JOIN current_year_revenue c CROSS JOIN latest_snapshot lm WHERE fc.broker_month BETWEEN ADD_MONTHS( DATE_TRUNC('year', lm.latest_date), -12 ) AND ADD_MONTHS( ADD_MONTHS( DATE_TRUNC('year', lm.latest_date), -12 ), c.completed_months ) - 1 AND fa.account_status_indicator='O' AND fa.is_active=1 ) SELECT ROUND( c.ytd_revenue * 12 / c.completed_months, 2 ) AS estimated_annual_revenue, ROUND( p.ytd_revenue * 12 / c.completed_months, 2 ) AS previous_estimated_revenue, ROUND( ( (c.ytd_revenue * 12 / c.completed_months) - (p.ytd_revenue * 12 / c.completed_months) )/ NULLIF((p.ytd_revenue * 12 / c.completed_months),0) * 100, 2 ) AS yoy_growth_pct FROM current_year_revenue c CROSS JOIN previous_year_revenue p; | K24: (with new derived table) | L24: Phase 3 WIP | M24: Category: (with new derived table). Revenue & fee rate via new derived table; actual revenue (net_fee) available. | N24: R&D | O24: 46225 | P24: confusion on formula , data avaliable however there is an confusion on the right formula.
A25: Leadership | B25: Advisor Intelligence Dashboard (Leadership View) | C25: KPI | D25: Highest Satisfaction | E25: Best client satisfaction score / proxy (TBD - no Insigneo data) | F25: fact_client_360.satisfaction_score / proxy | G25: TBD data | H25: Satisfaction matric not available | I25: TABLE-LD-ADV-08 | J25: - | K25: Data Not Available | L25: Phase 3 Cannot be Achieable | M25: Category: Data Not Available. Highest Satisfaction - no satisfaction data in Insigneo (proxy TBD). | P25: reference query Not available
A26: Leadership | B26: Household Insights Dashboard (Leadership View) | C26: KPI | D26: High Risk Households | E26: Households with Risk Score >= high threshold | F26: Weighted concentration/drift/cash | G26: Done | H26: dim_model_portfolio | I26: KPI-072 | J26: WITH latest_snapshot AS ( SELECT MAX(snapshot_date) AS max_snapshot_date FROM wealth_pulse_insigneo_model.gold.positions ), /* Account level AUM and cash */ account_base AS ( SELECT ac.financial_account_id, ac.account_number, ac.investment_professional_number, h.house_hold_name, ( COALESCE(ac.trade_date_net_worth,0) + COALESCE(ac.cash_available,0) ) AS account_aum, CASE WHEN ( COALESCE(ac.trade_date_net_worth,0) + COALESCE(ac.cash_available,0) ) = 0 THEN 0 ELSE ac.cash_available * 100.0 / ( COALESCE(ac.trade_date_net_worth,0) + COALESCE(ac.cash_available,0) ) END AS cash_pct FROM wealth_pulse_insigneo_model.gold.account_summary ac JOIN wealth_pulse_insigneo_model.gold.household_details h ON ac.financial_account_id = h.financial_account_id ), /* Maximum security concentration per account */ account_concentration AS ( SELECT p.financial_account_id, MAX( ABS(p.amount) *100.0 / NULLIF(ab.account_aum,0) ) AS concentration_pct FROM wealth_pulse_insigneo_model.gold.positions p JOIN account_base ab ON p.financial_account_id = ab.financial_account_id CROSS JOIN latest_snapshot l WHERE p.snapshot_date = l.max_snapshot_date GROUP BY p.financial_account_id ), /* Account model drift */ account_drift AS ( SELECT ab.financial_account_id, ABS( ( ac.total_equity * 100.0 / NULLIF( ( COALESCE(ac.trade_date_net_worth,0) + COALESCE(ac.cash_available,0) ), 0 ) ) - dmp.target_equity_pct ) AS drift_pct FROM account_base ab JOIN wealth_pulse_insigneo_model.gold.account_summary ac ON ab.financial_account_id = ac.financial_account_id JOIN wealth_pulse_insigneo_model.silver.account_model_mapping amm ON ab.account_number = amm.account_number JOIN wealth_pulse_insigneo_model.gold.dim_model_portfolio dmp ON amm.model_id = dmp.model_id ), /* Household weighted risk metrics */ household_risk AS ( SELECT ab.investment_professional_number, ab.house_hold_name, /* Maximum concentration risk */ MAX( COALESCE(cc.concentration_pct,0) ) AS concentration_risk, /* AUM weighted drift */ SUM( COALESCE(ad.drift_pct,0) * ab.account_aum ) / NULLIF( SUM(ab.account_aum), 0 ) AS drift_risk, /* AUM weighted cash */ SUM( ab.cash_pct * ab.account_aum ) / NULLIF( SUM(ab.account_aum), 0 ) AS cash_risk FROM account_base ab LEFT JOIN account_concentration cc ON ab.financial_account_id = cc.financial_account_id LEFT JOIN account_drift ad ON ab.financial_account_id = ad.financial_account_id GROUP BY ab.investment_professional_number, ab.house_hold_name ), /* Calculate household risk score */ household_score AS ( SELECT investment_professional_number, house_hold_name, ( (CASE WHEN concentration_risk > 10 THEN 100 ELSE concentration_risk * 10 END) + (CASE WHEN drift_risk > 8 THEN 100 ELSE drift_risk * 12.5 END) + (CASE WHEN cash_risk > 10 THEN 100 ELSE cash_risk * 10 END) ) / 3 AS risk_score FROM household_risk ) SELECT investment_professional_number AS advisor, COUNT( CASE WHEN risk_score >= 70 THEN 1 END ) AS high_risk_households, COUNT(*) AS total_households, COUNT( CASE WHEN risk_score >= 70 THEN 1 END ) *100.0 / NULLIF(COUNT(*),0) AS high_risk_household_pct FROM household_score GROUP BY investment_professional_number; | K26: Data Not Available | L26: Phase 3 Done | M26: Category: Data Not Available. High Risk Households - needs drift/cost-basis/unrealized/model/engagement signals not in Insigneo.
A27: Leadership | B27: Household Insights Dashboard (Leadership View) | C27: Filter/Control | D27: Search & Filters | E27: Search (household/client), Advisor filter, Risk filter (High/Med/Low) | F27: UI controls | G27: Done | I27: - | J27: - | K27: - | L27: 5 - Insights | M27: Category: -. Search/Advisor filter is UI; Risk filter depends on blocked risk data.
A28: Leadership | B28: Household Insights Dashboard (Leadership View) | C28: KPI | D28: Reviews Overdue | E28: Households past review SLA (TBD data) | F28: Days since last review > cycle | G28: TBD data | H28: days_since_last_meeting not provided | I28: TABLE-LD-HH-06 | J28: - | K28: Data Not Available | L28: Phase 3 Cannot be Achieable | M28: Category: Data Not Available. Reviews Overdue - no client-review data in Insigneo.
A29: Leadership | B29: Household Insights Dashboard (Leadership View) | C29: Panel | D29: Household Detail Side Panel | E29: AUM, YTD Return, Vs Benchmark, Model Drift, Unrealized G/L, Cash Drag, Model Portfolio, Client Retention Risk (TBD), Review Status (TBD) | F29: On-row-click drilldown | G29: Done | I29: KPI-038 | J29: WITH latest_snapshot AS ( SELECT MAX(snapshot_date) AS max_snapshot_date FROM wealth_pulse_insigneo_model.gold.positions ), /* Latest household AUM */ household_aum AS ( SELECT h.house_hold_name, SUM(p.amount) AS aum FROM wealth_pulse_insigneo_model.gold.positions p JOIN wealth_pulse_insigneo_model.gold.household_details h ON p.financial_account_id = h.financial_account_id JOIN wealth_pulse_insigneo_model.gold.financial_account a ON p.financial_account_id = a.financial_account_id CROSS JOIN latest_snapshot l WHERE p.snapshot_date = l.max_snapshot_date AND a.account_status_indicator = 'O' AND a.is_active = 1 GROUP BY h.house_hold_name ), /* Beginning household AUM */ beginning_household_aum AS ( SELECT h.house_hold_name, SUM(p.amount) AS beginning_aum FROM wealth_pulse_insigneo_model.gold.positions p JOIN wealth_pulse_insigneo_model.gold.household_details h ON p.financial_account_id = h.financial_account_id JOIN wealth_pulse_insigneo_model.gold.financial_account a ON p.financial_account_id = a.financial_account_id WHERE p.snapshot_date = ( SELECT MAX(snapshot_date) FROM wealth_pulse_insigneo_model.gold.positions WHERE snapshot_date < DATE_TRUNC( 'year', (SELECT max_snapshot_date FROM latest_snapshot) ) ) AND a.account_status_indicator = 'O' AND a.is_active = 1 GROUP BY h.house_hold_name ), /* Household NNM YTD */ household_nna_ytd AS ( SELECT h.house_hold_name, SUM( CASE WHEN t.transaction_code IN ('CONTRIBUTION','TRANSFER_IN','RFF','CSR') THEN ABS(t.amount) ELSE 0 END ) - SUM( CASE WHEN t.transaction_code IN ('DISTRIBUTION','TRANSFER_OUT','SFF','PCC') THEN ABS(t.amount) ELSE 0 END ) AS nna_ytd FROM wealth_pulse_insigneo_model.gold.transactions t JOIN wealth_pulse_insigneo_model.gold.financial_account fa ON t.financial_account_id = fa.financial_account_id JOIN wealth_pulse_insigneo_model.gold.household_details h ON fa.financial_account_id = h.financial_account_id CROSS JOIN latest_snapshot l WHERE CAST(t.transaction_date AS DATE) BETWEEN DATE_TRUNC('year', l.max_snapshot_date) AND l.max_snapshot_date AND fa.account_status_indicator = 'O' AND fa.is_active = 1 GROUP BY h.house_hold_name ), /* Current Equity % at Account Level */ account_equity AS ( SELECT ac.account_number, ac.financial_account_id, ac.total_equity AS equity_value, ( COALESCE(p.amount,0) + COALESCE(ac.cash_available,0) ) AS total_value, CASE WHEN ( COALESCE(p.amount,0) + COALESCE(ac.cash_available,0) ) = 0 THEN NULL ELSE ac.total_equity * 100.0 / ( COALESCE(p.amount,0) + COALESCE(ac.cash_available,0) ) END AS current_equity_pct FROM wealth_pulse_insigneo_model.gold.positions p JOIN wealth_pulse_insigneo_model.gold.account_summary ac ON p.financial_account_id = ac.financial_account_id JOIN wealth_pulse_insigneo_model.gold.financial_account a ON p.financial_account_id = a.financial_account_id CROSS JOIN latest_snapshot l WHERE p.snapshot_date = l.max_snapshot_date AND a.account_status_indicator = 'O' AND a.is_active = 1 ), /* Drift Per Account */ account_drift AS ( SELECT h.house_hold_name, fa.investment_professional_number, ae.account_number, ae.current_equity_pct, dmp.target_equity_pct, (ae.current_equity_pct - dmp.target_equity_pct) AS drift_pct, ae.total_value FROM account_equity ae JOIN wealth_pulse_insigneo_model.gold.financial_account fa ON ae.financial_account_id = fa.financial_account_id JOIN wealth_pulse_insigneo_model.gold.household_details h ON h.financial_account_id = fa.financial_account_id JOIN wealth_pulse_insigneo_model.silver.account_model_mapping amm ON amm.account_number = ae.account_number JOIN wealth_pulse_insigneo_model.gold.dim_model_portfolio dmp ON dmp.model_id = amm.model_id ), /* Household Drift */ household_drift AS ( SELECT house_hold_name, SUM(drift_pct * total_value) / NULLIF(SUM(total_value),0) AS model_drift FROM account_drift GROUP BY house_hold_name ), household_unrealized_gl AS ( SELECT hd.house_hold_name, SUM(p.amount) - SUM(p.total_cost) AS unrealized_gl FROM wealth_pulse_insigneo_model.gold.positions p JOIN wealth_pulse_insigneo_model.gold.household_details hd ON p.financial_account_id = hd.financial_account_id JOIN wealth_pulse_insigneo_model.gold.financial_account fa ON p.financial_account_id = fa.financial_account_id CROSS JOIN latest_snapshot l WHERE p.snapshot_date = l.max_snapshot_date AND fa.account_status_indicator = 'O' AND fa.is_active = 1 GROUP BY hd.house_hold_name ), household_market_value AS ( SELECT p.financial_account_id, SUM(p.amount) AS market_value FROM wealth_pulse_insigneo_model.gold.positions p CROSS JOIN latest_snapshot l WHERE p.snapshot_date = l.max_snapshot_date GROUP BY p.financial_account_id ), account_cash AS ( SELECT hd.house_hold_name, fa.investment_professional_number, a.financial_account_id, a.cash_available, mv.market_value, a.cash_available / NULLIF(mv.market_value,0) AS cash_pct FROM wealth_pulse_insigneo_model.gold.account_summary a JOIN household_market_value mv ON a.financial_account_id = mv.financial_account_id JOIN wealth_pulse_insigneo_model.gold.household_details hd ON a.financial_account_id = hd.financial_account_id JOIN wealth_pulse_insigneo_model.gold.financial_account fa ON a.financial_account_id = fa.financial_account_id WHERE fa.account_status_indicator='O' AND fa.is_active=1 ), household_cash_drag AS ( SELECT house_hold_name, ROUND( ( AVG(cash_pct) - 0.03 ) * ( 10 --10 - 4.5 --4.5 ) *10000, 2 ) AS cash_drag_bps FROM account_cash WHERE cash_pct > 0.03 GROUP BY house_hold_name ), household_advisors AS ( SELECT hd.house_hold_name, STRING_AGG( DISTINCT fa.rep_id, ', ' ) AS advisor_ids FROM wealth_pulse_insigneo_model.gold.household_details hd JOIN wealth_pulse_insigneo_model.gold.financial_account acc ON hd.financial_account_id = acc.financial_account_id JOIN wealth_pulse_insigneo_model.gold.financial_advisor fa ON acc.investment_professional_number = fa.rep_id WHERE acc.account_status_indicator='O' AND acc.is_active=1 AND fa.is_active=1 GROUP BY hd.house_hold_name ), client_segment AS ( SELECT t.house_hold_name, CASE WHEN MAX( CASE WHEN t.entity_name IS NOT NULL AND TRIM(t.entity_name) <> '' THEN 1 ELSE 0 END ) = 1 THEN 'Corporate' WHEN SUM(t.maximum_net_worth) >= 10000000 THEN 'UHNW' WHEN SUM(t.maximum_net_worth) >= 1000000 THEN 'HNW' WHEN SUM(t.maximum_net_worth) IS NOT NULL THEN 'Mass Affluent' WHEN SUM(t.maximum_annual_income) >= 1000000 THEN 'UHNW (Estimated)' WHEN SUM(t.maximum_annual_income) >= 250000 THEN 'HNW (Estimated)' ELSE 'Mass Affluent' END AS household_segment FROM ( SELECT DISTINCT hd.house_hold_name, pa.person_account_id, pa.entity_name, pa.maximum_net_worth, pa.maximum_annual_income FROM wealth_pulse_insigneo_model.gold.positions p JOIN wealth_pulse_insigneo_model.gold.household_details hd ON p.financial_account_id = hd.financial_account_id JOIN wealth_pulse_insigneo_model.gold.person_financial_mapping pfm ON p.financial_account_id = pfm.financial_account_id JOIN wealth_pulse_insigneo_model.gold.person_account pa ON pfm.person_account_id = pa.person_account_id JOIN wealth_pulse_insigneo_model.gold.financial_account fa ON p.financial_account_id = fa.financial_account_id CROSS JOIN latest_snapshot l WHERE p.snapshot_date = l.max_snapshot_date AND fa.account_status_indicator = 'O' AND fa.is_active = 1 ) t GROUP BY t.house_hold_name ), /* Account level AUM and cash */ account_base AS ( SELECT ac.financial_account_id, ac.account_number, h.house_hold_name, ( COALESCE(p.amount,0) + COALESCE(ac.cash_available,0) ) AS account_aum, CASE WHEN ( COALESCE(p.amount,0) + COALESCE(ac.cash_available,0) ) = 0 THEN 0 ELSE ac.cash_available * 100.0 / ( COALESCE(p.amount,0) + COALESCE(ac.cash_available,0) ) END AS cash_pct FROM wealth_pulse_insigneo_model.gold.positions p JOIN wealth_pulse_insigneo_model.gold.account_summary ac ON ac.financial_account_id = p.financial_account_id JOIN wealth_pulse_insigneo_model.gold.household_details h ON ac.financial_account_id = h.financial_account_id JOIN wealth_pulse_insigneo_model.gold.financial_account fa ON ac.financial_account_id = fa.financial_account_id CROSS JOIN latest_snapshot l WHERE p.snapshot_date = l.max_snapshot_date AND fa.account_status_indicator = 'O' AND fa.is_active = 1 ), /* Maximum security concentration per account */ account_concentration AS ( SELECT p.financial_account_id, MAX( ABS(p.amount) *100.0 / NULLIF(ab.account_aum,0) ) AS concentration_pct FROM wealth_pulse_insigneo_model.gold.positions p JOIN account_base ab ON p.financial_account_id = ab.financial_account_id JOIN wealth_pulse_insigneo_model.gold.financial_account fa ON p.financial_account_id = fa.financial_account_id CROSS JOIN latest_snapshot l WHERE p.snapshot_date = l.max_snapshot_date AND fa.account_status_indicator = 'O' AND fa.is_active = 1 GROUP BY p.financial_account_id ), /* Account model drift */ account_drift1 AS ( SELECT ab.financial_account_id, ABS( ( ac.total_equity * 100.0 / NULLIF( ( COALESCE(p.amount,0) + COALESCE(ac.cash_available,0) ), 0 ) ) - dmp.target_equity_pct ) AS drift_pct FROM wealth_pulse_insigneo_model.gold.positions p JOIN account_base ab ON p.financial_account_id = ab.financial_account_id JOIN wealth_pulse_insigneo_model.gold.account_summary ac ON ab.financial_account_id = ac.financial_account_id JOIN wealth_pulse_insigneo_model.silver.account_model_mapping amm ON ab.account_number = amm.account_number JOIN wealth_pulse_insigneo_model.gold.dim_model_portfolio dmp ON amm.model_id = dmp.model_id CROSS JOIN latest_snapshot l WHERE p.snapshot_date = l.max_snapshot_date ), /* Household weighted risk metrics */ household_risk AS ( SELECT ab.house_hold_name, /* Maximum concentration risk */ MAX( COALESCE(cc.concentration_pct,0) ) AS concentration_risk, /* AUM weighted drift */ SUM( COALESCE(ad.drift_pct,0) * ab.account_aum ) / NULLIF( SUM(ab.account_aum), 0 ) AS drift_risk, /* AUM weighted cash */ SUM( ab.cash_pct * ab.account_aum ) / NULLIF( SUM(ab.account_aum), 0 ) AS cash_risk FROM account_base ab LEFT JOIN account_concentration cc ON ab.financial_account_id = cc.financial_account_id LEFT JOIN account_drift1 ad ON ab.financial_account_id = ad.financial_account_id GROUP BY ab.house_hold_name ), /* Calculate household risk score */ household_score AS ( SELECT house_hold_name, ( (CASE WHEN concentration_risk > 10 THEN 100 ELSE concentration_risk * 10 END) + (CASE WHEN drift_risk > 8 THEN 100 ELSE drift_risk * 12.5 END) + (CASE WHEN cash_risk > 10 THEN 100 ELSE cash_risk * 10 END) ) / 3 AS risk_score FROM household_risk ), household_alerts AS ( SELECT hr.house_hold_name, CASE /* Critical */ WHEN hr.concentration_risk > 10 OR hr.drift_risk > 8 THEN CONCAT( 'CRITICAL - ', CONCAT_WS(', ', CASE WHEN hr.concentration_risk > 10 THEN 'Concentration > 10%' END, CASE WHEN hr.drift_risk > 8 THEN 'Model Drift > 8%' END ) ) /* Warning */ WHEN hr.drift_risk > 4 OR hr.cash_risk > 10 THEN CONCAT( 'WARNING - ', CONCAT_WS(', ', CASE WHEN hr.drift_risk > 4 THEN 'Model Drift > 4%' END, CASE WHEN hr.cash_risk > 10 THEN 'Cash > 10%' END ) ) /* Opportunity */ WHEN ug.unrealized_gl < -5000 THEN 'OPPORTUNITY - Tax Loss Harvesting' ELSE 'NO ALERT' END AS risk_alert, CASE WHEN hr.concentration_risk > 10 OR hr.drift_risk > 8 THEN 'CRITICAL' WHEN hr.drift_risk > 4 OR hr.cash_risk > 10 THEN 'WARNING' WHEN ug.unrealized_gl < -5000 THEN 'OPPORTUNITY' ELSE 'NONE' END AS alert_severity FROM household_risk hr LEFT JOIN household_unrealized_gl ug ON hr.house_hold_name = ug.house_hold_name ), household_risk_level AS ( SELECT hr.house_hold_name, CASE WHEN hr.drift_risk > 4 OR hr.concentration_risk > 25 OR hr.cash_risk > 15 THEN 'high' WHEN hr.drift_risk > 2 OR hr.cash_risk > 10 THEN 'medium' ELSE 'low' END AS risk_level FROM household_risk hr ) SELECT ha.house_hold_name AS household, cs.household_segment, adv.advisor_ids, ha.aum, ((ha.aum - COALESCE(b.beginning_aum,0)) / NULLIF(b.beginning_aum,0)) * 100 AS ytd_return, NULL AS vs_benchmark, hd.model_drift, ROUND(COALESCE(cd.cash_drag_bps,0),2) AS cash_drag_bps, ROUND(COALESCE(ug.unrealized_gl,0),2) AS unrealized_gain_loss, ROUND(COALESCE(hs.risk_score,0),2) AS risk_score, ha1.alert_severity, ha1.risk_alert, rl.risk_level FROM household_aum ha LEFT JOIN household_advisors adv ON ha.house_hold_name = adv.house_hold_name LEFT JOIN beginning_household_aum b ON ha.house_hold_name = b.house_hold_name LEFT JOIN household_nna_ytd n ON ha.house_hold_name = n.house_hold_name LEFT JOIN household_drift hd ON ha.house_hold_name = hd.house_hold_name LEFT JOIN household_cash_drag cd ON ha.house_hold_name = cd.house_hold_name LEFT JOIN household_unrealized_gl ug ON ha.house_hold_name = ug.house_hold_name LEFT JOIN client_segment cs ON ha.house_hold_name = cs.house_hold_name LEFT JOIN household_score hs ON ha.house_hold_name = hs.house_hold_name LEFT JOIN household_alerts ha1 ON ha.house_hold_name = ha1.house_hold_name LEFT JOIN household_risk_level rl ON ha.house_hold_name = rl.house_hold_name ORDER BY ha.aum DESC; | K29: Data Available/Calculation Required | L29: missing benchmark, model portfolio | M29: Category: Data Available/Calculation Required. Side panel needs Unrealized G/L, Model Drift, Retention Risk, Review Status - not in Insigneo. AUM/Cash Drag available. | Q29: model drift is not available
A30: Advisor | B30: Advisor Home Dashboard | C30: KPI | D30: Total AUM | E30: Total AUM + quarterly growth %, target achievement %, progress bar | F30: SUM(market_value latest snapshot) | G30: Done | I30: KPI-001 | J30: SELECT SUM(p.amount) AS total_aum FROM wealth_pulse_insigneo_model.gold.positions p JOIN financial_account a ON p.financial_account_id = a.financial_account_id WHERE p.snapshot_date = ( SELECT MAX(snapshot_date) FROM wealth_pulse_insigneo_model.gold.positions ) AND a.account_status_indicator = 'O' AND a.is_active = 1 | K30: Done | L30: 1 - Done | M30: Category: Done. Total AUM updated in DB.
A31: Advisor | B31: Advisor Home Dashboard | C31: KPI | D31: Net New Assets (QTD) | E31: Quarterly inflow, organic growth %, goal status | F31: Contributions+TransfersIn - Withdrawals-TransfersOut | G31: Done | I31: KPI-016 | J31: WITH latest_snapshot AS ( SELECT MAX(snapshot_date) AS end_date FROM wealth_pulse_insigneo_model.gold.positions ), date_filter AS ( SELECT end_date, DATE_SUB(end_date, @days_filter) AS start_date FROM latest_snapshot ) SELECT ROUND( SUM( CASE WHEN t.transaction_code IN ('CONTRIBUTION', 'TRANSFER_IN', 'RFF', 'CSR') THEN ABS(t.amount) ELSE 0 END ) - SUM( CASE WHEN t.transaction_code IN ('DISTRIBUTION', 'TRANSFER_OUT', 'SFF', 'PCC') THEN ABS(t.amount) ELSE 0 END ), 2 ) AS net_new_assets FROM wealth_pulse_insigneo_model.gold.transactions t JOIN wealth_pulse_insigneo_model.gold.financial_account fa ON t.financial_account_id = fa.financial_account_id WHERE CAST(t.transaction_date AS DATE) BETWEEN ( SELECT start_date FROM date_filter ) AND ( SELECT end_date FROM date_filter ) AND fa.account_status_indicator = 'O' AND fa.is_active = 1; | K31: Done | L31: 1 - Done | M31: Category: Done. Net New Assets updated in DB.
A32: Advisor | B32: Advisor Home Dashboard | C32: KPI | D32: Idle Cash | E32: Idle cash amount, % of AUM, impacted households | F32: fact_cash_balance / AUM | G32: Done | I32: KPI-013 | J32: WITH latest_snapshot AS ( SELECT MAX(snapshot_date) AS max_snapshot_date FROM wealth_pulse_insigneo_model.gold.positions ), position_mv AS ( SELECT p.financial_account_id, SUM(p.amount) AS market_value FROM wealth_pulse_insigneo_model.gold.positions p JOIN wealth_pulse_insigneo_model.gold.financial_account a ON p.financial_account_id = a.financial_account_id CROSS JOIN latest_snapshot l WHERE p.snapshot_date = l.max_snapshot_date AND a.account_status_indicator = 'O' AND a.is_active = 1 GROUP BY p.financial_account_id ), account_cash AS ( SELECT hd.house_hold_name, a.financial_account_id, mv.market_value, a.cash_available, a.cash_available / NULLIF(mv.market_value,0) AS cash_pct FROM wealth_pulse_insigneo_model.gold.account_summary a JOIN position_mv mv ON a.financial_account_id = mv.financial_account_id LEFT JOIN wealth_pulse_insigneo_model.gold.household_details hd ON a.financial_account_id = hd.financial_account_id JOIN wealth_pulse_insigneo_model.gold.financial_account fa ON a.financial_account_id = fa.financial_account_id WHERE fa.account_status_indicator = 'O' AND fa.is_active = 1 ) SELECT ROUND(SUM(cash_available),2) AS idle_cash FROM account_cash WHERE cash_pct > 0.05 | K32: (with new derived table) | L32: 2 - In Progress | M32: Category: (with new derived table). Idle Cash via new derived table. | N32: Yes
A33: Advisor | B33: Advisor Home Dashboard | C33: KPI | D33: Concentration Risk | E33: Accounts breaching limits, top security, severity | F33: Position value/portfolio > 10% | G33: Done | I33: KPI-049 | J33: WITH latest_snapshot AS ( SELECT MAX(snapshot_date) AS snapshot_date FROM wealth_pulse_insigneo_model.gold.positions ), account_positions AS ( SELECT p.investment_professional_number, hd.house_hold_name, p.account_number, UPPER( COALESCE( NULLIF(TRIM(s.ticker), ''), NULLIF(TRIM(p.cusip), '') ) ) AS ticker, MAX(s.asset_name) AS security_name, SUM(p.amount) AS market_value FROM wealth_pulse_insigneo_model.gold.positions p JOIN wealth_pulse_insigneo_model.gold.financial_account fa ON p.financial_account_id = fa.financial_account_id JOIN wealth_pulse_insigneo_model.gold.household_details hd ON p.financial_account_id = hd.financial_account_id LEFT JOIN wealth_pulse_insigneo_model.gold.securities s ON p.cusip = s.cusip WHERE p.snapshot_date = ( SELECT snapshot_date FROM latest_snapshot ) AND fa.account_status_indicator = 'O' AND fa.is_active = 1 GROUP BY p.investment_professional_number, hd.house_hold_name, p.account_number, UPPER( COALESCE( NULLIF(TRIM(s.ticker), ''), NULLIF(TRIM(p.cusip), '') ) ) ), account_total AS ( SELECT investment_professional_number, house_hold_name, account_number, SUM(market_value) AS total_aum FROM account_positions GROUP BY investment_professional_number, house_hold_name, account_number ) SELECT ap.investment_professional_number, ap.house_hold_name, ap.account_number, ap.ticker, ap.security_name, ROUND( ap.market_value * 100.0 / NULLIF(at.total_aum, 0), 2 ) AS pct_aum, ROUND(ap.market_value, 2) AS value FROM account_positions ap JOIN account_total at ON ap.investment_professional_number = at.investment_professional_number AND ap.house_hold_name = at.house_hold_name AND ap.account_number = at.account_number ORDER BY ap.investment_professional_number, ap.house_hold_name, ap.account_number, pct_aum DESC; | K33: Done | L33: 1 - Done | M33: Category: Done. Concentration Risk updated in DB.
A34: Leadership | B34: Household Insights Dashboard (Leadership View) | C34: KPI | D34: Avg YTD Return | E34: AUM-weighted YTD return across households | F34: SUM(ytd_return×beg_value)/SUM(beg_value) | G34: Done | H34: household_details join with account_summary get AUM | I34: TABLE-LD-HH-02 | J34: WITH latest_snapshot AS ( SELECT MAX(snapshot_date) AS max_snapshot_date FROM wealth_pulse_insigneo_model.gold.positions ), /* Latest Household AUM */ household_aum AS ( SELECT h.house_hold_name, SUM(p.amount) AS aum FROM wealth_pulse_insigneo_model.gold.positions p JOIN wealth_pulse_insigneo_model.gold.household_details h ON p.financial_account_id = h.financial_account_id JOIN wealth_pulse_insigneo_model.gold.financial_account fa ON p.financial_account_id = fa.financial_account_id CROSS JOIN latest_snapshot l WHERE p.snapshot_date = l.max_snapshot_date AND fa.account_status_indicator = 'O' AND fa.is_active = 1 GROUP BY h.house_hold_name ), /* Beginning Household AUM */ beginning_household_aum AS ( SELECT h.house_hold_name, SUM(p.amount) AS beginning_aum FROM wealth_pulse_insigneo_model.gold.positions p JOIN wealth_pulse_insigneo_model.gold.household_details h ON p.financial_account_id = h.financial_account_id JOIN wealth_pulse_insigneo_model.gold.financial_account fa ON p.financial_account_id = fa.financial_account_id WHERE p.snapshot_date = ( SELECT MAX(snapshot_date) FROM wealth_pulse_insigneo_model.gold.positions WHERE snapshot_date < DATE_TRUNC( 'year', (SELECT max_snapshot_date FROM latest_snapshot) ) ) AND fa.account_status_indicator = 'O' AND fa.is_active = 1 GROUP BY h.house_hold_name ), /* Household YTD Return */ household_ytd_return AS ( SELECT ha.house_hold_name, ( (ha.aum - COALESCE(b.beginning_aum,0)) / NULLIF(b.beginning_aum,0) ) * 100 AS ytd_return FROM household_aum ha LEFT JOIN beginning_household_aum b ON ha.house_hold_name = b.house_hold_name ) SELECT ROUND(AVG(ytd_return), 2) AS avg_household_ytd_return_pct FROM household_ytd_return WHERE ytd_return IS NOT NULL; | K34: Data Not Available | L34: Phase 3 Done | M34: Category: Data Not Available. Avg YTD Return - no performance table in Insigneo.
A35: Advisor | B35: Household Detail Pages (4 tabs) | C35: KPI | D35: Tab1: YTD Return | E35: Portfolio performance YTD | F35: fact_performance household level | G35: Done | H35: how to get the performance ? Already defined fact_performance table used | I35: - | J35: WITH latest_snapshot AS ( SELECT MAX(snapshot_date) AS max_snapshot_date FROM wealth_pulse_insigneo_model.gold.positions ), current_household_aum AS ( SELECT h.house_hold_name, SUM(p.amount) AS current_aum FROM wealth_pulse_insigneo_model.gold.positions p JOIN wealth_pulse_insigneo_model.gold.household_details h ON p.financial_account_id = h.financial_account_id JOIN wealth_pulse_insigneo_model.gold.financial_account a ON p.financial_account_id = a.financial_account_id CROSS JOIN latest_snapshot l WHERE p.snapshot_date = l.max_snapshot_date AND h.house_hold_name = :house_hold_name AND a.account_status_indicator = 'O' AND a.is_active = 1 GROUP BY h.house_hold_name ), beginning_household_aum AS ( SELECT h.house_hold_name, SUM(p.amount) AS beginning_aum FROM wealth_pulse_insigneo_model.gold.positions p JOIN wealth_pulse_insigneo_model.gold.household_details h ON p.financial_account_id = h.financial_account_id JOIN wealth_pulse_insigneo_model.gold.financial_account a ON p.financial_account_id = a.financial_account_id CROSS JOIN latest_snapshot l WHERE p.snapshot_date = ( SELECT MAX(snapshot_date) FROM wealth_pulse_insigneo_model.gold.positions WHERE snapshot_date < DATE_TRUNC('year', l.max_snapshot_date) ) AND h.house_hold_name = :house_hold_name AND a.account_status_indicator = 'O' AND a.is_active = 1 GROUP BY h.house_hold_name ) SELECT ((c.current_aum - b.beginning_aum) / NULLIF(b.beginning_aum, 0)) * 100 AS ytd_return_pct FROM current_household_aum c LEFT JOIN beginning_household_aum b ON c.house_hold_name = b.house_hold_name; | K35: Data Not Available | L35: Phase 3 Done | M35: Category: Data Not Available. YTD Return - no performance data in Insigneo.
A36: Advisor | B36: Portfolio Analytics Dashboard | C36: KPI | D36: Risk Card - International Exposure % | E36: International allocation % vs target range | F36: intl_pct AUM-weighted | G36: Done | H36: How to identify the international stock, how can I classify it ? Add in sample data, in gold securities , country column | I36: KPI-037 | J36: WITH latest_snapshot AS ( SELECT MAX(snapshot_date) AS snapshot_date FROM wealth_pulse_insigneo_model.gold.positions ) SELECT ROUND( SUM( CASE WHEN UPPER(TRIM(COALESCE(s.country, ''))) NOT IN ( 'UNITED STATES', 'UNITED STATES OF AMERICA', 'USA', 'U.S.A.', 'US', 'U.S.' ) THEN p.amount ELSE 0 END ) * 100.0 / NULLIF(SUM(p.amount), 0), 2 ) AS international_exposure_pct FROM wealth_pulse_insigneo_model.gold.positions p JOIN wealth_pulse_insigneo_model.gold.household_details hd ON p.financial_account_id = hd.financial_account_id JOIN wealth_pulse_insigneo_model.gold.financial_account fa ON p.financial_account_id = fa.financial_account_id JOIN wealth_pulse_insigneo_model.gold.securities s ON p.cusip = s.cusip WHERE hd.house_hold_name = 'CYGNUS' AND p.snapshot_date = ( SELECT snapshot_date FROM latest_snapshot ) AND fa.account_status_indicator = 'O' AND fa.is_active = 1; | K36: Data Available/Calculation Required | L36: Phase 3 Done | M36: Category: Data Available/Calculation Required. International Exposure - security country not in Insigneo.
A37: Advisor | B37: Household Detail Pages (4 tabs) | C37: Section | D37: Tab2: Account Card + Subtotal + Cash | E37: Expandable account card, subtotal row, cash & equivalents section | F37: dim_account + fact_cash_balance | G37: Done | H37: household->account->positions and securities with details(Ticker, Security, Name, Type, Asset Class, Shares, Price, Market Value, Cost Basis, UnrealizedG/L, %Acct, Holding) | I37: - | J37: WITH latest_snapshot AS ( SELECT MAX(snapshot_date) AS snapshot_date FROM wealth_pulse_insigneo_model.gold.positions ), latest_positions AS ( SELECT p.financial_account_id, p.account_number, p.cusip, p.quantity, p.price, p.amount, p.total_cost, p.account_type, p.snapshot_date FROM wealth_pulse_insigneo_model.gold.positions p WHERE p.snapshot_date = ( SELECT snapshot_date FROM latest_snapshot ) ) SELECT hd.house_hold_name, lp.account_number, fa.account_short_name, s.ticker, s.asset_name AS security_name, lp.account_type AS type, s.asset_class, lp.quantity AS shares, lp.price, lp.amount AS market_value, lp.total_cost AS cost_basis, (lp.amount - lp.total_cost) AS unrealized_gl, ROUND( lp.amount * 100.0 / NULLIF( SUM(lp.amount) OVER (PARTITION BY lp.account_number), 0 ), 2 ) AS pct_acct, ROUND( lp.amount * 100.0 / NULLIF( SUM(lp.amount) OVER (PARTITION BY hd.house_hold_name), 0 ), 2 ) AS holding FROM latest_positions lp JOIN wealth_pulse_insigneo_model.gold.household_details hd ON lp.financial_account_id = hd.financial_account_id JOIN wealth_pulse_insigneo_model.gold.financial_account fa ON lp.financial_account_id = fa.financial_account_id LEFT JOIN wealth_pulse_insigneo_model.gold.securities s ON lp.cusip = s.cusip WHERE hd.house_hold_name = 'AURORA' AND fa.account_status_indicator = 'O' AND fa.is_active = 1 ORDER BY lp.account_number, market_value DESC; | K37: Data Not Available | L37: Phase 3 Done | M37: Category: Data Not Available. Account subtotals - cost-basis/unrealized subtotals need data not in Insigneo; MV & cash available.
A38: Advisor | B38: Advisor Home Dashboard | C38: Panel | D38: Morning Briefing Panel | E38: AI/rules daily insights (growth, risk, idle cash, tax) - expandable cards | F38: Stage-1 agent insights | G38: Done | I38: KPI-043 | J38: - | K38: Data Available/Calculation Required | L38: 5 - Insights | M38: Category: Data Available/Calculation Required. Morning Briefing - insights framework; tax-harvest calc-derivable, some risk insights blocked.
A39: Advisor | B39: Advisor Home Dashboard | C39: Panel | D39: Priority Actions Panel | E39: Ranked advisor actions with severity + deep-link (see US 16010) | F39: Insights / Stage-2 agents | G39: Framework | I39: - | J39: - | K39: - | L39: 5 - Insights | M39: Category: -. Priority Actions - Stage-2 agent framework, not data-driven yet.
A40: Advisor | B40: Advisor Home Dashboard | C40: Panel | D40: Market News (Placeholder) | E40: Reserved 'Coming Soon' market news container | F40: Placeholder | G40: Done | I40: - | J40: - | K40: - | L40: 5 - Insights | M40: Category: -. Market News placeholder.
A41: Advisor | B41: Advisor Home Dashboard | C41: Panel | D41: Portfolio Intelligence (Placeholder) | E41: Future real-time market signal panel (Epic 26 / Stage 2) | F41: Placeholder (US 16011) | G41: Done | I41: - | J41: - | K41: - | L41: 5 - Insights | M41: Category: -. Portfolio Intelligence placeholder (Stage-2 / Epic 26).
A42: Advisor | B42: Advisor Home Dashboard | C42: Table | D42: Households Needing Attention | E42: Household, AUM, issue summary, urgency (High/Med/Low); flag rules idle cash/concentration/attrition/drift | F42: fact_position/cash/client_360 flag logic | G42: Done | I42: KPI-050 | J42: - | K42: (with new derived table) | L42: 2 - In Progress | M42: Category: (with new derived table). Households Needing Attention - concentration & idle-cash flags available (derived); model-drift & engagement-gap flags blocked. | N42: Yes | P42: Drift can't be achieved
A43: Advisor | B43: Advisor Home Dashboard | C43: Chart | D43: AUM Trend Analytics | E43: Monthly AUM line chart, 3M/6M/12M filters | F43: Monthly SUM(market_value) | G43: Done | I43: CHART-005 | J43: SELECT DATEFROMPARTS(YEAR(fp.snapshot_date), MONTH(fp.snapshot_date), 1) AS [month], SUM(ABS(fp.amount)) AS aum FROM positions fp WHERE fp.investment_professional_number = 'N04' -- AND CAST(fp.snapshot_date AS DATE) = EOMONTH(fp.snapshot_date) AND CAST(fp.snapshot_date AS DATE) >= DATEADD( MONTH, -5, DATEFROMPARTS(YEAR(GETDATE()), MONTH(GETDATE()), 1) ) GROUP BY DATEFROMPARTS(YEAR(fp.snapshot_date), MONTH(fp.snapshot_date), 1) ORDER BY [month]; | K43: Done | L43: 1 - Done | M43: Category: Done. 6-month AUM trend; validate vs Insigneo (flagged 'Doubt').
A44: Leadership | B44: Firm Dashboard (Leadership Home) | C44: Table | D44: Advisor Performance Table | E44: Cols: Advisor, AUM, NNA (QTD), Growth, Retention, HH, Revenue, Rank + underperformer alert row | F44: fact_position/transaction/billing_event + dim_advisor | G44: Done | H44: limited details - household->account_summary | I44: CHART-004 | J44: WITH latest_snapshot AS ( SELECT MAX(snapshot_date) AS max_snapshot_date FROM wealth_pulse_insigneo_model.gold.positions ), aum AS ( SELECT p.investment_professional_number, SUM(p.amount) AS total_aum FROM wealth_pulse_insigneo_model.gold.positions p JOIN wealth_pulse_insigneo_model.gold.financial_account fa ON p.financial_account_id = fa.financial_account_id WHERE p.snapshot_date = ( SELECT max_snapshot_date FROM latest_snapshot ) AND fa.account_status_indicator = 'O' AND fa.is_active = 1 GROUP BY p.investment_professional_number ), nna_qtd AS ( SELECT fa.investment_professional_number, SUM( CASE WHEN t.transaction_code IN ( 'CONTRIBUTION', 'TRANSFER_IN', 'RFF', 'CSR' ) THEN ABS(t.amount) ELSE 0 END ) - SUM( CASE WHEN t.transaction_code IN ( 'DISTRIBUTION', 'TRANSFER_OUT', 'SFF', 'PCC' ) THEN ABS(t.amount) ELSE 0 END ) AS nna_qtd FROM wealth_pulse_insigneo_model.gold.transactions t INNER JOIN wealth_pulse_insigneo_model.gold.financial_account fa ON t.financial_account_id = fa.financial_account_id CROSS JOIN latest_snapshot ls WHERE CAST(t.transaction_date AS DATE) BETWEEN DATE_TRUNC('quarter', ls.max_snapshot_date) AND ls.max_snapshot_date AND fa.account_status_indicator = 'O' AND fa.is_active = 1 GROUP BY fa.investment_professional_number ), beg_aum AS ( SELECT p.investment_professional_number, SUM(p.amount) AS beg_aum FROM wealth_pulse_insigneo_model.gold.positions p JOIN wealth_pulse_insigneo_model.gold.financial_account fa ON p.financial_account_id = fa.financial_account_id CROSS JOIN latest_snapshot ls WHERE p.snapshot_date = ( SELECT MAX(snapshot_date) FROM wealth_pulse_insigneo_model.gold.positions WHERE snapshot_date < DATE_TRUNC('year', ls.max_snapshot_date) ) AND fa.account_status_indicator = 'O' AND fa.is_active = 1 GROUP BY p.investment_professional_number ), households AS ( SELECT fa.investment_professional_number, COUNT(DISTINCT hd.house_hold_name) AS household_count, ROUND( COUNT( DISTINCT CASE WHEN fa.account_status_indicator='O' THEN fa.financial_account_id END ) *100.0 / NULLIF( COUNT(DISTINCT fa.financial_account_id), 0 ), 2 ) AS retention_pct FROM wealth_pulse_insigneo_model.gold.financial_account fa LEFT JOIN wealth_pulse_insigneo_model.gold.household_details hd ON fa.financial_account_id = hd.financial_account_id WHERE fa.is_active=1 GROUP BY fa.investment_professional_number ), revenue AS ( SELECT investment_professional_number, SUM(gross_comm) AS est_revenue FROM wealth_pulse_insigneo_model.gold.fa_commission CROSS JOIN latest_snapshot ls WHERE broker_month >= DATE_TRUNC('year', ls.max_snapshot_date) AND broker_month <= ls.max_snapshot_date GROUP BY investment_professional_number ) SELECT adv.rep_id AS investment_professional_number, adv.record_assigned_name, ROUND(COALESCE(a.total_aum,0),2) AS aum, ROUND(COALESCE(n.nna_qtd,0),2) AS nna_qtd, ROUND( COALESCE(n.nna_qtd,0) / NULLIF(b.beg_aum,0) *100, 2) AS growth_pct, COALESCE(h.retention_pct,0) AS retention_pct, COALESCE(h.household_count,0) AS households, ROUND(COALESCE(r.est_revenue,0),2) AS revenue, DENSE_RANK() OVER( ORDER BY COALESCE(a.total_aum,0) DESC ) AS advisor_rank FROM wealth_pulse_insigneo_model.gold.financial_advisor adv LEFT JOIN aum a ON adv.rep_id = a.investment_professional_number LEFT JOIN nna_qtd n ON adv.rep_id = n.investment_professional_number LEFT JOIN beg_aum b ON adv.rep_id = b.investment_professional_number LEFT JOIN households h ON adv.rep_id = h.investment_professional_number LEFT JOIN revenue r ON adv.rep_id = r.investment_professional_number ORDER BY advisor_rank; | K44: Data Not Available | L44: Phase 3 Done | M44: Category: Data Not Available. Advisor Performance leaderboard flagged data-gap; core columns come from Done KPIs.
A45: Advisor | B45: Household Management Dashboard | C45: KPI | D45: Total AUM | E45: Total AUM aggregated across all households | F45: SUM(dim_household.total_aum) | G45: Done | I45: KPI-001 | J45: SELECT SUM(p.amount) AS total_aum FROM positions p JOIN financial_account a ON p.financial_account_id = a.financial_account_id WHERE p.snapshot_date BETWEEN DATEADD(DAY, 1 - DATEPART(WEEKDAY, '2026-01-01'), '2026-01-01') AND DATEADD(DAY, 7 - DATEPART(WEEKDAY, '2026-01-01'), '2026-01-01') AND a.account_status_indicator = 'O' AND a.is_active = 1 | K45: Done | L45: 1 - Done | M45: Category: Done. Total AUM updated in DB.
A46: Advisor | B46: Household Management Dashboard | C46: KPI | D46: Total Households | E46: Count of households for advisor | F46: COUNT(household_id) | G46: Done | I46: KPI-008 | J46: - | K46: (with new derived table) | L46: 2 - In Progress | M46: Category: (with new derived table). Total Households via new derived table. | N46: Yes | P46: Query tobe shared
A47: Leadership | B47: Advisor Intelligence Dashboard (Leadership View) | C47: Table | D47: Advisor Comparison Table | E47: Cols: Advisor, AUM, Households, YTD Growth, Vs Benchmark, NNM YTD, NNM Goal %, Revenue, Retention, Satisfaction, Risk Score | F47: KPI-009/016/020/047/058 + derived | G47: Done | H47: limited details - household->account_summary | I47: CHART-022 | J47: WITH latest_snapshot AS ( SELECT MAX(snapshot_date) AS max_snapshot_date FROM wealth_pulse_insigneo_model.gold.positions ), aum AS ( SELECT p.investment_professional_number, SUM(p.amount) AS aum FROM wealth_pulse_insigneo_model.gold.positions p JOIN wealth_pulse_insigneo_model.gold.financial_account fa ON p.financial_account_id = fa.financial_account_id WHERE p.snapshot_date = (SELECT max_snapshot_date FROM latest_snapshot) AND fa.account_status_indicator = 'O' AND fa.is_active = 1 GROUP BY p.investment_professional_number ), beginning_aum AS ( SELECT p.investment_professional_number, SUM(p.amount) AS beginning_aum FROM wealth_pulse_insigneo_model.gold.positions p JOIN wealth_pulse_insigneo_model.gold.financial_account fa ON p.financial_account_id = fa.financial_account_id WHERE p.snapshot_date = ( SELECT MAX(snapshot_date) FROM wealth_pulse_insigneo_model.gold.positions WHERE snapshot_date < DATE_TRUNC( 'year', (SELECT max_snapshot_date FROM latest_snapshot) ) ) AND fa.account_status_indicator = 'O' AND fa.is_active = 1 GROUP BY p.investment_professional_number ), nnm_ytd AS ( SELECT fa.investment_professional_number, SUM( CASE WHEN t.transaction_code IN ('CONTRIBUTION','TRANSFER_IN','RFF','CSR') THEN ABS(t.amount) ELSE 0 END ) - SUM( CASE WHEN t.transaction_code IN ('DISTRIBUTION','TRANSFER_OUT','SFF','PCC') THEN ABS(t.amount) ELSE 0 END ) AS nnm_ytd FROM wealth_pulse_insigneo_model.gold.transactions t JOIN wealth_pulse_insigneo_model.gold.financial_account fa ON t.financial_account_id = fa.financial_account_id CROSS JOIN latest_snapshot l WHERE (CAST(t.transaction_date AS DATE) BETWEEN DATE_TRUNC('year', l.max_snapshot_date) AND l.max_snapshot_date) AND fa.account_status_indicator='O' AND fa.is_active=1 GROUP BY fa.investment_professional_number ), households AS ( SELECT f.investment_professional_number, COUNT(DISTINCT h.house_hold_name) AS households FROM wealth_pulse_insigneo_model.gold.household_details h JOIN wealth_pulse_insigneo_model.gold.financial_account f ON h.financial_account_id = f.financial_account_id WHERE f.account_status_indicator='O' AND f.is_active=1 GROUP BY f.investment_professional_number ), revenue AS ( SELECT fc.investment_professional_number, SUM(fc.gross_comm) AS revenue FROM wealth_pulse_insigneo_model.gold.fa_commission fc JOIN wealth_pulse_insigneo_model.gold.financial_account f ON fc.financial_account_id = f.financial_account_id CROSS JOIN latest_snapshot l WHERE fc.broker_month >= DATE_TRUNC('year', l.max_snapshot_date) AND f.account_status_indicator='O' AND f.is_active=1 GROUP BY fc.investment_professional_number ), retention AS ( SELECT f.investment_professional_number, COUNT(DISTINCT CASE WHEN f.account_status_indicator = 'O' THEN f.financial_account_id END) / NULLIF(COUNT(DISTINCT f.financial_account_id),0) * 100 AS retention_pct FROM wealth_pulse_insigneo_model.gold.financial_account f GROUP BY f.investment_professional_number ) SELECT fa.rep_id, a.aum, COALESCE(h.households,0) AS households, ( (a.aum - COALESCE(b.beginning_aum,0) - COALESCE(n.nnm_ytd,0)) / NULLIF(b.beginning_aum,0) ) * 100 AS ytd_growth, NULL AS vs_benchmark, COALESCE(n.nnm_ytd,0) AS nnm_ytd, NULL AS nnm_goal_pct, COALESCE(r.revenue,0) AS revenue, COALESCE(rt.retention_pct,0) AS retention FROM wealth_pulse_insigneo_model.gold.financial_advisor fa LEFT JOIN aum a ON a.investment_professional_number = fa.rep_id LEFT JOIN beginning_aum b ON a.investment_professional_number = b.investment_professional_number LEFT JOIN nnm_ytd n ON a.investment_professional_number = n.investment_professional_number LEFT JOIN households h ON a.investment_professional_number = h.investment_professional_number LEFT JOIN revenue r ON a.investment_professional_number = r.investment_professional_number LEFT JOIN retention rt ON a.investment_professional_number = rt.investment_professional_number ORDER BY a.aum DESC; | K47: Data Not Available | L47: Phase 3 Done | M47: Category: Data Not Available. Advisor Comparison table flagged data-gap; blocked columns: Vs-Benchmark (alpha), Satisfaction, Overdue Reviews. Other columns from Done KPIs.
A48: Leadership | B48: Household Insights Dashboard (Leadership View) | C48: Table | D48: Household Intelligence Table | E48: Cols: Household, Advisor, AUM, YTD Return, Vs Benchmark, Model Drift, Risk, Last Review (TBD) | F48: fact_position/performance + dim_household | G48: Done | H48: limited details - household->account_summary | I48: CHART-024 | J48: WITH latest_snapshot AS ( SELECT MAX(snapshot_date) AS max_snapshot_date FROM wealth_pulse_insigneo_model.gold.positions ), /* Latest household AUM */ household_aum AS ( SELECT h.house_hold_name, SUM(p.amount) AS aum FROM wealth_pulse_insigneo_model.gold.positions p JOIN wealth_pulse_insigneo_model.gold.household_details h ON p.financial_account_id = h.financial_account_id JOIN wealth_pulse_insigneo_model.gold.financial_account a ON p.financial_account_id = a.financial_account_id CROSS JOIN latest_snapshot l WHERE p.snapshot_date = l.max_snapshot_date AND a.account_status_indicator = 'O' AND a.is_active = 1 GROUP BY h.house_hold_name ), /* Beginning household AUM */ beginning_household_aum AS ( SELECT h.house_hold_name, SUM(p.amount) AS beginning_aum FROM wealth_pulse_insigneo_model.gold.positions p JOIN wealth_pulse_insigneo_model.gold.household_details h ON p.financial_account_id = h.financial_account_id JOIN wealth_pulse_insigneo_model.gold.financial_account a ON p.financial_account_id = a.financial_account_id WHERE p.snapshot_date = ( SELECT MAX(snapshot_date) FROM wealth_pulse_insigneo_model.gold.positions WHERE snapshot_date < DATE_TRUNC( 'year', (SELECT max_snapshot_date FROM latest_snapshot) ) ) AND a.account_status_indicator = 'O' AND a.is_active = 1 GROUP BY h.house_hold_name ), /* Household NNM YTD */ household_nna_ytd AS ( SELECT h.house_hold_name, SUM( CASE WHEN t.transaction_code IN ('CONTRIBUTION','TRANSFER_IN','RFF','CSR') THEN ABS(t.amount) ELSE 0 END ) - SUM( CASE WHEN t.transaction_code IN ('DISTRIBUTION','TRANSFER_OUT','SFF','PCC') THEN ABS(t.amount) ELSE 0 END ) AS nna_ytd FROM wealth_pulse_insigneo_model.gold.transactions t JOIN wealth_pulse_insigneo_model.gold.financial_account fa ON t.financial_account_id = fa.financial_account_id JOIN wealth_pulse_insigneo_model.gold.household_details h ON fa.financial_account_id = h.financial_account_id CROSS JOIN latest_snapshot l WHERE CAST(t.transaction_date AS DATE) BETWEEN DATE_TRUNC('year', l.max_snapshot_date) AND l.max_snapshot_date AND fa.account_status_indicator = 'O' AND fa.is_active = 1 GROUP BY h.house_hold_name ), /* Current Equity % at Account Level */ account_equity AS ( SELECT ac.account_number, ac.financial_account_id, ac.total_equity AS equity_value, ( COALESCE(p.amount,0) + COALESCE(ac.cash_available,0) ) AS total_value, CASE WHEN ( COALESCE(p.amount,0) + COALESCE(ac.cash_available,0) ) = 0 THEN NULL ELSE ac.total_equity * 100.0 / ( COALESCE(p.amount,0) + COALESCE(ac.cash_available,0) ) END AS current_equity_pct FROM wealth_pulse_insigneo_model.gold.positions p JOIN wealth_pulse_insigneo_model.gold.account_summary ac ON p.financial_account_id = ac.financial_account_id JOIN wealth_pulse_insigneo_model.gold.financial_account a ON p.financial_account_id = a.financial_account_id CROSS JOIN latest_snapshot l WHERE p.snapshot_date = l.max_snapshot_date AND a.account_status_indicator = 'O' AND a.is_active = 1 ), /* Drift Per Account */ account_drift AS ( SELECT h.house_hold_name, fa.investment_professional_number, ae.account_number, ae.current_equity_pct, dmp.target_equity_pct, (ae.current_equity_pct - dmp.target_equity_pct) AS drift_pct, ae.total_value FROM account_equity ae JOIN wealth_pulse_insigneo_model.gold.financial_account fa ON ae.financial_account_id = fa.financial_account_id JOIN wealth_pulse_insigneo_model.gold.household_details h ON h.financial_account_id = fa.financial_account_id JOIN wealth_pulse_insigneo_model.silver.account_model_mapping amm ON amm.account_number = ae.account_number JOIN wealth_pulse_insigneo_model.gold.dim_model_portfolio dmp ON dmp.model_id = amm.model_id ), /* Household Drift */ household_drift AS ( SELECT house_hold_name, SUM(drift_pct * total_value) / NULLIF(SUM(total_value),0) AS model_drift FROM account_drift GROUP BY house_hold_name ), household_unrealized_gl AS ( SELECT hd.house_hold_name, SUM(p.amount) - SUM(p.total_cost) AS unrealized_gl FROM wealth_pulse_insigneo_model.gold.positions p JOIN wealth_pulse_insigneo_model.gold.household_details hd ON p.financial_account_id = hd.financial_account_id JOIN wealth_pulse_insigneo_model.gold.financial_account fa ON p.financial_account_id = fa.financial_account_id CROSS JOIN latest_snapshot l WHERE p.snapshot_date = l.max_snapshot_date AND fa.account_status_indicator = 'O' AND fa.is_active = 1 GROUP BY hd.house_hold_name ), household_market_value AS ( SELECT p.financial_account_id, SUM(p.amount) AS market_value FROM wealth_pulse_insigneo_model.gold.positions p CROSS JOIN latest_snapshot l WHERE p.snapshot_date = l.max_snapshot_date GROUP BY p.financial_account_id ), account_cash AS ( SELECT hd.house_hold_name, fa.investment_professional_number, a.financial_account_id, a.cash_available, mv.market_value, a.cash_available / NULLIF(mv.market_value,0) AS cash_pct FROM wealth_pulse_insigneo_model.gold.account_summary a JOIN household_market_value mv ON a.financial_account_id = mv.financial_account_id JOIN wealth_pulse_insigneo_model.gold.household_details hd ON a.financial_account_id = hd.financial_account_id JOIN wealth_pulse_insigneo_model.gold.financial_account fa ON a.financial_account_id = fa.financial_account_id WHERE fa.account_status_indicator='O' AND fa.is_active=1 ), household_cash_drag AS ( SELECT house_hold_name, ROUND( ( AVG(cash_pct) - 0.03 ) * ( 10 --10 - 4.5 --4.5 ) *10000, 2 ) AS cash_drag_bps FROM account_cash WHERE cash_pct > 0.03 GROUP BY house_hold_name ), household_advisors AS ( SELECT hd.house_hold_name, STRING_AGG( DISTINCT fa.rep_id, ', ' ) AS advisor_ids FROM wealth_pulse_insigneo_model.gold.household_details hd JOIN wealth_pulse_insigneo_model.gold.financial_account acc ON hd.financial_account_id = acc.financial_account_id JOIN wealth_pulse_insigneo_model.gold.financial_advisor fa ON acc.investment_professional_number = fa.rep_id WHERE acc.account_status_indicator='O' AND acc.is_active=1 AND fa.is_active=1 GROUP BY hd.house_hold_name ), client_segment AS ( SELECT t.house_hold_name, CASE WHEN MAX( CASE WHEN t.entity_name IS NOT NULL AND TRIM(t.entity_name) <> '' THEN 1 ELSE 0 END ) = 1 THEN 'Corporate' WHEN SUM(t.maximum_net_worth) >= 10000000 THEN 'UHNW' WHEN SUM(t.maximum_net_worth) >= 1000000 THEN 'HNW' WHEN SUM(t.maximum_net_worth) IS NOT NULL THEN 'Mass Affluent' WHEN SUM(t.maximum_annual_income) >= 1000000 THEN 'UHNW (Estimated)' WHEN SUM(t.maximum_annual_income) >= 250000 THEN 'HNW (Estimated)' ELSE 'Mass Affluent' END AS household_segment FROM ( SELECT DISTINCT hd.house_hold_name, pa.person_account_id, pa.entity_name, pa.maximum_net_worth, pa.maximum_annual_income FROM wealth_pulse_insigneo_model.gold.positions p JOIN wealth_pulse_insigneo_model.gold.household_details hd ON p.financial_account_id = hd.financial_account_id JOIN wealth_pulse_insigneo_model.gold.person_financial_mapping pfm ON p.financial_account_id = pfm.financial_account_id JOIN wealth_pulse_insigneo_model.gold.person_account pa ON pfm.person_account_id = pa.person_account_id JOIN wealth_pulse_insigneo_model.gold.financial_account fa ON p.financial_account_id = fa.financial_account_id CROSS JOIN latest_snapshot l WHERE p.snapshot_date = l.max_snapshot_date AND fa.account_status_indicator = 'O' AND fa.is_active = 1 ) t GROUP BY t.house_hold_name ), /* Account level AUM and cash */ account_base AS ( SELECT ac.financial_account_id, ac.account_number, h.house_hold_name, ( COALESCE(p.amount,0) + COALESCE(ac.cash_available,0) ) AS account_aum, CASE WHEN ( COALESCE(p.amount,0) + COALESCE(ac.cash_available,0) ) = 0 THEN 0 ELSE ac.cash_available * 100.0 / ( COALESCE(p.amount,0) + COALESCE(ac.cash_available,0) ) END AS cash_pct FROM wealth_pulse_insigneo_model.gold.positions p JOIN wealth_pulse_insigneo_model.gold.account_summary ac ON ac.financial_account_id = p.financial_account_id JOIN wealth_pulse_insigneo_model.gold.household_details h ON ac.financial_account_id = h.financial_account_id JOIN wealth_pulse_insigneo_model.gold.financial_account fa ON ac.financial_account_id = fa.financial_account_id CROSS JOIN latest_snapshot l WHERE p.snapshot_date = l.max_snapshot_date AND fa.account_status_indicator = 'O' AND fa.is_active = 1 ), /* Maximum security concentration per account */ account_concentration AS ( SELECT p.financial_account_id, MAX( ABS(p.amount) *100.0 / NULLIF(ab.account_aum,0) ) AS concentration_pct FROM wealth_pulse_insigneo_model.gold.positions p JOIN account_base ab ON p.financial_account_id = ab.financial_account_id JOIN wealth_pulse_insigneo_model.gold.financial_account fa ON p.financial_account_id = fa.financial_account_id CROSS JOIN latest_snapshot l WHERE p.snapshot_date = l.max_snapshot_date AND fa.account_status_indicator = 'O' AND fa.is_active = 1 GROUP BY p.financial_account_id ), /* Account model drift */ account_drift1 AS ( SELECT ab.financial_account_id, ABS( ( ac.total_equity * 100.0 / NULLIF( ( COALESCE(p.amount,0) + COALESCE(ac.cash_available,0) ), 0 ) ) - dmp.target_equity_pct ) AS drift_pct FROM wealth_pulse_insigneo_model.gold.positions p JOIN account_base ab ON p.financial_account_id = ab.financial_account_id JOIN wealth_pulse_insigneo_model.gold.account_summary ac ON ab.financial_account_id = ac.financial_account_id JOIN wealth_pulse_insigneo_model.silver.account_model_mapping amm ON ab.account_number = amm.account_number JOIN wealth_pulse_insigneo_model.gold.dim_model_portfolio dmp ON amm.model_id = dmp.model_id CROSS JOIN latest_snapshot l WHERE p.snapshot_date = l.max_snapshot_date ), /* Household weighted risk metrics */ household_risk AS ( SELECT ab.house_hold_name, /* Maximum concentration risk */ MAX( COALESCE(cc.concentration_pct,0) ) AS concentration_risk, /* AUM weighted drift */ SUM( COALESCE(ad.drift_pct,0) * ab.account_aum ) / NULLIF( SUM(ab.account_aum), 0 ) AS drift_risk, /* AUM weighted cash */ SUM( ab.cash_pct * ab.account_aum ) / NULLIF( SUM(ab.account_aum), 0 ) AS cash_risk FROM account_base ab LEFT JOIN account_concentration cc ON ab.financial_account_id = cc.financial_account_id LEFT JOIN account_drift1 ad ON ab.financial_account_id = ad.financial_account_id GROUP BY ab.house_hold_name ), /* Calculate household risk score */ household_score AS ( SELECT house_hold_name, ( (CASE WHEN concentration_risk > 10 THEN 100 ELSE concentration_risk * 10 END) + (CASE WHEN drift_risk > 8 THEN 100 ELSE drift_risk * 12.5 END) + (CASE WHEN cash_risk > 10 THEN 100 ELSE cash_risk * 10 END) ) / 3 AS risk_score FROM household_risk ), household_alerts AS ( SELECT hr.house_hold_name, CASE /* Critical */ WHEN hr.concentration_risk > 10 OR hr.drift_risk > 8 THEN CONCAT( 'CRITICAL - ', CONCAT_WS(', ', CASE WHEN hr.concentration_risk > 10 THEN 'Concentration > 10%' END, CASE WHEN hr.drift_risk > 8 THEN 'Model Drift > 8%' END ) ) /* Warning */ WHEN hr.drift_risk > 4 OR hr.cash_risk > 10 THEN CONCAT( 'WARNING - ', CONCAT_WS(', ', CASE WHEN hr.drift_risk > 4 THEN 'Model Drift > 4%' END, CASE WHEN hr.cash_risk > 10 THEN 'Cash > 10%' END ) ) /* Opportunity */ WHEN ug.unrealized_gl < -5000 THEN 'OPPORTUNITY - Tax Loss Harvesting' ELSE 'NO ALERT' END AS risk_alert, CASE WHEN hr.concentration_risk > 10 OR hr.drift_risk > 8 THEN 'CRITICAL' WHEN hr.drift_risk > 4 OR hr.cash_risk > 10 THEN 'WARNING' WHEN ug.unrealized_gl < -5000 THEN 'OPPORTUNITY' ELSE 'NONE' END AS alert_severity FROM household_risk hr LEFT JOIN household_unrealized_gl ug ON hr.house_hold_name = ug.house_hold_name ), household_risk_level AS ( SELECT hr.house_hold_name, CASE WHEN hr.drift_risk > 4 OR hr.concentration_risk > 25 OR hr.cash_risk > 15 THEN 'high' WHEN hr.drift_risk > 2 OR hr.cash_risk > 10 THEN 'medium' ELSE 'low' END AS risk_level FROM household_risk hr ) SELECT ha.house_hold_name AS household, cs.household_segment, adv.advisor_ids, ha.aum, ((ha.aum - COALESCE(b.beginning_aum,0)) / NULLIF(b.beginning_aum,0)) * 100 AS ytd_return, NULL AS vs_benchmark, hd.model_drift, ROUND(COALESCE(cd.cash_drag_bps,0),2) AS cash_drag_bps, ROUND(COALESCE(ug.unrealized_gl,0),2) AS unrealized_gain_loss, ROUND(COALESCE(hs.risk_score,0),2) AS risk_score, ha1.alert_severity, ha1.risk_alert, rl.risk_level FROM household_aum ha LEFT JOIN household_advisors adv ON ha.house_hold_name = adv.house_hold_name LEFT JOIN beginning_household_aum b ON ha.house_hold_name = b.house_hold_name LEFT JOIN household_nna_ytd n ON ha.house_hold_name = n.house_hold_name LEFT JOIN household_drift hd ON ha.house_hold_name = hd.house_hold_name LEFT JOIN household_cash_drag cd ON ha.house_hold_name = cd.house_hold_name LEFT JOIN household_unrealized_gl ug ON ha.house_hold_name = ug.house_hold_name LEFT JOIN client_segment cs ON ha.house_hold_name = cs.house_hold_name LEFT JOIN household_score hs ON ha.house_hold_name = hs.house_hold_name LEFT JOIN household_alerts ha1 ON ha.house_hold_name = ha1.house_hold_name LEFT JOIN household_risk_level rl ON ha.house_hold_name = rl.house_hold_name ORDER BY ha.aum DESC; | K48: Data Not Available | L48: Phase 3 Done | M48: Category: Data Not Available. Household Insights table flagged data-gap; blocked columns: YTD Return, Vs Benchmark, Model Drift, Risk, Last Review, Open Alerts.
A49: Advisor | B49: Household Management Dashboard | C49: Chart | D49: Asset Allocation Overview | E49: Allocation across Equity / Fixed Income / Cash / Other | F49: portfolio/holdings data | G49: Done | I49: CHART-018 | J49: - | K49: Data Available/Calculation Required | L49: 2 - In Progress | M49: Category: Data Available/Calculation Required. Asset Allocation Overview - derivable/calc required in DB. | N49: Yes
A50: Advisor | B50: Household Management Dashboard | C50: Filter/Control | D50: Search / Segment / Status Filters + Sort | E50: Search (household/client/account); Segment (All/Mass Affluent/HNW/UHNW); Status (All/Active/At Risk/New); Sort (AUM/Name/YTD/Cash%) | F50: UI controls | G50: Done | I50: - | J50: - | K50: - | L50: 5 - Insights | M50: Category: -. Search/status/sort is UI; Segment filter & YTD sort depend on blocked data.
A51: Advisor | B51: Household Management Dashboard | C51: Table | D51: Household Listing Table | E51: Cols: Household, Primary client, Segment badge, AUM, # Accounts, Cash %, YTD %, Custodian badges, Status, Start date | F51: dim_household + portfolio metrics | G51: Done | H51: limited details - household->account_summary | I51: TABLE-ADV-HH-03 | J51: WITH latest_snapshot AS ( SELECT MAX(snapshot_date) AS snapshot_date FROM wealth_pulse_insigneo_model.gold.positions ), beginning_snapshot AS ( SELECT MAX(snapshot_date) AS snapshot_date FROM wealth_pulse_insigneo_model.gold.positions WHERE snapshot_date < ( SELECT DATE_TRUNC('year', snapshot_date) FROM latest_snapshot ) ), client_segment AS( SELECT t.house_hold_name, CASE WHEN MAX( CASE WHEN t.entity_name IS NOT NULL AND TRIM(t.entity_name) <> '' THEN 1 ELSE 0 END ) = 1 THEN 'Corporate' WHEN SUM(t.maximum_net_worth) >= 10000000 THEN 'UHNW' WHEN SUM(t.maximum_net_worth) >= 1000000 THEN 'HNW' WHEN SUM(t.maximum_net_worth) IS NOT NULL THEN 'Mass Affluent' WHEN SUM(t.maximum_annual_income) >= 1000000 THEN 'UHNW (Estimated)' WHEN SUM(t.maximum_annual_income) >= 250000 THEN 'HNW (Estimated)' ELSE 'Mass Affluent' END AS client_segment FROM ( SELECT DISTINCT hd.house_hold_name, pa.person_account_id, pa.entity_name, pa.maximum_net_worth, pa.maximum_annual_income FROM wealth_pulse_insigneo_model.gold.positions p JOIN wealth_pulse_insigneo_model.gold.household_details hd ON p.financial_account_id = hd.financial_account_id JOIN wealth_pulse_insigneo_model.gold.person_financial_mapping pfm ON p.financial_account_id = pfm.financial_account_id JOIN wealth_pulse_insigneo_model.gold.person_account pa ON pfm.person_account_id = pa.person_account_id WHERE p.snapshot_date = ( SELECT snapshot_date FROM latest_snapshot ) ) t GROUP BY t.house_hold_name ), beginning_household_aum AS ( SELECT hd.house_hold_name, SUM(p.amount) AS beginning_aum FROM wealth_pulse_insigneo_model.gold.positions p JOIN wealth_pulse_insigneo_model.gold.household_details hd ON p.financial_account_id = hd.financial_account_id JOIN wealth_pulse_insigneo_model.gold.financial_account fa ON fa.financial_account_id = p.financial_account_id WHERE p.snapshot_date = ( SELECT snapshot_date FROM beginning_snapshot ) AND fa.account_status_indicator = 'O' AND fa.is_active = 1 GROUP BY hd.house_hold_name ), current_household_aum AS ( SELECT hd.house_hold_name, SUM(p.amount) AS current_aum FROM wealth_pulse_insigneo_model.gold.positions p JOIN wealth_pulse_insigneo_model.gold.household_details hd ON p.financial_account_id = hd.financial_account_id JOIN wealth_pulse_insigneo_model.gold.financial_account fa ON fa.financial_account_id = p.financial_account_id WHERE p.snapshot_date = ( SELECT snapshot_date FROM latest_snapshot ) AND fa.account_status_indicator = 'O' AND fa.is_active = 1 GROUP BY hd.house_hold_name ), ytd_cte AS ( SELECT c.house_hold_name, c.current_aum, b.beginning_aum, ROUND( ( c.current_aum - b.beginning_aum ) * 100.0 / NULLIF(b.beginning_aum,0), 2 ) AS ytd FROM current_household_aum c JOIN beginning_household_aum b ON c.house_hold_name = b.house_hold_name ), household_cash AS ( SELECT hd.house_hold_name, SUM(ac.cash_available) AS cash_available, COUNT(DISTINCT hd.account_number) AS accounts, MIN(fa.date_account_opened) AS since, STRING_AGG(DISTINCT p.custodian, ', ') AS custodians, CASE WHEN COUNT(CASE WHEN fa.account_status_indicator <> 'O' THEN 1 END)=0 THEN 'Open' ELSE 'Mixed' END AS status FROM wealth_pulse_insigneo_model.gold.positions p JOIN wealth_pulse_insigneo_model.gold.household_details hd ON p.financial_account_id = hd.financial_account_id LEFT JOIN wealth_pulse_insigneo_model.gold.account_summary ac ON p.financial_account_id = ac.financial_account_id JOIN wealth_pulse_insigneo_model.gold.financial_account fa ON p.financial_account_id = fa.financial_account_id WHERE p.snapshot_date = ( SELECT snapshot_date FROM latest_snapshot ) GROUP BY hd.house_hold_name ) -- SELECT * from household_cash SELECT y.house_hold_name AS household, NULL AS segment, y.beginning_aum, y.current_aum AS aum, ac.accounts, ac.custodians, ROUND( ac.cash_available / NULLIF(y.current_aum,0) *100, 2 ) AS cash_pct, y.ytd, ac.status, ac.since FROM ytd_cte y -- LEFT JOIN client_segment cs -- ON y.house_hold_name = y.house_hold_name INNER JOIN household_cash ac ON y.house_hold_name = ac.house_hold_name | K51: Data Not Available | L51: Phase 3 Done | M51: Category: Data Not Available. Household Listing works for AUM/Accounts/Cash%/Custodian/Status; YTD Return % & Segment columns blocked.
A52: Advisor | B52: Household Detail Pages (4 tabs) | C52: KPI | D52: Tab1: Total AUM | E52: Sum of market value across household accounts | F52: fact_position via dim_account.household_id | G52: Done | I52: KPI-001 | J52: SELECT SUM(p.amount) AS total_aum FROM wealth_pulse_insigneo_model.gold.positions p JOIN financial_account a ON p.financial_account_id = a.financial_account_id WHERE p.snapshot_date = ( SELECT MAX(snapshot_date) FROM wealth_pulse_insigneo_model.gold.positions ) AND a.account_status_indicator = 'O' AND a.is_active = 1 | K52: Done | L52: 1 - Done | M52: Category: Done. Total AUM updated in DB.
A53: Advisor | B53: Household Detail Pages (4 tabs) | C53: KPI | D53: Tab1: Cash Position | E53: Liquid cash & % of portfolio | F53: fact_cash_balance + fact_position (KPI-011) | G53: Done | I53: KPI-011 | J53: - | K53: (with new derived table) | L53: 2 - In Progress | M53: Category: (with new derived table). Cash Position via new derived table. | N53: Yes
A54: Advisor | B54: Household Detail Pages (4 tabs) | C54: Table | D54: Tab1: Account Summary Table | E54: Cols: Account Name, Custodian, Registration, AUM, Model, Cash %, Status | F54: dim_account + fact_position | G54: Done | H54: limited details - household->account_summary | I54: TABLE-ADV-ACCT-01 | J54: WITH latest_snapshot AS ( SELECT MAX(snapshot_date) AS snapshot_date FROM wealth_pulse_insigneo_model.gold.positions ), account_aum AS ( SELECT hd.house_hold_name, hd.account_number, p.financial_account_id, SUM(p.amount) AS aum FROM wealth_pulse_insigneo_model.gold.positions p JOIN wealth_pulse_insigneo_model.gold.household_details hd ON p.financial_account_id = hd.financial_account_id JOIN wealth_pulse_insigneo_model.gold.financial_account fa ON p.financial_account_id = fa.financial_account_id WHERE p.snapshot_date = ( SELECT snapshot_date FROM latest_snapshot ) AND fa.account_status_indicator = 'O' AND fa.is_active = 1 AND hd.house_hold_name = 'CYGNUS' GROUP BY hd.house_hold_name, hd.account_number, p.financial_account_id ) SELECT aa.house_hold_name, aa.account_number, MAX(fa.account_short_name) AS account_name, MAX(aa.aum) AS aum, COUNT(DISTINCT p.custodian) AS custodians, STRING_AGG(DISTINCT fa.registration_type, ', ') AS registration, STRING_AGG( DISTINCT COALESCE(mp.model_name, 'No Model Assigned'), ', ' ) AS model, MAX(COALESCE(ac.cash_available, 0)) AS available, ROUND( MAX(COALESCE(ac.cash_available, 0)) * 100.0 / NULLIF(MAX(aa.aum), 0), 2 ) AS cash_pct, CASE WHEN MAX(fa.account_status_indicator) = 'O' THEN 'Open' WHEN MAX(fa.account_status_indicator) = 'C' THEN 'Closed' ELSE MAX(fa.account_status_indicator) END AS status FROM account_aum aa JOIN wealth_pulse_insigneo_model.gold.financial_account fa ON aa.financial_account_id = fa.financial_account_id JOIN wealth_pulse_insigneo_model.gold.positions p ON aa.financial_account_id = p.financial_account_id AND p.snapshot_date = ( SELECT snapshot_date FROM latest_snapshot ) LEFT JOIN wealth_pulse_insigneo_model.gold.account_summary ac ON aa.financial_account_id = ac.financial_account_id LEFT JOIN wealth_pulse_insigneo_model.silver.account_model_mapping mam ON aa.account_number = mam.account_number LEFT JOIN wealth_pulse_insigneo_model.gold.dim_model_portfolio mp ON mam.model_id = mp.model_id GROUP BY aa.house_hold_name, aa.account_number ORDER BY aa.account_number; | K54: Data Not Available | L54: Phase 3 Done | M54: Category: Data Not Available. Account Summary works for Custodian/Registration/Status; Account AUM, Cash Balance, Cash %, Model columns blocked.
A55: Advisor | B55: Household Detail Pages (4 tabs) | C55: KPI | D55: Tab1: Accounts | E55: Count of active accounts linked to household | F55: COUNT dim_account (ACTIVE) | G55: Done | I55: KPI-007 | J55: SELECT COUNT(DISTINCT financial_account_id) AS account_count FROM financial_account WHERE is_active = 1 AND account_status_indicator = 'O' | K55: Done | L55: 1 - Done | M55: Category: Done. Accounts count updated in DB.
A56: Advisor | B56: Household Detail Pages (4 tabs) | C56: Chart | D56: Tab1: Asset Allocation Donut | E56: Distribution across asset classes | F56: fact_position.asset_class grouped | G56: Done | I56: CHART-018 | J56: - | K56: Data Available/Calculation Required | L56: 2 - In Progress | M56: Category: Data Available/Calculation Required. Asset Allocation Donut - derivable/calc required in DB. | N56: Yes
A57: Advisor | B57: Portfolio Analytics Dashboard | C57: Table | D57: Performance Summary (CHART-011) | E57: Total Return, Benchmark Return, Alpha across MTD/QTD/YTD/1Y; negative alpha red | F57: fact_performance + Yahoo Finance | G57: Done | H57: fact_performance, benchmark return by API, partial (calulation is not performed) / expected from the source side. | I57: CHART-011 | J57: WITH latest_snapshot AS ( SELECT MAX(snapshot_date) AS snapshot_date FROM wealth_pulse_insigneo_model.gold.positions ), account_market_value AS ( SELECT account_number, SUM(ABS(amount)) AS market_value FROM wealth_pulse_insigneo_model.gold.positions WHERE snapshot_date = ( SELECT snapshot_date FROM latest_snapshot ) GROUP BY account_number ), performance_summary AS ( SELECT fp.period_type, SUM(fp.twr_return * amv.market_value) / NULLIF(SUM(amv.market_value),0) AS twr_return, SUM(fp.benchmark_return * amv.market_value) / NULLIF(SUM(amv.market_value),0) AS benchmark_return, SUM(fp.alpha * amv.market_value) / NULLIF(SUM(amv.market_value),0) AS alpha FROM wealth_pulse_insigneo_model.gold.fact_performance fp INNER JOIN account_market_value amv ON fp.account_number = amv.account_number WHERE fp.period_end_date = ( SELECT snapshot_date FROM latest_snapshot ) AND fp.period_type IN ('MTD','QTD','YTD','1YR') GROUP BY fp.period_type ) SELECT 'Total Return' AS Metric, MAX(CASE WHEN period_type='MTD' THEN twr_return END) AS `1 Month`, MAX(CASE WHEN period_type='QTD' THEN twr_return END) AS `3 Month`, MAX(CASE WHEN period_type='YTD' THEN twr_return END) AS `YTD`, MAX(CASE WHEN period_type='1YR' THEN twr_return END) AS `1 Year` FROM performance_summary UNION ALL SELECT 'S&P 500 (Benchmark)', MAX(CASE WHEN period_type='MTD' THEN benchmark_return END), MAX(CASE WHEN period_type='QTD' THEN benchmark_return END), MAX(CASE WHEN period_type='YTD' THEN benchmark_return END), MAX(CASE WHEN period_type='1YR' THEN benchmark_return END) FROM performance_summary UNION ALL SELECT 'Alpha', MAX(CASE WHEN period_type='MTD' THEN alpha END), MAX(CASE WHEN period_type='QTD' THEN alpha END), MAX(CASE WHEN period_type='YTD' THEN alpha END), MAX(CASE WHEN period_type='1YR' THEN alpha END) FROM performance_summary; | K57: Data Available/Calculation Required | L57: Phase 3 WIP | M57: Category: Data Available/Calculation Required. Performance Summary - calc/derivation required; confirm TWR/Alpha/Sharpe source with Aman.
A58: Advisor | B58: Household Detail Pages (4 tabs) | C58: Table | D58: Tab2: Position Table | E58: Cols: Ticker, Security Name, Type, Asset Class, Shares, Price, Market Value, Cost Basis, Unrealized G/L, % of Account, Holding | F58: fact_position + dim_security | G58: Done | I58: TABLE-ADV-PORT-03 | J58: WITH latest_snapshot AS ( SELECT MAX(snapshot_date) AS snapshot_date FROM wealth_pulse_insigneo_model.gold.positions ), latest_positions AS ( SELECT p.financial_account_id, p.account_number, p.cusip, p.quantity, p.price, p.amount, p.total_cost, p.account_type, p.snapshot_date FROM wealth_pulse_insigneo_model.gold.positions p WHERE p.snapshot_date = ( SELECT snapshot_date FROM latest_snapshot ) ) SELECT hd.house_hold_name, lp.account_number, fa.account_short_name, s.ticker, s.asset_name AS security_name, lp.account_type AS type, s.asset_class, lp.quantity AS shares, lp.price, lp.amount AS market_value, lp.total_cost AS cost_basis, (lp.amount - lp.total_cost) AS unrealized_gl, ROUND( lp.amount * 100.0 / NULLIF( SUM(lp.amount) OVER (PARTITION BY lp.account_number), 0 ), 2 ) AS pct_acct, ROUND( lp.amount * 100.0 / NULLIF( SUM(lp.amount) OVER (PARTITION BY hd.house_hold_name), 0 ), 2 ) AS holding FROM latest_positions lp JOIN wealth_pulse_insigneo_model.gold.household_details hd ON lp.financial_account_id = hd.financial_account_id JOIN wealth_pulse_insigneo_model.gold.financial_account fa ON lp.financial_account_id = fa.financial_account_id LEFT JOIN wealth_pulse_insigneo_model.gold.securities s ON lp.cusip = s.cusip WHERE hd.house_hold_name = 'AURORA' AND fa.account_status_indicator = 'O' AND fa.is_active = 1 ORDER BY lp.account_number, market_value DESC; | K58: Data Not Available | L58: 2 - In Progress | M58: Category: Data Not Available. Position table works for Ticker/Name/Type/Shares/Price/MV; Cost Basis & Unrealized G/L columns blocked.
A59: Advisor | B59: Portfolio Analytics Dashboard | C59: Table | D59: Top Holdings / Extended Holdings (1-20) | E59: Rank, Ticker, Security, Market Value, % of portfolio, Unrealized G/L, status; concentration alerts | F59: fact_position + dim_security | G59: Done | H59: previous KPIs | I59: TABLE-ADV-PORT-01 | J59: WITH latest_position AS ( SELECT * FROM wealth_pulse_insigneo_model.gold.positions WHERE snapshot_date = ( SELECT MAX(snapshot_date) FROM wealth_pulse_insigneo_model.gold.positions ) ), book_aum AS ( SELECT SUM(trade_date_net_worth) AS total_aum FROM wealth_pulse_insigneo_model.gold.account_summary WHERE investment_professional_number = 'C54' ), holdings_by_cusip AS ( SELECT p.cusip, SUM(p.amount) AS market_value, SUM(p.total_cost) AS total_cost, SUM(p.amount - p.total_cost) AS unrealized_gl FROM latest_position p JOIN wealth_pulse_insigneo_model.gold.financial_account f ON p.financial_account_id = f.financial_account_id WHERE p.cusip IS NOT NULL AND TRIM(p.cusip) <> '' AND f.investment_professional_number = 'C54' GROUP BY p.cusip ), ranked_holdings AS ( SELECT h.cusip, s.ticker, s.asset_name AS security_name, h.market_value, h.total_cost, h.unrealized_gl, ROUND( h.market_value / NULLIF(b.total_aum, 0) * 100, 2 ) AS pct_of_book, ROUND( h.unrealized_gl / NULLIF(h.total_cost, 0) * 100, 2 ) AS unrealized_gl_pct, CASE WHEN h.market_value / NULLIF(b.total_aum, 0) > 0.10 THEN 'Over 10%' ELSE NULL END AS concentration_badge, ROW_NUMBER() OVER (ORDER BY h.market_value DESC) AS rank FROM holdings_by_cusip h CROSS JOIN book_aum b LEFT JOIN wealth_pulse_insigneo_model.gold.securities s ON h.cusip = s.cusip AND s.is_active = 1 ) SELECT rank, cusip, ticker, security_name, ROUND(market_value, 2) AS market_value, pct_of_book, unrealized_gl_pct, concentration_badge FROM ranked_holdings WHERE rank <= 20 ORDER BY rank; | K59: Data Not Available | L59: Phase 3 Done | M59: Category: Data Not Available. Top Holdings - rank/%-of-book available; Market Value flagged & Unrealized G/L $/% columns blocked.
A60: Advisor | B60: Household Detail Pages (4 tabs) | C60: Table | D60: Tab3: Activity Table | E60: Cols: Date, Account, Custodian, Type, Security, Qty, Price, Net Amount + Period/Custodian/Type filters | F60: fact_transaction + dim_security | G60: Done | I60: - | J60: WITH latest_snapshot AS ( SELECT MAX(snapshot_date) AS end_date FROM wealth_pulse_insigneo_model.gold.positions ), date_filter AS ( SELECT end_date, DATE_SUB(end_date, 30) AS start_date FROM latest_snapshot ), account_details AS ( SELECT account_number, MAX(account_short_name) AS account_short_name, MAX(registration_type) AS registration_type FROM wealth_pulse_insigneo_model.gold.financial_account WHERE account_status_indicator = 'O' AND is_active = 1 GROUP BY account_number ), household_transactions AS ( SELECT hd.house_hold_name, t.transaction_date, t.financial_account_id, t.account_number, t.custodian, t.cusip, t.quantity, t.price, t.amount FROM wealth_pulse_insigneo_model.gold.transactions t JOIN wealth_pulse_insigneo_model.gold.household_details hd ON t.financial_account_id = hd.financial_account_id JOIN wealth_pulse_insigneo_model.gold.financial_account fa ON t.financial_account_id = fa.financial_account_id WHERE hd.house_hold_name = 'SAPPHIRE' AND fa.account_status_indicator = 'O' AND fa.is_active = 1 AND t.transaction_date BETWEEN (SELECT start_date FROM date_filter) AND (SELECT end_date FROM date_filter) ) SELECT ht.transaction_date AS Date, ad.account_short_name AS Account, ht.custodian AS Custodian, ad.registration_type AS Registration, COALESCE(MAX(s.asset_name), ht.cusip) AS Security, ht.quantity AS Qty, ht.price AS Price, ht.amount AS `Net Amount` FROM household_transactions ht JOIN account_details ad ON ht.account_number = ad.account_number LEFT JOIN wealth_pulse_insigneo_model.gold.securities s ON ht.cusip = s.cusip GROUP BY ht.transaction_date, ad.account_short_name, ad.registration_type, ht.custodian, ht.cusip, ht.quantity, ht.price, ht.amount ORDER BY ht.transaction_date DESC, ad.account_short_name; | K60: Done | L60: 1 - Done | M60: Category: Done. Activity (transactions) available - updated in DB.
A61: Advisor | B61: Household Detail Pages (4 tabs) | C61: Section | D61: Tab4: Tax Lot Summary | E61: Unrealized G/L split by holding period (long/short) | F61: fact_position holding_period | G61: Done | I61: CHART-015 | J61: - | K61: Data Not Available | L61: 2 - In Progress | M61: Category: Data Not Available. Tax Lot Summary - needs unrealized G/L, cost basis & holding period, not in Insigneo. | O61: 46216
A62: Advisor | B62: Household Detail Pages (4 tabs) | C62: Chart | D62: Tab4: Custodian Distribution Chart | E62: Share of portfolio value across custodians | F62: fact_position grouped by source_custodian | G62: Done | I62: CHART-016 | J62: SELECT p.custodian AS custodian, SUM(p.market_value) AS aum FROM positions p JOIN household_details h ON p.financial_account_id = h.financial_account_id WHERE h.id = :id AND p.snapshot_date = (SELECT MAX(sp.snapshot_date) FROM positions sp JOIN household_details sh ON sp.financial_account_id = sh.financial_account_id WHERE sh.id = :household_id) GROUP BY p.custodian ORDER BY aum DESC; | K62: Done | L62: 1 - Done | M62: Category: Done. Custodian Distribution donut; validate vs Insigneo (flagged 'Doubt').
A63: Advisor | B63: Portfolio Analytics Dashboard | C63: Filter/Control | D63: Scope & Compare Controls | E63: Scope (Book/Team/Household/Model/Segment); Compare (Model Target / Prev vs Current Qtr / Benchmark S&P500) | F63: config + Yahoo Finance API | G63: Done | I63: - | J63: - | K63: - | L63: 5 - Insights | M63: Category: -. Scope/Compare control; benchmark via Yahoo API, model-target compare needs config.
A64: Advisor | B64: Portfolio Analytics Dashboard | C64: Chart | D64: Asset Allocation - Current vs Target (CHART-008) | E64: Grouped bars current vs comparison + delta row; Gold asset_class enums | F64: fact_position + model config | G64: Done | I64: CHART-008 | J64: WITH latest_snapshot AS ( SELECT MAX(snapshot_date) AS snapshot_date FROM wealth_pulse_insigneo_model.gold.positions ), account_aum AS ( SELECT hd.house_hold_name, hd.account_number, SUM(p.amount) AS account_aum FROM wealth_pulse_insigneo_model.gold.positions p JOIN wealth_pulse_insigneo_model.gold.household_details hd ON p.financial_account_id = hd.financial_account_id JOIN wealth_pulse_insigneo_model.gold.financial_account fa ON p.financial_account_id = fa.financial_account_id WHERE p.snapshot_date = ( SELECT snapshot_date FROM latest_snapshot ) AND hd.house_hold_name = 'AURORA' AND fa.account_status_indicator = 'O' AND fa.is_active = 1 GROUP BY hd.house_hold_name, hd.account_number ), current_allocation AS ( SELECT s.asset_class, ROUND( SUM(ABS(p.amount))*100.0/ SUM(SUM(ABS(p.amount))) OVER(), 2 ) AS current_pct FROM wealth_pulse_insigneo_model.gold.positions p JOIN wealth_pulse_insigneo_model.gold.household_details hd ON p.financial_account_id=hd.financial_account_id JOIN wealth_pulse_insigneo_model.gold.financial_account fa ON p.financial_account_id=fa.financial_account_id JOIN wealth_pulse_insigneo_model.gold.securities s ON p.cusip=s.cusip WHERE p.snapshot_date=( SELECT snapshot_date FROM latest_snapshot ) AND hd.house_hold_name='AURORA' AND fa.account_status_indicator='O' AND fa.is_active=1 GROUP BY s.asset_class ), target_allocation AS ( SELECT SUM(aa.account_aum*dmp.target_equity_pct) /SUM(aa.account_aum) AS target_equity, SUM(aa.account_aum*dmp.target_fi_pct) /SUM(aa.account_aum) AS target_fi, SUM(aa.account_aum*dmp.target_alt_pct) /SUM(aa.account_aum) AS target_alt, SUM(aa.account_aum*dmp.target_cash_pct) /SUM(aa.account_aum) AS target_cash FROM account_aum aa JOIN wealth_pulse_insigneo_model.silver.account_model_mapping mam ON aa.account_number=mam.account_number JOIN wealth_pulse_insigneo_model.gold.dim_model_portfolio dmp ON mam.model_id=dmp.model_id ) SELECT 'Equity' AS asset, COALESCE(MAX(CASE WHEN asset_class='Equity' THEN current_pct END),0) AS current, ROUND(MAX(target_equity),2) AS target FROM current_allocation CROSS JOIN target_allocation UNION ALL SELECT 'Fixed Income', COALESCE(MAX(CASE WHEN asset_class='Fixed Income' THEN current_pct END),0), ROUND(MAX(target_fi),2) FROM current_allocation CROSS JOIN target_allocation UNION ALL SELECT 'Alternative', COALESCE(MAX(CASE WHEN asset_class='Alternative' THEN current_pct END),0), ROUND(MAX(target_alt),2) FROM current_allocation CROSS JOIN target_allocation UNION ALL SELECT 'Cash', COALESCE(MAX(CASE WHEN asset_class='Cash' THEN current_pct END),0), ROUND(MAX(target_cash),2) FROM current_allocation CROSS JOIN target_allocation; | K64: Done | L64: 1 - Done | M64: Category: Done. Allocation Current vs Target; sub-asset-class classification to validate ('Doubt').
A65: Advisor | B65: Advisor Home Dashboard | C65: Widget | D65: Portfolio Health | E65: % households aligned to model, drifting accounts, circular progress | F65: Accounts within ±5% drift / total | G65: Done | H65: dim_model_portfolio | I65: KPI-070 | J65: WITH latest_snapshot AS ( SELECT MAX(snapshot_date) AS max_snapshot_date FROM wealth_pulse_insigneo_model.gold.positions ), /* Account level equity allocation and AUM */ account_base AS ( SELECT ac.financial_account_id, fa.account_number, fa.investment_professional_number, h.house_hold_name, ac.total_equity, p.amount AS account_aum FROM wealth_pulse_insigneo_model.gold.account_summary ac JOIN wealth_pulse_insigneo_model.gold.financial_account fa ON ac.financial_account_id = fa.financial_account_id JOIN wealth_pulse_insigneo_model.gold.positions p ON p.financial_account_id = ac.financial_account_id JOIN wealth_pulse_insigneo_model.gold.household_details h ON ac.financial_account_id = h.financial_account_id ), /* Account model assignment + drift calculation */ account_health AS ( SELECT ab.investment_professional_number, ab.house_hold_name, ab.account_number, amm.model_id, ABS( ( ab.total_equity * 100.0 / NULLIF(ab.account_aum,0) ) - dmp.target_equity_pct ) AS drift_pct, COALESCE( dmp.drift_threshold_pct, 5 ) AS drift_threshold_pct FROM account_base ab LEFT JOIN wealth_pulse_insigneo_model.silver.account_model_mapping amm ON ab.account_number = amm.account_number LEFT JOIN wealth_pulse_insigneo_model.gold.dim_model_portfolio dmp ON amm.model_id = dmp.model_id ), /* Household health evaluation */ household_health AS ( SELECT investment_professional_number, house_hold_name, COUNT( CASE WHEN model_id IS NULL THEN 1 END ) AS unmodeled_accounts, COUNT( CASE WHEN drift_pct > COALESCE(drift_threshold_pct, 0.05) THEN 1 END ) AS drifting_accounts FROM account_health GROUP BY investment_professional_number, house_hold_name ) SELECT investment_professional_number AS advisor, COUNT( CASE WHEN unmodeled_accounts = 0 AND drifting_accounts = 0 THEN 1 END ) AS healthy_households, COUNT(*) AS total_households, COUNT( CASE WHEN unmodeled_accounts = 0 AND drifting_accounts = 0 THEN 1 END ) * 100.0 / NULLIF(COUNT(*),0) AS portfolio_health_pct FROM household_health GROUP BY investment_professional_number; | K65: Data Not Available | L65: Phase 3 Done | M65: Category: Data Not Available. Portfolio Health % - needs model-portfolio & drift, not in Insigneo.
A66: Advisor | B66: Portfolio Analytics Dashboard | C66: Chart | D66: Top 20 Holdings Concentration Map (CHART-010) | E66: Top 20 by MV, % of book bar, >10% red badge | F66: SUM(market_value) by cusip | G66: Done | I66: CHART-010 | J66: WITH latest_snapshot AS ( SELECT MAX(snapshot_date) AS snapshot_date FROM wealth_pulse_insigneo_model.gold.positions ), book_total AS ( SELECT SUM(p.amount) AS total_mv FROM wealth_pulse_insigneo_model.gold.positions p JOIN wealth_pulse_insigneo_model.gold.household_details hd ON p.financial_account_id = hd.financial_account_id JOIN wealth_pulse_insigneo_model.gold.financial_account fa ON p.financial_account_id = fa.financial_account_id WHERE hd.house_hold_name = 'AURORA' AND p.snapshot_date = ( SELECT snapshot_date FROM latest_snapshot ) AND fa.account_status_indicator = 'O' AND fa.is_active = 1 ), rolled AS ( SELECT p.cusip, MAX(s.ticker) AS ticker, MAX(s.asset_name) AS asset_name, SUM(p.amount) AS market_value, SUM(p.total_cost) AS cost_basis, SUM(p.amount) - SUM(p.total_cost) AS unrealized_gl FROM wealth_pulse_insigneo_model.gold.positions p JOIN wealth_pulse_insigneo_model.gold.household_details hd ON p.financial_account_id = hd.financial_account_id JOIN wealth_pulse_insigneo_model.gold.financial_account fa ON p.financial_account_id = fa.financial_account_id LEFT JOIN wealth_pulse_insigneo_model.gold.securities s ON p.cusip = s.cusip WHERE hd.house_hold_name = 'AURORA' AND p.snapshot_date = ( SELECT snapshot_date FROM latest_snapshot ) AND fa.account_status_indicator = 'O' AND fa.is_active = 1 GROUP BY p.cusip ) SELECT ROW_NUMBER() OVER (ORDER BY r.market_value DESC) AS rank, r.cusip, r.ticker, r.asset_name, ROUND(r.market_value, 2) AS market_value, ROUND(r.cost_basis, 2) AS cost_basis, ROUND(r.unrealized_gl, 2) AS unrealized_gain_loss, ROUND( r.market_value * 100.0 / NULLIF(bt.total_mv, 0), 2 ) AS pct_of_book, CASE WHEN r.market_value * 100.0 / NULLIF(bt.total_mv, 0) > 10 THEN 'RED' ELSE 'NORMAL' END AS concentration_flag FROM rolled r CROSS JOIN book_total bt ORDER BY r.market_value DESC LIMIT 20; | K66: Data Not Available | L66: 2 - Logic can be driven | M66: Category: Data Not Available. Top 20 Concentration Map - query/logic fix needed (data available).
A67: Advisor | B67: Advisor Home Dashboard | C67: Widget | D67: Client Engagement | E67: Meeting completion %, overdue reviews, circular progress | F67: fact_client_360 | G67: Done | H67: days_since_last_meeting not provided | I67: KPI-071 | J67: - | K67: Data Not Available | L67: Phase 3 Cannot be Achieable | M67: Category: Data Not Available. Client Engagement - needs meeting/last-meeting data, not in Insigneo. | P67: Data Not Available, Scoped for a agents
A68: Advisor | B68: Portfolio Analytics Dashboard | C68: KPI | D68: Risk Card - Top 10 Concentration % | E68: Combined exposure of top 10 holdings (threshold 40%) | F68: AUM-weighted | G68: Done | I68: KPI-034 | J68: WITH latest_snapshot AS ( SELECT MAX(snapshot_date) AS snapshot_date FROM wealth_pulse_insigneo_model.gold.positions ), holdings AS ( SELECT UPPER( COALESCE( NULLIF(TRIM(s.ticker), ''), NULLIF(TRIM(p.cusip), '') ) ) AS position_key, SUM(p.amount) AS market_value FROM wealth_pulse_insigneo_model.gold.positions p JOIN wealth_pulse_insigneo_model.gold.household_details hd ON p.financial_account_id = hd.financial_account_id JOIN wealth_pulse_insigneo_model.gold.financial_account fa ON p.financial_account_id = fa.financial_account_id LEFT JOIN wealth_pulse_insigneo_model.gold.securities s ON p.cusip = s.cusip WHERE hd.house_hold_name = 'CYGNUS' AND p.snapshot_date = ( SELECT MAX(snapshot_date) FROM wealth_pulse_insigneo_model.gold.positions ) AND fa.account_status_indicator = 'O' AND fa.is_active = 1 GROUP BY UPPER( COALESCE( NULLIF(TRIM(s.ticker), ''), NULLIF(TRIM(p.cusip), '') ) ) ), ranked AS ( SELECT market_value, ROW_NUMBER() OVER (ORDER BY market_value DESC) AS rn FROM holdings ) SELECT ROUND( ( SELECT SUM(market_value) FROM ranked WHERE rn <= 10 ) * 100.0 / ( SELECT SUM(market_value) FROM holdings ), 2 ) AS top10_concentration_pct; | K68: Done | L68: 1 - Done | M68: Category: Done. Top 10 Concentration updated in DB.
A69: Advisor | B69: Portfolio Analytics Dashboard | C69: KPI | D69: Risk Card - Single Position Max % | E69: Largest single position exposure + security | F69: highest % of book | G69: Done | I69: KPI-035 | J69: WITH latest_snapshot AS ( SELECT MAX(snapshot_date) AS snapshot_date FROM wealth_pulse_insigneo_model.gold.positions ), holdings AS ( SELECT UPPER( COALESCE( NULLIF(TRIM(s.ticker), ''), NULLIF(TRIM(p.cusip), '') ) ) AS position_key, SUM(p.amount) AS market_value FROM wealth_pulse_insigneo_model.gold.positions p JOIN wealth_pulse_insigneo_model.gold.household_details hd ON p.financial_account_id = hd.financial_account_id JOIN wealth_pulse_insigneo_model.gold.financial_account fa ON p.financial_account_id = fa.financial_account_id LEFT JOIN wealth_pulse_insigneo_model.gold.securities s ON p.cusip = s.cusip WHERE hd.house_hold_name = 'AURORA' AND p.snapshot_date = ( SELECT snapshot_date FROM latest_snapshot ) AND fa.account_status_indicator = 'O' AND fa.is_active = 1 GROUP BY UPPER( COALESCE( NULLIF(TRIM(s.ticker), ''), NULLIF(TRIM(p.cusip), '') ) ) ) SELECT ROUND( MAX(market_value) * 100.0 / NULLIF(SUM(market_value), 0), 2 ) AS max_concentration_pct FROM holdings; | K69: Done | L69: 1 - Done | M69: Category: Done. Single Position Max updated in DB.
A70: Advisor | B70: Portfolio Analytics Dashboard | C70: KPI | D70: Risk Card - Cash Drag (bps) | E70: Return impact of idle cash | F70: cash_pct × 5% × 100 | G70: Done | I70: KPI-014 | J70: WITH latest_snapshot AS ( SELECT MAX(snapshot_date) AS snapshot_date FROM wealth_pulse_insigneo_model.gold.positions ), account_mv AS ( SELECT p.financial_account_id, SUM(p.amount) AS market_value FROM wealth_pulse_insigneo_model.gold.positions p WHERE p.snapshot_date = ( SELECT snapshot_date FROM latest_snapshot ) GROUP BY p.financial_account_id ), acct_cash AS ( SELECT a.financial_account_id, a.account_number, a.cash_available, mv.market_value, a.cash_available / NULLIF(mv.market_value, 0) AS cash_pct FROM wealth_pulse_insigneo_model.gold.account_summary a JOIN account_mv mv ON a.financial_account_id = mv.financial_account_id JOIN wealth_pulse_insigneo_model.gold.household_details hd ON a.financial_account_id = hd.financial_account_id JOIN wealth_pulse_insigneo_model.gold.financial_account fa ON a.financial_account_id = fa.financial_account_id WHERE hd.house_hold_name = @house_hold_name AND fa.account_status_indicator = 'O' AND fa.is_active = 1 ) SELECT ROUND( ( AVG(cash_pct) - 0.03 ) * ( @equity_benchmark_return - @money_market_rate ) * 10000, 2 ) AS cash_drag_bps FROM acct_cash WHERE cash_pct > 0.03; | K70: (with new derived table) | L70: 2 - In Progress | M70: Category: (with new derived table). Cash Drag via new derived table. | N70: Yes
A71: Advisor | B71: Advisor Home Dashboard | C71: Widget | D71: Risk Alerts | E71: Counts of critical / warning / opportunity items | F71: Signal/Insights framework | G71: Done | H71: dim_model_portfolio | I71: KPI-072 | J71: WITH latest_snapshot AS ( SELECT MAX(snapshot_date) AS max_snapshot_date FROM wealth_pulse_insigneo_model.gold.positions ), /* Account level AUM and cash allocation */ account_metrics_base AS ( SELECT ac.financial_account_id, ( COALESCE(ac.trade_date_net_worth,0) + COALESCE(ac.cash_available,0) ) AS account_aum, CASE WHEN ( COALESCE(ac.trade_date_net_worth,0) + COALESCE(ac.cash_available,0) ) = 0 THEN 0 ELSE ac.cash_available * 100.0 / ( COALESCE(ac.trade_date_net_worth,0) + COALESCE(ac.cash_available,0) ) END AS cash_pct FROM wealth_pulse_insigneo_model.gold.account_summary ac ), /* Security concentration per account */ security_concentration AS ( SELECT p.financial_account_id, MAX( ABS(p.amount) * 100.0 / NULLIF(am.account_aum,0) ) AS max_position_pct FROM wealth_pulse_insigneo_model.gold.positions p JOIN account_metrics_base am ON p.financial_account_id = am.financial_account_id CROSS JOIN latest_snapshot l WHERE p.snapshot_date = l.max_snapshot_date GROUP BY p.financial_account_id ), /* Unrealized gain/loss */ account_pnl AS ( SELECT financial_account_id, SUM( amount - total_cost ) AS unrealized_gl FROM wealth_pulse_insigneo_model.gold.positions CROSS JOIN latest_snapshot l WHERE snapshot_date = l.max_snapshot_date GROUP BY financial_account_id ), /* Model drift calculation */ account_drift AS ( SELECT ac.financial_account_id, ABS( ( ac.total_equity * 100.0 / NULLIF( ( COALESCE(ac.trade_date_net_worth,0) + COALESCE(ac.cash_available,0) ), 0 ) ) - dmp.target_equity_pct ) AS drift_pct FROM wealth_pulse_insigneo_model.gold.account_summary ac JOIN wealth_pulse_insigneo_model.gold.financial_account fa ON ac.financial_account_id = fa.financial_account_id JOIN wealth_pulse_insigneo_model.silver.account_model_mapping amm ON amm.account_number = fa.account_number JOIN wealth_pulse_insigneo_model.gold.dim_model_portfolio dmp ON dmp.model_id = amm.model_id ), /* Combine all account-level metrics */ account_alert_metrics AS ( SELECT fa.investment_professional_number, sc.max_position_pct, d.drift_pct, am.cash_pct, pnl.unrealized_gl FROM account_metrics_base am JOIN wealth_pulse_insigneo_model.gold.financial_account fa ON am.financial_account_id = fa.financial_account_id LEFT JOIN security_concentration sc ON am.financial_account_id = sc.financial_account_id LEFT JOIN account_drift d ON am.financial_account_id = d.financial_account_id LEFT JOIN account_pnl pnl ON am.financial_account_id = pnl.financial_account_id ) SELECT investment_professional_number AS advisor, /* CRITICAL ALERTS */ COUNT( CASE WHEN max_position_pct > 10 OR drift_pct > 8 THEN 1 END ) AS critical_alerts, /* WARNING ALERTS */ COUNT( CASE WHEN drift_pct > 4 OR cash_pct > 10 THEN 1 END ) AS warning_alerts, /* OPPORTUNITY ALERTS */ COUNT( CASE WHEN unrealized_gl < -5000 THEN 1 END ) AS opportunity_alerts FROM account_alert_metrics GROUP BY investment_professional_number; | K71: Data Not Available | L71: Phase 3 Done | M71: Category: Data Not Available. Risk Alerts - needs multi-signal risk data, not in Insigneo.
A72: Advisor | B72: Advisor Home Dashboard | C72: Widget | D72: Upcoming Activities | E72: Upcoming meetings, report reminders, review due dates | F72: Calendar/events | G72: Done | H72: days_since_last_meeting not provided | I72: - | J72: - | K72: Data Not Available | L72: Phase 3 Cannot be Achieable | M72: Category: Data Not Available. Upcoming Activities - no meeting/review calendar data in Insigneo. | P72: Data Not Available, Scoped for a agents
A73: Advisor | B73: Market News & Portfolio Intelligence (Placeholder) | C73: Panel | D73: Market News Placeholder | E73: Static 'Coming Soon' market news container | F73: Placeholder | G73: Done | I73: - | J73: - | K73: - | L73: 5 - Insights | M73: Category: -. Market News placeholder.
A74: Advisor | B74: Market News & Portfolio Intelligence (Placeholder) | C74: Panel | D74: Portfolio Intelligence Panel Placeholder | E74: Framework for future real-time signals / AI recs (Epic 26, Stage 2) | F74: Placeholder (US 16011) | G74: Done | I74: - | J74: - | K74: - | L74: 5 - Insights | M74: Category: -. Portfolio Intelligence placeholder.
A75: Advisor | B75: Action Items & Alerts Screen | C75: KPI | D75: Critical / Warnings / Opportunities / Informational counts | E75: 4 summary counters by insight severity (clickable filters) | F75: Insights Portal framework | G75: Ready for Testing | I75: - | J75: - | K75: Data Available/Calculation Required | L75: 5 - Insights | M75: Category: Data Available/Calculation Required. Insight counts - Insights framework; drivable for available signals, risk/engagement-based counts blocked.
A76: Advisor | B76: Action Items & Alerts Screen | C76: Filter/Control | D76: Category Tabs + Show Dismissed | E76: All/Critical/Warnings/Opportunities/Informational tabs; show-dismissed toggle | F76: UI controls | G76: Ready for Testing | I76: - | J76: - | K76: - | L76: 5 - Insights | M76: Category: -. Category tabs - UI control.
A77: Advisor | B77: Action Items & Alerts Screen | C77: Section | D77: Insight Cards List | E77: Each card: Severity, Title, Description (what+why), Key Data Points, Affected Entity, Recommendation, Timestamp + actions (View HH/Dismiss/Resolve) | F77: Insights framework | G77: Ready for Testing | I77: - | J77: - | K77: Data Available/Calculation Required | L77: 5 - Insights | M77: Category: Data Available/Calculation Required. Insight cards - Insights framework build; content depends on signals (some blocked).
A78: Advisor | B78: Priority Actions Panel (Framework) | C78: Section | D78: Workflow Queue Sections | E78: High Priority / Upcoming / In Progress / Completed queues | F78: Seeded + Stage-2 agent outputs | G78: New | I78: - | J78: - | K78: - | L78: 5 - Insights | M78: Category: -. Workflow queue - Stage-2 framework.
A79: Advisor | B79: Priority Actions Panel (Framework) | C79: Section | D79: Action Cards | E79: Action title, priority, category, related client/HH, due date, source; interactions (open/complete/snooze) | F79: Prioritization framework | G79: New | I79: - | J79: - | K79: - | L79: 5 - Insights | M79: Category: -. Action cards - Stage-2 framework.
A80: Advisor | B80: Portfolio Analytics Dashboard | C80: KPI | D80: Concentration Analysis - Top 10 Positions | I80: - | J80: WITH latest_snapshot AS ( SELECT MAX(snapshot_date) AS snapshot_date FROM wealth_pulse_insigneo_model.gold.positions ), latest_positions AS ( SELECT p.financial_account_id, p.account_number, p.cusip, p.amount AS market_value FROM wealth_pulse_insigneo_model.gold.positions p WHERE p.snapshot_date = (SELECT snapshot_date FROM latest_snapshot) ), hh_positions AS ( SELECT hd.house_hold_name, COALESCE(NULLIF(TRIM(s.ticker), ''), NULLIF(TRIM(lp.cusip), '')) AS position_key, COALESCE(NULLIF(TRIM(s.ticker), ''), lp.cusip) AS ticker, COALESCE(s.asset_name, '—') AS security_name, lp.market_value FROM latest_positions lp JOIN wealth_pulse_insigneo_model.gold.household_details hd ON lp.financial_account_id = hd.financial_account_id JOIN wealth_pulse_insigneo_model.gold.financial_account fa ON lp.financial_account_id = fa.financial_account_id LEFT JOIN wealth_pulse_insigneo_model.gold.securities s ON lp.cusip = s.cusip WHERE fa.account_status_indicator = 'O' AND fa.is_active = 1 AND hd.house_hold_name = 'AURORA' -- change household ), rolled AS ( SELECT house_hold_name, UPPER(position_key) AS position_key, MAX(ticker) AS ticker, MAX(security_name) AS security_name, SUM(market_value) AS market_value FROM hh_positions WHERE position_key IS NOT NULL GROUP BY house_hold_name, UPPER(position_key) ), hh_aum AS ( SELECT house_hold_name, SUM(market_value) AS total_aum FROM rolled GROUP BY house_hold_name ) SELECT r.house_hold_name, r.ticker, r.security_name, ROUND(r.market_value, 2) AS market_value, ROUND(r.market_value * 100.0 / NULLIF(a.total_aum, 0), 2) AS pct_of_household, CASE WHEN r.market_value * 100.0 / NULLIF(a.total_aum, 0) > 10 THEN 'over_limit' ELSE 'ok' END AS status FROM rolled r JOIN hh_aum a ON r.house_hold_name = a.house_hold_name ORDER BY r.market_value DESC LIMIT 10; | L80: Phase 3
A81: Advisor | B81: Portfolio Analytics Dashboard | C81: KPI | D81: Tab 3 - Activity | I81: - | J81: WITH latest_snapshot AS ( SELECT MAX(snapshot_date) AS end_date FROM wealth_pulse_insigneo_model.gold.positions ), date_filter AS ( SELECT end_date, DATE_SUB(end_date, 30) AS start_date FROM latest_snapshot ), account_details AS ( SELECT account_number, MAX(account_short_name) AS account_short_name, MAX(registration_type) AS registration_type FROM wealth_pulse_insigneo_model.gold.financial_account WHERE account_status_indicator = 'O' AND is_active = 1 GROUP BY account_number ), household_transactions AS ( SELECT hd.house_hold_name, t.transaction_date, t.financial_account_id, t.account_number, t.custodian, t.cusip, t.quantity, t.price, t.amount FROM wealth_pulse_insigneo_model.gold.transactions t JOIN wealth_pulse_insigneo_model.gold.household_details hd ON t.financial_account_id = hd.financial_account_id JOIN wealth_pulse_insigneo_model.gold.financial_account fa ON t.financial_account_id = fa.financial_account_id WHERE hd.house_hold_name = 'SAPPHIRE' AND fa.account_status_indicator = 'O' AND fa.is_active = 1 AND t.transaction_date BETWEEN (SELECT start_date FROM date_filter) AND (SELECT end_date FROM date_filter) ) SELECT ht.transaction_date AS Date, ad.account_short_name AS Account, ht.custodian AS Custodian, ad.registration_type AS Registration, COALESCE(MAX(s.asset_name), ht.cusip) AS Security, ht.quantity AS Qty, ht.price AS Price, ht.amount AS `Net Amount` FROM household_transactions ht JOIN account_details ad ON ht.account_number = ad.account_number LEFT JOIN wealth_pulse_insigneo_model.gold.securities s ON ht.cusip = s.cusip GROUP BY ht.transaction_date, ad.account_short_name, ad.registration_type, ht.custodian, ht.cusip, ht.quantity, ht.price, ht.amount ORDER BY ht.transaction_date DESC, ad.account_short_name; | L81: Phase 3
A82: Leadership | B82: Firm Dashboard (Leadership Home) | C82: Table | D82: Estimated Revenue & Fee Rate Drilldown (AUM by Tier) | J82: WITH latest_snapshot AS ( SELECT MAX(snapshot_date) AS latest_date FROM wealth_pulse_insigneo_model.gold.positions ), quarter_dates AS ( SELECT latest_date, CAST(DATE_TRUNC('quarter', latest_date) AS DATE) AS current_qtr_start, ADD_MONTHS( CAST(DATE_TRUNC('quarter', latest_date) AS DATE), -3 ) AS previous_qtr_start, DATE_SUB( CAST(DATE_TRUNC('quarter', latest_date) AS DATE), 1 ) AS previous_qtr_end FROM latest_snapshot ), snapshot_dates AS ( SELECT q.latest_date, ( SELECT MAX(snapshot_date) FROM wealth_pulse_insigneo_model.gold.positions WHERE snapshot_date <= q.previous_qtr_end ) AS previous_snapshot, q.current_qtr_start, q.previous_qtr_start, q.previous_qtr_end FROM quarter_dates q ), ranked_trades AS ( SELECT fc.financial_account_id, tb.trade_id, tb.workflow_status, tb.broker_month, tb.gross_comm, tb.load_time, ROW_NUMBER() OVER ( PARTITION BY tb.trade_id ORDER BY CASE tb.workflow_status WHEN 'Reconciled' THEN 2 WHEN 'Confirmed' THEN 1 ELSE 0 END DESC, tb.load_time DESC ) AS rn FROM wealth_pulse_insigneo_model.silver.transaction_blotter tb INNER JOIN wealth_pulse_insigneo_model.gold.fa_commission fc ON tb.trade_id = fc.trade_id ), current_position AS ( SELECT p.financial_account_id, SUM(ABS(p.amount)) AS market_value FROM wealth_pulse_insigneo_model.gold.positions p INNER JOIN wealth_pulse_insigneo_model.gold.financial_account fa ON p.financial_account_id = fa.financial_account_id CROSS JOIN snapshot_dates s WHERE p.snapshot_date = s.latest_date AND fa.account_status_indicator='O' AND fa.is_active=1 GROUP BY p.financial_account_id ), previous_position AS ( SELECT p.financial_account_id, SUM(ABS(p.amount)) AS market_value FROM wealth_pulse_insigneo_model.gold.positions p INNER JOIN wealth_pulse_insigneo_model.gold.financial_account fa ON p.financial_account_id = fa.financial_account_id CROSS JOIN snapshot_dates s WHERE p.snapshot_date = s.previous_snapshot AND fa.account_status_indicator='O' AND fa.is_active=1 GROUP BY p.financial_account_id ), current_fee AS ( SELECT rt.financial_account_id, SUM(rt.gross_comm) AS fee_revenue FROM ranked_trades rt INNER JOIN wealth_pulse_insigneo_model.gold.financial_account fa ON rt.financial_account_id = fa.financial_account_id CROSS JOIN snapshot_dates s WHERE rt.rn = 1 AND rt.broker_month BETWEEN s.current_qtr_start AND s.latest_date AND fa.account_status_indicator='O' AND fa.is_active=1 GROUP BY rt.financial_account_id ), previous_fee AS ( SELECT rt.financial_account_id, SUM(rt.gross_comm) AS fee_revenue FROM ranked_trades rt INNER JOIN wealth_pulse_insigneo_model.gold.financial_account fa ON rt.financial_account_id = fa.financial_account_id CROSS JOIN snapshot_dates s WHERE rt.rn = 1 AND rt.broker_month BETWEEN s.previous_qtr_start AND s.previous_qtr_end AND fa.account_status_indicator='O' AND fa.is_active=1 GROUP BY rt.financial_account_id ), household_current AS ( SELECT hd.house_hold_name, SUM(cp.market_value) AS current_aum, SUM(COALESCE(cf.fee_revenue,0)) AS current_fee FROM current_position cp INNER JOIN wealth_pulse_insigneo_model.gold.household_details hd ON cp.financial_account_id = hd.financial_account_id LEFT JOIN current_fee cf ON cp.financial_account_id = cf.financial_account_id GROUP BY hd.house_hold_name ), household_previous AS ( SELECT hd.house_hold_name, SUM(pp.market_value) AS previous_aum, SUM(COALESCE(pf.fee_revenue,0)) AS previous_fee FROM previous_position pp INNER JOIN wealth_pulse_insigneo_model.gold.household_details hd ON pp.financial_account_id = hd.financial_account_id LEFT JOIN previous_fee pf ON pp.financial_account_id = pf.financial_account_id GROUP BY hd.house_hold_name ), client_segment AS ( SELECT t.house_hold_name, CASE WHEN MAX( CASE WHEN t.entity_name IS NOT NULL AND TRIM(t.entity_name) <> '' THEN 1 ELSE 0 END ) = 1 THEN 'Corporate' WHEN SUM(t.maximum_net_worth) >= 10000000 THEN 'UHNW' WHEN SUM(t.maximum_net_worth) >= 1000000 THEN 'HNW' WHEN SUM(t.maximum_net_worth) IS NOT NULL THEN 'Mass Affluent' WHEN SUM(t.maximum_annual_income) >= 1000000 THEN 'UHNW (Estimated)' WHEN SUM(t.maximum_annual_income) >= 250000 THEN 'HNW (Estimated)' ELSE 'Mass Affluent' END AS client_segment FROM ( SELECT DISTINCT hd.house_hold_name, pa.person_account_id, pa.entity_name, pa.maximum_net_worth, pa.maximum_annual_income FROM wealth_pulse_insigneo_model.gold.positions p JOIN wealth_pulse_insigneo_model.gold.household_details hd ON p.financial_account_id = hd.financial_account_id JOIN wealth_pulse_insigneo_model.gold.person_financial_mapping pfm ON p.financial_account_id = pfm.financial_account_id JOIN wealth_pulse_insigneo_model.gold.person_account pa ON pfm.person_account_id = pa.person_account_id JOIN wealth_pulse_insigneo_model.gold.financial_account fa ON p.financial_account_id = fa.financial_account_id WHERE p.snapshot_date = ( SELECT snapshot_date FROM latest_snapshot ) AND fa.account_status_indicator = 'O' AND fa.is_active = 1 ) t GROUP BY t.house_hold_name ), segment_households AS ( SELECT cs.client_segment, hc.house_hold_name, hc.current_aum, hc.current_fee, hp.previous_aum, hp.previous_fee, ROUND( current_fee / NULLIF(current_aum,0) *10000, 2 ) AS current_household_bps FROM household_current hc LEFT JOIN household_previous hp ON hc.house_hold_name=hp.house_hold_name JOIN client_segment cs ON hc.house_hold_name=cs.house_hold_name ), tier_summary AS ( SELECT client_segment, COUNT(DISTINCT house_hold_name) AS households, SUM(current_aum) AS total_current_aum, SUM(previous_aum) AS total_previous_aum, SUM(current_fee) AS total_current_fee, SUM(previous_fee) AS total_previous_fee, ROUND( AVG(current_household_bps), 2 ) AS avg_current_bps FROM segment_households GROUP BY client_segment ) SELECT client_segment, households, ROUND( total_current_fee / NULLIF(total_current_aum,0) *10000, 2 ) AS current_bps, ROUND( total_previous_fee / NULLIF(total_previous_aum,0) *10000, 2 ) AS previous_bps, avg_current_bps FROM tier_summary ORDER BY CASE client_segment WHEN 'UHNW' THEN 1 WHEN 'HNW' THEN 2 WHEN 'Mass Affluent' THEN 3 WHEN 'UHNW (Estimated)' THEN 4 WHEN 'HNW (Estimated)' THEN 5 ELSE 6 END;
A84: Advisor | B84: Household Detail Pages (4 tabs) | D84: Household Dashboard | J84: WITH latest_snapshot AS ( SELECT MAX(snapshot_date) AS snapshot_date FROM wealth_pulse_insigneo_model.gold.positions ), beginning_snapshot AS ( SELECT MAX(snapshot_date) AS snapshot_date FROM wealth_pulse_insigneo_model.gold.positions WHERE snapshot_date < ( SELECT DATE_TRUNC('year', snapshot_date) FROM latest_snapshot ) ), client_segment AS( SELECT t.house_hold_name, CASE WHEN MAX( CASE WHEN t.entity_name IS NOT NULL AND TRIM(t.entity_name) <> '' THEN 1 ELSE 0 END ) = 1 THEN 'Corporate' WHEN SUM(t.maximum_net_worth) >= 10000000 THEN 'UHNW' WHEN SUM(t.maximum_net_worth) >= 1000000 THEN 'HNW' WHEN SUM(t.maximum_net_worth) IS NOT NULL THEN 'Mass Affluent' WHEN SUM(t.maximum_annual_income) >= 1000000 THEN 'UHNW (Estimated)' WHEN SUM(t.maximum_annual_income) >= 250000 THEN 'HNW (Estimated)' ELSE 'Mass Affluent' END AS client_segment FROM ( SELECT DISTINCT hd.house_hold_name, pa.person_account_id, pa.entity_name, pa.maximum_net_worth, pa.maximum_annual_income FROM wealth_pulse_insigneo_model.gold.positions p JOIN wealth_pulse_insigneo_model.gold.household_details hd ON p.financial_account_id = hd.financial_account_id JOIN wealth_pulse_insigneo_model.gold.person_financial_mapping pfm ON p.financial_account_id = pfm.financial_account_id JOIN wealth_pulse_insigneo_model.gold.person_account pa ON pfm.person_account_id = pa.person_account_id WHERE p.snapshot_date = ( SELECT snapshot_date FROM latest_snapshot ) ) t GROUP BY t.house_hold_name ), beginning_household_aum AS ( SELECT hd.house_hold_name, SUM(p.amount) AS beginning_aum FROM wealth_pulse_insigneo_model.gold.positions p JOIN wealth_pulse_insigneo_model.gold.household_details hd ON p.financial_account_id = hd.financial_account_id JOIN wealth_pulse_insigneo_model.gold.financial_account fa ON fa.financial_account_id = p.financial_account_id WHERE p.snapshot_date = ( SELECT snapshot_date FROM beginning_snapshot ) AND fa.account_status_indicator = 'O' AND fa.is_active = 1 GROUP BY hd.house_hold_name ), current_household_aum AS ( SELECT hd.house_hold_name, SUM(p.amount) AS current_aum FROM wealth_pulse_insigneo_model.gold.positions p JOIN wealth_pulse_insigneo_model.gold.household_details hd ON p.financial_account_id = hd.financial_account_id JOIN wealth_pulse_insigneo_model.gold.financial_account fa ON fa.financial_account_id = p.financial_account_id WHERE p.snapshot_date = ( SELECT snapshot_date FROM latest_snapshot ) AND fa.account_status_indicator = 'O' AND fa.is_active = 1 GROUP BY hd.house_hold_name ), ytd_cte AS ( SELECT c.house_hold_name, c.current_aum, b.beginning_aum, ROUND( ( c.current_aum - b.beginning_aum ) * 100.0 / NULLIF(b.beginning_aum,0), 2 ) AS ytd FROM current_household_aum c JOIN beginning_household_aum b ON c.house_hold_name = b.house_hold_name ), household_cash AS ( SELECT hd.house_hold_name, SUM(ac.cash_available) AS cash_available, COUNT(DISTINCT hd.account_number) AS accounts, MIN(fa.date_account_opened) AS since, STRING_AGG(DISTINCT p.custodian, ', ') AS custodians, CASE WHEN COUNT(CASE WHEN fa.account_status_indicator <> 'O' THEN 1 END)=0 THEN 'Open' ELSE 'Mixed' END AS status FROM wealth_pulse_insigneo_model.gold.positions p JOIN wealth_pulse_insigneo_model.gold.household_details hd ON p.financial_account_id = hd.financial_account_id LEFT JOIN wealth_pulse_insigneo_model.gold.account_summary ac ON p.financial_account_id = ac.financial_account_id JOIN wealth_pulse_insigneo_model.gold.financial_account fa ON p.financial_account_id = fa.financial_account_id WHERE p.snapshot_date = ( SELECT snapshot_date FROM latest_snapshot ) GROUP BY hd.house_hold_name ) -- SELECT * from household_cash SELECT y.house_hold_name AS household, NULL AS segment, y.beginning_aum, y.current_aum AS aum, ac.accounts, ac.custodians, ROUND( ac.cash_available / NULLIF(y.current_aum,0) *100, 2 ) AS cash_pct, y.ytd, ac.status, ac.since FROM ytd_cte y -- LEFT JOIN client_segment cs -- ON y.house_hold_name = y.house_hold_name INNER JOIN household_cash ac ON y.house_hold_name = ac.house_hold_name
A85: Advisor | B85: Advisor Home Dashboard | C85: KPI | D85: Idle Cash (Silder) | J85: WITH latest_snapshot AS ( SELECT MAX(snapshot_date) AS max_snapshot_date FROM wealth_pulse_insigneo_model.gold.positions ), position_mv AS ( SELECT p.financial_account_id, SUM(p.amount) AS market_value FROM wealth_pulse_insigneo_model.gold.positions p JOIN wealth_pulse_insigneo_model.gold.financial_account a ON p.financial_account_id = a.financial_account_id CROSS JOIN latest_snapshot l WHERE p.snapshot_date = l.max_snapshot_date AND a.account_status_indicator = 'O' AND a.is_active = 1 GROUP BY p.financial_account_id ), account_cash AS ( SELECT hd.house_hold_name, a.financial_account_id, mv.market_value, a.cash_available, a.cash_available / NULLIF(mv.market_value,0) AS cash_pct FROM wealth_pulse_insigneo_model.gold.account_summary a JOIN position_mv mv ON a.financial_account_id = mv.financial_account_id LEFT JOIN wealth_pulse_insigneo_model.gold.household_details hd ON a.financial_account_id = hd.financial_account_id JOIN wealth_pulse_insigneo_model.gold.financial_account fa ON a.financial_account_id = fa.financial_account_id WHERE fa.account_status_indicator = 'O' AND fa.is_active = 1 ), household_aum AS ( SELECT hd.house_hold_name, SUM(p.amount) AS household_aum FROM wealth_pulse_insigneo_model.gold.positions p JOIN wealth_pulse_insigneo_model.gold.household_details hd ON p.financial_account_id = hd.financial_account_id JOIN wealth_pulse_insigneo_model.gold.financial_account fa ON p.financial_account_id = fa.financial_account_id CROSS JOIN latest_snapshot l WHERE p.snapshot_date = l.max_snapshot_date AND fa.account_status_indicator = 'O' AND fa.is_active = 1 GROUP BY hd.house_hold_name ), /* Idle cash only for households exceeding 5% */ household_idle_cash AS ( SELECT house_hold_name, ROUND(SUM(cash_available),2) AS idle_cash FROM account_cash GROUP BY house_hold_name ), /* Complete household list */ households AS ( SELECT DISTINCT house_hold_name FROM wealth_pulse_insigneo_model.gold.household_details ) SELECT h.house_hold_name, ROUND(COALESCE(ha.household_aum,0),2) AS aum, ROUND(COALESCE(hic.idle_cash,0),2) AS cash, ROUND( COALESCE(hic.idle_cash,0) * 100.0 / NULLIF(ha.household_aum,0), 2 ) AS cash_pct_aum FROM households h LEFT JOIN household_idle_cash hic ON h.house_hold_name = hic.house_hold_name LEFT JOIN household_aum ha ON h.house_hold_name = ha.house_hold_name ORDER BY cash DESC, h.house_hold_name;
A86: Advisor | B86: Advisor Home Dashboard | C86: KPI | D86: Total AUM - AUM by segment (silder) | J86: WITH latest_snapshot AS ( SELECT MAX(snapshot_date) AS snapshot_date FROM wealth_pulse_insigneo_model.gold.positions ), client_segment AS ( SELECT t.house_hold_name, CASE WHEN MAX( CASE WHEN t.entity_name IS NOT NULL AND TRIM(t.entity_name) <> '' THEN 1 ELSE 0 END ) = 1 THEN 'Corporate' WHEN SUM(t.maximum_net_worth) >= 10000000 THEN 'UHNW' WHEN SUM(t.maximum_net_worth) >= 1000000 THEN 'HNW' WHEN SUM(t.maximum_net_worth) IS NOT NULL THEN 'Mass Affluent' WHEN SUM(t.maximum_annual_income) >= 1000000 THEN 'UHNW (Estimated)' WHEN SUM(t.maximum_annual_income) >= 250000 THEN 'HNW (Estimated)' ELSE 'Mass Affluent' END AS client_segment FROM ( SELECT DISTINCT hd.house_hold_name, pa.person_account_id, pa.entity_name, pa.maximum_net_worth, pa.maximum_annual_income FROM wealth_pulse_insigneo_model.gold.positions p JOIN wealth_pulse_insigneo_model.gold.household_details hd ON p.financial_account_id = hd.financial_account_id JOIN wealth_pulse_insigneo_model.gold.person_financial_mapping pfm ON p.financial_account_id = pfm.financial_account_id JOIN wealth_pulse_insigneo_model.gold.person_account pa ON pfm.person_account_id = pa.person_account_id JOIN wealth_pulse_insigneo_model.gold.financial_account fa ON p.financial_account_id = fa.financial_account_id WHERE p.snapshot_date = ( SELECT snapshot_date FROM latest_snapshot ) AND fa.account_status_indicator = 'O' AND fa.is_active = 1 ) t GROUP BY t.house_hold_name ), household_aum AS ( SELECT hd.house_hold_name, SUM(p.amount) AS household_aum FROM wealth_pulse_insigneo_model.gold.positions p JOIN wealth_pulse_insigneo_model.gold.household_details hd ON p.financial_account_id = hd.financial_account_id JOIN wealth_pulse_insigneo_model.gold.financial_account fa ON p.financial_account_id = fa.financial_account_id WHERE p.snapshot_date = ( SELECT snapshot_date FROM latest_snapshot ) AND fa.account_status_indicator = 'O' AND fa.is_active = 1 GROUP BY hd.house_hold_name ) SELECT cs.client_segment, COUNT(DISTINCT ha.house_hold_name) AS household_count, ROUND(SUM(ha.household_aum),2) AS aum, ROUND( SUM(ha.household_aum) * 100.0 / SUM(SUM(ha.household_aum)) OVER (), 2 ) AS segment_aum_pct FROM household_aum ha JOIN client_segment cs ON ha.house_hold_name = cs.house_hold_name GROUP BY cs.client_segment ORDER BY aum DESC;
A87: Advisor | B87: Advisor Home Dashboard | C87: KPI | D87: Top Net New Assets by advisor- NNA (Slider) | J87: WITH latest_snapshot AS ( SELECT MAX(snapshot_date) AS end_date FROM wealth_pulse_insigneo_model.gold.positions ), beginning_snapshot AS ( SELECT MAX(snapshot_date) AS start_date FROM wealth_pulse_insigneo_model.gold.positions WHERE snapshot_date < ( SELECT DATE_TRUNC('year', end_date) FROM latest_snapshot ) ) SELECT t.investment_professional_number, ROUND( SUM( CASE WHEN t.transaction_code IN ('CONTRIBUTION','TRANSFER_IN','RFF','CSR') THEN ABS(t.amount) ELSE 0 END ) - SUM( CASE WHEN t.transaction_code IN ('DISTRIBUTION','TRANSFER_OUT','SFF','PCC') THEN ABS(t.amount) ELSE 0 END ), 2 ) AS net_new_assets FROM wealth_pulse_insigneo_model.gold.transactions t JOIN wealth_pulse_insigneo_model.gold.financial_account fa ON t.financial_account_id = fa.financial_account_id CROSS JOIN latest_snapshot ls CROSS JOIN beginning_snapshot bs WHERE CAST(t.transaction_date AS DATE) BETWEEN bs.start_date AND ls.end_date AND fa.account_status_indicator = 'O' AND fa.is_active = 1 GROUP BY t.investment_professional_number ORDER BY net_new_assets DESC LIMIT 10;

Sheet Dashboard Inventory
A1: # | B1: Group | C1: Dashboard / Page | D1: ADO Feature / User Stories | E1: ADO IDs | F1: State | G1: # KPIs | H1: # Charts | I1: # Tables | J1: # Panels/Widgets | K1: # Filters/Sections | L1: Total Components | M1: Description | N1: 1 - Done | O1: 2 - Logic can be driven | P1: 3 - Can't be achieved | Q1: N/A | R1: % Done
A2: 1 | B2: Leadership | C2: Firm Dashboard (Leadership Home) | D2: Feature 6.1 Firm Dashboard | E2: 16641 (F), 16943 (US) | F2: Feature: New / US: Done | G2: =COUNTIFS('Component Detail'!$B:$B,$C2,'Component Detail'!$C:$C,"KPI") -> 5 | H2: =COUNTIFS('Component Detail'!$B:$B,$C2,'Component Detail'!$C:$C,"Chart") -> 3 | I2: =COUNTIFS('Component Detail'!$B:$B,$C2,'Component Detail'!$C:$C,"Table") -> 2 | J2: =COUNTIFS('Component Detail'!$B:$B,$C2,'Component Detail'!$C:$C,"Panel")+COUNTIFS('Component Detail'!$B:$B,$C2,'Component Detail'!$C:$C,"Widget") -> 2 | K2: =COUNTIFS('Component Detail'!$B:$B,$C2,'Component Detail'!$C:$C,"Filter/Control")+COUNTIFS('Component Detail'!$B:$B,$C2,'Component Detail'!$C:$C,"Section") -> 0 | L2: =COUNTIF('Component Detail'!$B:$B,$C2) -> 12 | M2: Firm-level AUM, growth, revenue, retention, advisor performance | N2: =COUNTIFS('Component Detail'!$B:$B,$C2,'Component Detail'!$L:$L,"1 - Done") -> 7 | O2: =COUNTIFS('Component Detail'!$B:$B,$C2,'Component Detail'!$L:$L,"2 - Logic can be driven") -> 0 | P2: =COUNTIFS('Component Detail'!$B:$B,$C2,'Component Detail'!$L:$L,"3 - Can't be achieved") -> 0 | Q2: =COUNTIFS('Component Detail'!$B:$B,$C2,'Component Detail'!$L:$L,"N/A - UI/placeholder") -> 0 | R2: =IFERROR(N2/(N2+O2+P2),0) -> 1
A3: 2 | B3: Leadership | C3: Advisor Intelligence Dashboard (Leadership View) | D3: Feature 6.2 Advisor Intelligence | E3: 16643 (F), 16588, 17098 | F3: Feature: Active / US: Done | G3: =COUNTIFS('Component Detail'!$B:$B,$C3,'Component Detail'!$C:$C,"KPI") -> 4 | H3: =COUNTIFS('Component Detail'!$B:$B,$C3,'Component Detail'!$C:$C,"Chart") -> 5 | I3: =COUNTIFS('Component Detail'!$B:$B,$C3,'Component Detail'!$C:$C,"Table") -> 1 | J3: =COUNTIFS('Component Detail'!$B:$B,$C3,'Component Detail'!$C:$C,"Panel")+COUNTIFS('Component Detail'!$B:$B,$C3,'Component Detail'!$C:$C,"Widget") -> 0 | K3: =COUNTIFS('Component Detail'!$B:$B,$C3,'Component Detail'!$C:$C,"Filter/Control")+COUNTIFS('Component Detail'!$B:$B,$C3,'Component Detail'!$C:$C,"Section") -> 0 | L3: =COUNTIF('Component Detail'!$B:$B,$C3) -> 10 | M3: Comparative advisor performance; also embedded from Advisor portal | N3: =COUNTIFS('Component Detail'!$B:$B,$C3,'Component Detail'!$L:$L,"1 - Done") -> 6 | O3: =COUNTIFS('Component Detail'!$B:$B,$C3,'Component Detail'!$L:$L,"2 - Logic can be driven") -> 0 | P3: =COUNTIFS('Component Detail'!$B:$B,$C3,'Component Detail'!$L:$L,"3 - Can't be achieved") -> 0 | Q3: =COUNTIFS('Component Detail'!$B:$B,$C3,'Component Detail'!$L:$L,"N/A - UI/placeholder") -> 0 | R3: =IFERROR(N3/(N3+O3+P3),0) -> 1
A4: 3 | B4: Leadership | C4: Household Insights Dashboard (Leadership View) | D4: Feature 6.3 Household Insights | E4: 16644 (F), 16589, 17104 | F4: Feature: New / US: Done | G4: =COUNTIFS('Component Detail'!$B:$B,$C4,'Component Detail'!$C:$C,"KPI") -> 4 | H4: =COUNTIFS('Component Detail'!$B:$B,$C4,'Component Detail'!$C:$C,"Chart") -> 0 | I4: =COUNTIFS('Component Detail'!$B:$B,$C4,'Component Detail'!$C:$C,"Table") -> 1 | J4: =COUNTIFS('Component Detail'!$B:$B,$C4,'Component Detail'!$C:$C,"Panel")+COUNTIFS('Component Detail'!$B:$B,$C4,'Component Detail'!$C:$C,"Widget") -> 1 | K4: =COUNTIFS('Component Detail'!$B:$B,$C4,'Component Detail'!$C:$C,"Filter/Control")+COUNTIFS('Component Detail'!$B:$B,$C4,'Component Detail'!$C:$C,"Section") -> 1 | L4: =COUNTIF('Component Detail'!$B:$B,$C4) -> 7 | M4: Firm-wide household health, risk & servicing | N4: =COUNTIFS('Component Detail'!$B:$B,$C4,'Component Detail'!$L:$L,"1 - Done") -> 0 | O4: =COUNTIFS('Component Detail'!$B:$B,$C4,'Component Detail'!$L:$L,"2 - Logic can be driven") -> 0 | P4: =COUNTIFS('Component Detail'!$B:$B,$C4,'Component Detail'!$L:$L,"3 - Can't be achieved") -> 0 | Q4: =COUNTIFS('Component Detail'!$B:$B,$C4,'Component Detail'!$L:$L,"N/A - UI/placeholder") -> 0 | R4: =IFERROR(N4/(N4+O4+P4),0) -> 0
A5: 4 | B5: Advisor | C5: Advisor Home Dashboard | D5: Feature 7.1 Advisor Home | E5: 16632 (F), 16006, 16437, 16722 | F5: Feature: Active / FE Done, BE Ready for Testing | G5: =COUNTIFS('Component Detail'!$B:$B,$C5,'Component Detail'!$C:$C,"KPI") -> 7 | H5: =COUNTIFS('Component Detail'!$B:$B,$C5,'Component Detail'!$C:$C,"Chart") -> 2 | I5: =COUNTIFS('Component Detail'!$B:$B,$C5,'Component Detail'!$C:$C,"Table") -> 1 | J5: =COUNTIFS('Component Detail'!$B:$B,$C5,'Component Detail'!$C:$C,"Panel")+COUNTIFS('Component Detail'!$B:$B,$C5,'Component Detail'!$C:$C,"Widget") -> 8 | K5: =COUNTIFS('Component Detail'!$B:$B,$C5,'Component Detail'!$C:$C,"Filter/Control")+COUNTIFS('Component Detail'!$B:$B,$C5,'Component Detail'!$C:$C,"Section") -> 0 | L5: =COUNTIF('Component Detail'!$B:$B,$C5) -> 18 | M5: Primary advisor operational cockpit | N5: =COUNTIFS('Component Detail'!$B:$B,$C5,'Component Detail'!$L:$L,"1 - Done") -> 4 | O5: =COUNTIFS('Component Detail'!$B:$B,$C5,'Component Detail'!$L:$L,"2 - Logic can be driven") -> 0 | P5: =COUNTIFS('Component Detail'!$B:$B,$C5,'Component Detail'!$L:$L,"3 - Can't be achieved") -> 0 | Q5: =COUNTIFS('Component Detail'!$B:$B,$C5,'Component Detail'!$L:$L,"N/A - UI/placeholder") -> 0 | R5: =IFERROR(N5/(N5+O5+P5),0) -> 1
A6: 5 | B6: Advisor | C6: Household Management Dashboard | D6: Feature 7.3 Household Mgmt | E6: 16633 (F), 16005, 16436, 16723 | F6: Feature: Active / US Done/Ready | G6: =COUNTIFS('Component Detail'!$B:$B,$C6,'Component Detail'!$C:$C,"KPI") -> 2 | H6: =COUNTIFS('Component Detail'!$B:$B,$C6,'Component Detail'!$C:$C,"Chart") -> 3 | I6: =COUNTIFS('Component Detail'!$B:$B,$C6,'Component Detail'!$C:$C,"Table") -> 1 | J6: =COUNTIFS('Component Detail'!$B:$B,$C6,'Component Detail'!$C:$C,"Panel")+COUNTIFS('Component Detail'!$B:$B,$C6,'Component Detail'!$C:$C,"Widget") -> 0 | K6: =COUNTIFS('Component Detail'!$B:$B,$C6,'Component Detail'!$C:$C,"Filter/Control")+COUNTIFS('Component Detail'!$B:$B,$C6,'Component Detail'!$C:$C,"Section") -> 1 | L6: =COUNTIF('Component Detail'!$B:$B,$C6) -> 7 | M6: Household book list & segmentation | N6: =COUNTIFS('Component Detail'!$B:$B,$C6,'Component Detail'!$L:$L,"1 - Done") -> 1 | O6: =COUNTIFS('Component Detail'!$B:$B,$C6,'Component Detail'!$L:$L,"2 - Logic can be driven") -> 0 | P6: =COUNTIFS('Component Detail'!$B:$B,$C6,'Component Detail'!$L:$L,"3 - Can't be achieved") -> 0 | Q6: =COUNTIFS('Component Detail'!$B:$B,$C6,'Component Detail'!$L:$L,"N/A - UI/placeholder") -> 0 | R6: =IFERROR(N6/(N6+O6+P6),0) -> 1
A7: 6 | B7: Advisor | C7: Household Detail Pages (4 tabs) | D7: Feature 7.3 (7.3c) | E7: 16873 (US) | F7: Done | G7: =COUNTIFS('Component Detail'!$B:$B,$C7,'Component Detail'!$C:$C,"KPI") -> 4 | H7: =COUNTIFS('Component Detail'!$B:$B,$C7,'Component Detail'!$C:$C,"Chart") -> 2 | I7: =COUNTIFS('Component Detail'!$B:$B,$C7,'Component Detail'!$C:$C,"Table") -> 3 | J7: =COUNTIFS('Component Detail'!$B:$B,$C7,'Component Detail'!$C:$C,"Panel")+COUNTIFS('Component Detail'!$B:$B,$C7,'Component Detail'!$C:$C,"Widget") -> 0 | K7: =COUNTIFS('Component Detail'!$B:$B,$C7,'Component Detail'!$C:$C,"Filter/Control")+COUNTIFS('Component Detail'!$B:$B,$C7,'Component Detail'!$C:$C,"Section") -> 2 | L7: =COUNTIF('Component Detail'!$B:$B,$C7) -> 12 | M7: Overview / Accounts & Positions / Activity / Analytics tabs | N7: =COUNTIFS('Component Detail'!$B:$B,$C7,'Component Detail'!$L:$L,"1 - Done") -> 4 | O7: =COUNTIFS('Component Detail'!$B:$B,$C7,'Component Detail'!$L:$L,"2 - Logic can be driven") -> 0 | P7: =COUNTIFS('Component Detail'!$B:$B,$C7,'Component Detail'!$L:$L,"3 - Can't be achieved") -> 0 | Q7: =COUNTIFS('Component Detail'!$B:$B,$C7,'Component Detail'!$L:$L,"N/A - UI/placeholder") -> 0 | R7: =IFERROR(N7/(N7+O7+P7),0) -> 1
A8: 7 | B8: Advisor | C8: Portfolio Analytics Dashboard | D8: Feature 7.4 Portfolio Analytics | E8: 16634 (F), 16008, 16724 | F8: Feature: Active / US Done | G8: =COUNTIFS('Component Detail'!$B:$B,$C8,'Component Detail'!$C:$C,"KPI") -> 6 | H8: =COUNTIFS('Component Detail'!$B:$B,$C8,'Component Detail'!$C:$C,"Chart") -> 3 | I8: =COUNTIFS('Component Detail'!$B:$B,$C8,'Component Detail'!$C:$C,"Table") -> 2 | J8: =COUNTIFS('Component Detail'!$B:$B,$C8,'Component Detail'!$C:$C,"Panel")+COUNTIFS('Component Detail'!$B:$B,$C8,'Component Detail'!$C:$C,"Widget") -> 0 | K8: =COUNTIFS('Component Detail'!$B:$B,$C8,'Component Detail'!$C:$C,"Filter/Control")+COUNTIFS('Component Detail'!$B:$B,$C8,'Component Detail'!$C:$C,"Section") -> 1 | L8: =COUNTIF('Component Detail'!$B:$B,$C8) -> 12 | M8: Allocation, sector, concentration, performance, risk | N8: =COUNTIFS('Component Detail'!$B:$B,$C8,'Component Detail'!$L:$L,"1 - Done") -> 3 | O8: =COUNTIFS('Component Detail'!$B:$B,$C8,'Component Detail'!$L:$L,"2 - Logic can be driven") -> 1 | P8: =COUNTIFS('Component Detail'!$B:$B,$C8,'Component Detail'!$L:$L,"3 - Can't be achieved") -> 0 | Q8: =COUNTIFS('Component Detail'!$B:$B,$C8,'Component Detail'!$L:$L,"N/A - UI/placeholder") -> 0 | R8: =IFERROR(N8/(N8+O8+P8),0) -> 0.75
A9: 8 | B9: Advisor | C9: Market News & Portfolio Intelligence (Placeholder) | D9: Feature 7.2 Market News | E9: 16635 (F), 16011 | F9: Feature: Resolved / US Done | G9: =COUNTIFS('Component Detail'!$B:$B,$C9,'Component Detail'!$C:$C,"KPI") -> 0 | H9: =COUNTIFS('Component Detail'!$B:$B,$C9,'Component Detail'!$C:$C,"Chart") -> 0 | I9: =COUNTIFS('Component Detail'!$B:$B,$C9,'Component Detail'!$C:$C,"Table") -> 0 | J9: =COUNTIFS('Component Detail'!$B:$B,$C9,'Component Detail'!$C:$C,"Panel")+COUNTIFS('Component Detail'!$B:$B,$C9,'Component Detail'!$C:$C,"Widget") -> 2 | K9: =COUNTIFS('Component Detail'!$B:$B,$C9,'Component Detail'!$C:$C,"Filter/Control")+COUNTIFS('Component Detail'!$B:$B,$C9,'Component Detail'!$C:$C,"Section") -> 0 | L9: =COUNTIF('Component Detail'!$B:$B,$C9) -> 2 | M9: Placeholder for Stage-2 real-time signals | N9: =COUNTIFS('Component Detail'!$B:$B,$C9,'Component Detail'!$L:$L,"1 - Done") -> 0 | O9: =COUNTIFS('Component Detail'!$B:$B,$C9,'Component Detail'!$L:$L,"2 - Logic can be driven") -> 0 | P9: =COUNTIFS('Component Detail'!$B:$B,$C9,'Component Detail'!$L:$L,"3 - Can't be achieved") -> 0 | Q9: =COUNTIFS('Component Detail'!$B:$B,$C9,'Component Detail'!$L:$L,"N/A - UI/placeholder") -> 0 | R9: =IFERROR(N9/(N9+O9+P9),0) -> 0
A10: 9 | B10: Advisor | C10: Action Items & Alerts Screen | D10: Epic-7 US | E10: 16590 (US) | F10: Ready for Testing | G10: =COUNTIFS('Component Detail'!$B:$B,$C10,'Component Detail'!$C:$C,"KPI") -> 1 | H10: =COUNTIFS('Component Detail'!$B:$B,$C10,'Component Detail'!$C:$C,"Chart") -> 0 | I10: =COUNTIFS('Component Detail'!$B:$B,$C10,'Component Detail'!$C:$C,"Table") -> 0 | J10: =COUNTIFS('Component Detail'!$B:$B,$C10,'Component Detail'!$C:$C,"Panel")+COUNTIFS('Component Detail'!$B:$B,$C10,'Component Detail'!$C:$C,"Widget") -> 0 | K10: =COUNTIFS('Component Detail'!$B:$B,$C10,'Component Detail'!$C:$C,"Filter/Control")+COUNTIFS('Component Detail'!$B:$B,$C10,'Component Detail'!$C:$C,"Section") -> 2 | L10: =COUNTIF('Component Detail'!$B:$B,$C10) -> 3 | M10: Insight/alert list from Insights framework | N10: =COUNTIFS('Component Detail'!$B:$B,$C10,'Component Detail'!$L:$L,"1 - Done") -> 0 | O10: =COUNTIFS('Component Detail'!$B:$B,$C10,'Component Detail'!$L:$L,"2 - Logic can be driven") -> 0 | P10: =COUNTIFS('Component Detail'!$B:$B,$C10,'Component Detail'!$L:$L,"3 - Can't be achieved") -> 0 | Q10: =COUNTIFS('Component Detail'!$B:$B,$C10,'Component Detail'!$L:$L,"N/A - UI/placeholder") -> 0 | R10: =IFERROR(N10/(N10+O10+P10),0) -> 0
A11: 10 | B11: Advisor | C11: Priority Actions Panel (Framework) | D11: Epic-7 US | E11: 16010 (US) | F11: New | G11: =COUNTIFS('Component Detail'!$B:$B,$C11,'Component Detail'!$C:$C,"KPI") -> 0 | H11: =COUNTIFS('Component Detail'!$B:$B,$C11,'Component Detail'!$C:$C,"Chart") -> 0 | I11: =COUNTIFS('Component Detail'!$B:$B,$C11,'Component Detail'!$C:$C,"Table") -> 0 | J11: =COUNTIFS('Component Detail'!$B:$B,$C11,'Component Detail'!$C:$C,"Panel")+COUNTIFS('Component Detail'!$B:$B,$C11,'Component Detail'!$C:$C,"Widget") -> 0 | K11: =COUNTIFS('Component Detail'!$B:$B,$C11,'Component Detail'!$C:$C,"Filter/Control")+COUNTIFS('Component Detail'!$B:$B,$C11,'Component Detail'!$C:$C,"Section") -> 2 | L11: =COUNTIF('Component Detail'!$B:$B,$C11) -> 2 | M11: Workflow queue surface for Stage-2 agents | N11: =COUNTIFS('Component Detail'!$B:$B,$C11,'Component Detail'!$L:$L,"1 - Done") -> 0 | O11: =COUNTIFS('Component Detail'!$B:$B,$C11,'Component Detail'!$L:$L,"2 - Logic can be driven") -> 0 | P11: =COUNTIFS('Component Detail'!$B:$B,$C11,'Component Detail'!$L:$L,"3 - Can't be achieved") -> 0 | Q11: =COUNTIFS('Component Detail'!$B:$B,$C11,'Component Detail'!$L:$L,"N/A - UI/placeholder") -> 0 | R11: =IFERROR(N11/(N11+O11+P11),0) -> 0
C12: TOTAL | G12: =SUM(G2:G11) -> 33 | H12: =SUM(H2:H11) -> 18 | I12: =SUM(I2:I11) -> 11 | J12: =SUM(J2:J11) -> 13 | K12: =SUM(K2:K11) -> 9 | L12: =SUM(L2:L11) -> 85 | N12: =SUM(N2:N11) -> 25 | O12: =SUM(O2:O11) -> 1 | P12: =SUM(P2:P11) -> 0 | Q12: =SUM(Q2:Q11) -> 0 | R12: =IFERROR(N12/(N12+O12+P12),0) -> 0.96153846

Sheet ADO Work Items
A1: Group | B1: Work Item Type | C1: ADO ID | D1: Title | E1: State
A2: Leadership | B2: Epic | C2: 15989 | D2: Epic-6: Leadership Dashboard | E2: Active
A3: Leadership | B3: Feature | C3: 16641 | D3: 6.1 Firm Dashboard Creation and Integration for Leadership | E3: New
A4: Leadership | B4: User Story | C4: 16943 | D4: Leadership Dashboard Home screen Integration | E4: Done
A5: Leadership | B5: QA Story | C5: 17582 | D5: [QA] Leadership Dashboard Home screen Integration | E5: New
A6: Leadership | B6: Feature | C6: 16643 | D6: 6.2 Advisor Intelligence Dashboard Creation | E6: Active
A7: Leadership | B7: User Story | C7: 16588 | D7: 6.2a Advisor Intelligence Dashboard - KPI, Charts & Comparison View | E7: Done
A8: Leadership | B8: User Story | C8: 17098 | D8: Advisor Intelligence Dashboard (Leadership View) - Integration | E8: Done
A9: Leadership | B9: QA Story | C9: 17371 | D9: Advisor Intelligence Dashboard - UI & Interaction · QA | E9: In Progress
A10: Leadership | B10: QA Story | C10: 17372 | D10: Advisor Intelligence Dashboard - KPI & Data Integrity · QA | E10: New
A11: Leadership | B11: QA Story | C11: 17581 | D11: [QA] 6.2a Advisor Intelligence Dashboard | E11: New
A12: Leadership | B12: QA Story | C12: 17584 | D12: [QA] Advisor Intelligence Dashboard (Leadership View) | E12: New
... A47: Advisor | B47: User Story | C47: 17484 | D47: Advisor Dashboard - QA testing | E47: New

Sheet Not Used in Dashboards
A1: KPIs / charts / tables NOT surfaced in our Advisor & Leadership dashboards - KPIs: 24 · Charts: 7 · Tables: 0
A2: ID | B2: Item | C2: Type | D2: Impact bucket | E2: Category (logic doc) | F2: Achievable | G2: Note
A3: KPI-004 | B3: Average Account Size | C3: KPI | D3: 1 - Done | E3: Done | F3: Yes | G3: Exists in DB/logic doc but not surfaced in any Advisor/Leadership dashboard component.
A4: KPI-005 | B4: Average Household AUM | C4: KPI | D4: 1 - Done | E4: Done | F4: Yes | G4: Exists in DB/logic doc but not surfaced in any Advisor/Leadership dashboard component.
A5: KPI-006 | B5: Median Account Size | C5: KPI | D5: 1 - Done | E5: Done | F5: Yes | G5: Exists in DB/logic doc but not surfaced in any Advisor/Leadership dashboard component.
A6: KPI-010 | B6: Advisor Account Count | C6: KPI | D6: 1 - Done | E6: Done | F6: Yes | G6: Exists in DB/logic doc but not surfaced in any Advisor/Leadership dashboard component.
A7: KPI-012 | B7: Total Cash Holdings | C7: KPI | D7: 2 - Logic can be driven | E7: (with new derived table) | F7: Yes | G7: Exists in DB/logic doc but not surfaced in any Advisor/Leadership dashboard component.
A8: KPI-015 | B8: Pending Cash Activity | C8: KPI | D8: 2 - Logic can be driven | E8: Data Available/Calculation Required | F8: No | G8: Exists in DB/logic doc but not surfaced in any Advisor/Leadership dashboard component.
A9: KPI-021 | B9: New Account Opens | C9: KPI | D9: 1 - Done | E9: Done | F9: Yes | G9: Exists in DB/logic doc but not surfaced in any Advisor/Leadership dashboard component.
A10: KPI-022 | B10: Closed Accounts | C10: KPI | D10: 1 - Done | E10: Done | F10: Yes | G10: Exists in DB/logic doc but not surfaced in any Advisor/Leadership dashboard component.
A11: KPI-023 | B11: Total Trade Count | C11: KPI | D11: 1 - Done | E11: Done | F11: Yes | G11: Exists in DB/logic doc but not surfaced in any Advisor/Leadership dashboard component.
A12: KPI-024 | B12: Trade Volume ($) | C12: KPI | D12: 1 - Done | E12: Done | F12: Yes | G12: Exists in DB/logic doc but not surfaced in any Advisor/Leadership dashboard component.
A13: KPI-025 | B13: Buy/Sell Ratio | C13: KPI | D13: 1 - Done | E13: Done | F13: Yes | G13: Exists in DB/logic doc but not surfaced in any Advisor/Leadership dashboard component.
... A33: CHART-027 | B33: Data Quality Scorecard (Summary Pills + Detail Table) | C33: Chart | D33: 3 - Can't be achieved | E33: Data Not Available | F33: No | G33: Data-ops dashboard (Ingestion Monitor / Data Quality) - outside Advisor & Leadership scope.

Sheet KPI Logic - shared by Aman
A1: id | B1: display_name | C1: tables_used | D1: columns_used | E1: Achievable | F1: Reason | G1: SQL Query | H1: Insigneo Query | I1: Category | J1: UI Page | K1: Page 2 | L1: Remarks
A2: KPI-001 | B2: Total AUM | C2: fact_position; dim_account | D2: fact_position[market_value]; fact_position[position_date]; dim_account[account_status]; dim_account[is_current] | E2: Yes | G2: SELECT SUM(p.market_value) AS total_aum FROM fact_position p JOIN dim_account a ON p.canonical_account_id = a.canonical_account_id WHERE p.position_date = CURRENT_DATE AND a.account_status = 'ACTIVE' AND a.is_current = TRUE | H2: SELECT SUM(p.amount) AS total_aum FROM positions p JOIN financial_account a ON p.financial_account_id = a.financial_account_id WHERE p.snapshot_date BETWEEN DATEADD(DAY, 1 - DATEPART(WEEKDAY, '2026-01-01'), '2026-01-01') AND DATEADD(DAY, 7 - DATEPART(WEEKDAY, '2026-01-01'), '2026-01-01') AND a.account_status_indicator = 'O' AND a.is_active = 1 | I2: Done
A3: KPI-002 | B3: AUM by Asset Class | C3: fact_position; dim_account; dim_security | D3: fact_position[market_value]; fact_position[asset_class]; fact_position[position_date]; dim_account[account_status]; dim_account[is_current] | E3: Yes | G3: SELECT p.asset_class, SUM(p.market_value) AS aum FROM fact_position p JOIN dim_account a ON p.canonical_account_id = a.canonical_account_id WHERE p.position_date = CURRENT_DATE AND a.account_status = 'ACTIVE' AND a.is_current = TRUE GROUP BY p.asset_class ORDER BY aum DESC | H3: SELECT s.asset_class, SUM(p.amount) AS aum FROM positions p JOIN financial_account a ON p.financial_account_id = a.financial_account_id JOIN securities s on s.cusip = p.cusip WHERE CAST(snapshot_date AS DATE) BETWEEN DATEADD(DAY, 1 - DATEPART(WEEKDAY, '2026-01-01'), '2026-01-01') AND DATEADD(DAY, 7 - DATEPART(WEEKDAY, '2026-01-01'), '2026-01-01') AND a.account_status_indicator = 'O' AND a.is_active = 1 GROUP BY s.asset_class ORDER BY aum DESC | I3: Done
A4: KPI-003 | B4: AUM by Custodian | C4: fact_position; dim_account; dim_custodian | D4: fact_position[market_value]; fact_position[position_date]; dim_account[account_status]; dim_account[is_current]; dim_account[custodian_key]; dim_custodian[custodian_short_name] | E4: Yes | G4: SELECT p.source_custodian, SUM(p.market_value) AS aum FROM fact_position p WHERE p.position_date = CURRENT_DATE GROUP BY p.source_custodian ORDER BY aum DESC | H4: SELECT p.custodian, SUM(p.amount) AS aum FROM positions p WHERE CAST(p.snapshot_date AS DATE) BETWEEN DATEADD(DAY, 1 - DATEPART(WEEKDAY, '2026-01-01'), '2026-01-01') AND DATEADD(DAY, 7 - DATEPART(WEEKDAY, '2026-01-01'), '2026-01-01') GROUP BY p.custodian ORDER BY aum DESC | I4: Done
A5: KPI-004 | B5: Average Account Size | C5: fact_position; dim_account | D5: fact_position[market_value]; fact_position[position_date]; dim_account[account_id]; dim_account[account_status]; dim_account[is_current] | E5: Yes | G5: SELECT SUM(p.market_value) / NULLIF(COUNT(DISTINCT p.canonical_account_id), 0) AS avg_acct_size FROM fact_position p JOIN dim_account a ON p.canonical_account_id = a.canonical_account_id WHERE p.position_date = CURRENT_DATE AND a.account_status = 'ACTIVE' AND a.is_current = TRUE | H5: SELECT SUM(p.amount) / NULLIF(COUNT(DISTINCT p.financial_account_id), 0) AS avg_acct_size FROM positions p JOIN financial_account a ON p.financial_account_id = a.financial_account_id WHERE p.snapshot_date BETWEEN DATEADD(DAY, 1 - DATEPART(WEEKDAY, '2026-01-01'), '2026-01-01') AND DATEADD(DAY, 7 - DATEPART(WEEKDAY, '2026-01-01'), '2026-01-01') AND a.account_status_indicator = 'O' AND a.is_active = 1 | I5: Done
A6: KPI-005 | B6: Average Household AUM | C6: fact_position; dim_account | D6: fact_position[market_value]; fact_position[position_date]; dim_account[account_id]; dim_account[household_id]; dim_account[account_status]; dim_account[is_current] | E6: Yes | G6: SELECT SUM(p.market_value) / NULLIF(COUNT(DISTINCT a.household_id), 0) AS avg_hh_aum FROM fact_position p JOIN dim_account a ON p.canonical_account_id = a.canonical_account_id WHERE p.position_date = CURRENT_DATE AND a.account_status = 'ACTIVE' AND a.is_current = TRUE AND a.household_id IS NOT NULL | H6: SELECT SUM(p.amount) / NULLIF(COUNT(DISTINCT h.house_hold_name), 0) AS avg_hh_aum FROM positions p JOIN financial_account a ON p.financial_account_id = a.financial_account_id JOIN household_details h ON h.financial_account_id = a.financial_account_id WHERE CAST(p.snapshot_date AS DATE) BETWEEN DATEADD(DAY, 1 - DATEPART(WEEKDAY, '2026-01-01'), '2026-01-01') AND DATEADD(DAY, 7 - DATEPART(WEEKDAY, '2026-01-01'), '2026-01-01') AND a.account_status_indicator = 'O' AND a.is_active = 1 AND h.house_hold_name IS NOT NULL | I6: Done
A7: KPI-006 | B7: Median Account Size | C7: fact_position; dim_account | D7: fact_position[market_value]; fact_position[position_date]; dim_account[account_id]; dim_account[account_status] | E7: Yes | G7: SELECT PERCENTILE_CONT(0.5) WITHIN GROUP (ORDER BY acct_aum) AS median_acct_size FROM ( SELECT p.canonical_account_id, SUM(p.market_value) AS acct_aum FROM fact_position p JOIN dim_account a ON p.canonical_account_id = a.canonical_account_id WHERE p.position_date = CURRENT_DATE AND a.account_status = 'ACTIVE' AND a.is_current = TRUE GROUP BY p.canonical_account_id ) sub | H7: WITH acct_sizes AS ( SELECT p.financial_account_id, SUM(p.amount) AS acct_aum FROM positions p JOIN financial_account a ON p.financial_account_id = a.financial_account_id WHERE CAST(p.snapshot_date AS DATE) BETWEEN DATEADD(DAY, 1 - DATEPART(WEEKDAY, '2026-01-01'), '2026-01-01') AND DATEADD(DAY, 7 - DATEPART(WEEKDAY, '2026-01-01'), '2026-01-01') AND a.account_status_indicator = 'O' AND a.is_active = 1 GROUP BY p.financial_account_id ) SELECT DISTINCT PERCENTILE_CONT(0.5) WITHIN GROUP (ORDER BY acct_aum) OVER () AS median_acct_size FROM acct_sizes; | I7: Done
A8: KPI-007 | B8: Number of Accounts | C8: dim_account | D8: dim_account[account_id]; dim_account[account_status]; dim_account[is_current] | E8: Yes | G8: SELECT COUNT(DISTINCT canonical_account_id) AS account_count FROM dim_account WHERE account_status = 'ACTIVE' AND is_current = TRUE | H8: SELECT COUNT(DISTINCT financial_account_id) AS account_count FROM financial_account WHERE is_active = 1 AND account_status_indicator = 'O' | I8: Done
A9: KPI-008 | B9: Number of Households | C9: dim_account; dim_household | D9: dim_account[household_id]; dim_account[account_status]; dim_household[household_id] | E9: Yes | I9: (with new derived table)
A10: KPI-009 | B10: Advisor Book Size (AUM) | C10: fact_position; dim_account; dim_advisor | D10: fact_position[market_value]; fact_position[position_date]; dim_account[account_status]; dim_account[is_current]; dim_account[advisor_id] | E10: Yes | G10: SELECT a.advisor_id, SUM(p.market_value) AS advisor_aum FROM fact_position p JOIN dim_account a ON p.canonical_account_id = a.canonical_account_id WHERE p.position_date = CURRENT_DATE AND a.account_status = 'ACTIVE' AND a.is_current = TRUE GROUP BY a.advisor_id ORDER BY advisor_aum DESC | H10: SELECT a.investment_professional_number, SUM(p.amount) AS advisor_aum FROM positions p JOIN financial_account a ON p.financial_account_id = a.financial_account_id WHERE CAST(p.snapshot_date AS DATE) BETWEEN DATEADD(DAY, 1 - DATEPART(WEEKDAY, '2026-01-01'), '2026-01-01') AND DATEADD(DAY, 7 - DATEPART(WEEKDAY, '2026-01-01'), '2026-01-01') AND a.account_status_indicator = 'O' AND a.is_active = 1 GROUP BY a.investment_professional_number ORDER BY advisor_aum DESC | I10: Done
A11: KPI-010 | B11: Advisor Account Count | C11: dim_account; dim_advisor | D11: dim_account[account_id]; dim_account[account_status]; dim_account[is_current]; dim_account[advisor_id] | E11: Yes | G11: SELECT a.advisor_id, COUNT(DISTINCT a.canonical_account_id) AS acct_count FROM dim_account a WHERE a.account_status = 'ACTIVE' AND a.is_current = TRUE GROUP BY a.advisor_id ORDER BY acct_count DESC | H11: SELECT a.investment_professional_number, COUNT(DISTINCT a.financial_account_id) AS acct_count FROM financial_account a WHERE a.account_status_indicator = 'O' AND a.is_active = 1 GROUP BY a.investment_professional_number ORDER BY acct_count DESC | I11: Done
A12: KPI-011 | B12: Cash Percentage | C12: fact_cash_balance; fact_position; dim_account | D12: fact_cash_balance[total_cash_equivalent]; fact_cash_balance[balance_date]; fact_position[market_value]; fact_position[position_date]; dim_account[account_id]; dim_account[account_status] | E12: Yes | I12: (with new derived table)
A13: KPI-012 | B13: Total Cash Holdings | C13: fact_cash_balance; dim_account | D13: fact_cash_balance[total_cash_equivalent]; fact_cash_balance[balance_date]; dim_account[account_status]; dim_account[is_current] | E13: Yes | I13: (with new derived table)
A14: KPI-013 | B14: Idle Cash (Excess Cash) | C14: fact_cash_balance; fact_position; dim_account | D14: fact_cash_balance[total_cash_equivalent]; fact_cash_balance[balance_date]; fact_position[market_value]; dim_account[account_status]; dim_account[is_current] | E14: Yes | I14: (with new derived table)
A15: KPI-014 | B15: Cash Drag | C15: fact_cash_balance; fact_position; dim_account | D15: fact_cash_balance[total_cash_equivalent]; fact_cash_balance[balance_date]; fact_position[market_value]; dim_account[account_status] | E15: Yes | I15: (with new derived table)
A16: KPI-041 | B16: Realized Gain/Loss (Period) | C16: fact_transaction | D16: fact_transaction[txn_type]; fact_transaction[gross_amount] | E16: Yes | G16: SELECT a.household_id, SUM(t.net_amount - t.cost_basis_sold) AS realized_gain_loss, SUM(CASE WHEN t.net_amount - t.cost_basis_sold > 0 THEN t.net_amount - t.cost_basis_sold ELSE 0 END) AS realized_gains, SUM(CASE WHEN t.net_amount - t.cost_basis_sold < 0 THEN t.net_amount - t.cost_basis_sold ELSE 0 END) AS realized_losses FROM fact_transaction t JOIN dim_account a ON t.canonical_account_id = a.canonical_account_id WHERE t.txn_type = 'SELL' AND t.trade_date BETWEEN @start_date AND @end_date AND t.is_cancelled = FALSE AND a.account_status = 'ACTIVE' AND a.is_current = TRUE GROUP BY a.household_id | I16: (with new derived table)
A17: KPI-016 | B17: Net New Assets (NNA) | C17: fact_transaction; dim_account | D17: fact_transaction[net_amount]; fact_transaction[txn_type]; fact_transaction[trade_date]; fact_transaction[is_cancelled]; dim_account[account_status] | E17: Yes | G17: SELECT SUM(CASE WHEN t.txn_type IN ('CONTRIBUTION','TRANSFER_IN') THEN t.net_amount ELSE 0 END) - SUM(CASE WHEN t.txn_type IN ('DISTRIBUTION','TRANSFER_OUT') THEN ABS(t.net_amount) ELSE 0 END) AS net_new_assets FROM fact_transaction t JOIN dim_account a ON t.canonical_account_id = a.canonical_account_id WHERE t.trade_date BETWEEN @start_date AND @end_date AND t.is_cancelled = FALSE | H17: ('RFF', 'CSR', --cash in(value in -ve) 'SFF','PCC') -- cash out(value in +ve) SELECT SUM(CASE WHEN t.transaction_code IN ('CONTRIBUTION','TRANSFER_IN', 'RFF', 'CSR') THEN ABS(t.amount) ELSE 0 END) - SUM(CASE WHEN t.transaction_code IN ('DISTRIBUTION','TRANSFER_OUT', 'SFF','PCC') THEN (t.amount) ELSE 0 END) AS net_new_assets FROM transactions t JOIN financial_account a ON t.financial_account_id = a.financial_account_id WHERE CAST(t.transaction_date AS DATE) BETWEEN '2026-01-01' AND '2026-01-31' AND t.cancel_code = 0 | I17: Done
A18: KPI-017 | B18: Gross Inflows | C18: fact_transaction; dim_account | D18: fact_transaction[net_amount]; fact_transaction[txn_type]; fact_transaction[trade_date]; fact_transaction[is_cancelled] | E18: Yes | G18: SELECT SUM(t.net_amount) AS gross_inflows FROM fact_transaction t WHERE t.txn_type IN ('CONTRIBUTION','TRANSFER_IN') AND t.trade_date BETWEEN @start_date AND @end_date AND t.is_cancelled = FALSE | H18: SELECT ABS(SUM(t.amount)) AS gross_inflows FROM transactions t WHERE t.transaction_code IN ('CONTRIBUTION','TRANSFER_IN', 'RFF', 'CSR') AND CAST(t.transaction_date AS DATE) BETWEEN '2026-01-01' AND '2026-01-31' AND t.cancel_code = 0 | I18: Done
A19: KPI-018 | B19: Gross Outflows | C19: fact_transaction; dim_account | D19: fact_transaction[net_amount]; fact_transaction[txn_type]; fact_transaction[trade_date]; fact_transaction[is_cancelled] | E19: Yes | G19: SELECT SUM(ABS(t.net_amount)) AS gross_outflows FROM fact_transaction t WHERE t.txn_type IN ('DISTRIBUTION','TRANSFER_OUT') AND t.trade_date BETWEEN @start_date AND @end_date AND t.is_cancelled = FALSE | H19: SELECT SUM(ABS(t.amount)) AS gross_outflows FROM transactions t WHERE t.transaction_code IN ('DISTRIBUTION', 'TRANSFER_OUT', 'SFF','PCC') AND CAST(t.transaction_date AS DATE) BETWEEN '2026-01-01' AND '2026-01-31' AND t.cancel_code = 0 | I19: Done
A20: KPI-019 | B20: Organic Growth Rate | C20: fact_transaction; fact_position | D20: fact_transaction[net_amount]; fact_transaction[txn_type]; fact_transaction[trade_date]; fact_transaction[is_cancelled]; fact_position[market_value]; fact_position[position_date] | E20: Yes | G20: WITH beg AS ( SELECT SUM(p.market_value) AS beg_aum FROM fact_position p JOIN dim_account a ON p.canonical_account_id = a.canonical_account_id WHERE p.position_date = @start_date AND a.account_status = 'ACTIVE' AND a.is_current = TRUE ), nna AS ( SELECT SUM(CASE WHEN txn_type IN ('CONTRIBUTION','TRANSFER_IN') THEN net_amount ELSE 0 END) - SUM(CASE WHEN txn_type IN ('DISTRIBUTION','TRANSFER_OUT') THEN ABS(net_amount) ELSE 0 END) AS nna FROM fact_transaction WHERE trade_date BETWEEN @start_date AND @end_date AND is_cancelled = FALSE ) SELECT (nna.nna / NULLIF(beg.beg_aum, 0)) * (12.0 / @months) * 100 AS organic_growth_rate FROM beg, nna | I20: Done
A21: KPI-020 | B21: Client Retention Rate (Asset) | C21: fact_position; fact_transaction | D21: fact_position[market_value]; fact_position[position_date]; fact_transaction[net_amount]; fact_transaction[txn_type]; fact_transaction[trade_date]; fact_transaction[is_cancelled] | E21: Yes | G21: SELECT (beg.beg_aum - COALESCE(out.outflows, 0)) / NULLIF(beg.beg_aum, 0) * 100 AS retention_rate FROM ( SELECT SUM(market_value) AS beg_aum FROM fact_position WHERE position_date = @start_date ) beg, ( SELECT SUM(ABS(net_amount)) AS outflows FROM fact_transaction WHERE txn_type IN ('DISTRIBUTION','TRANSFER_OUT') AND trade_date BETWEEN @start_date AND @end_date AND is_cancelled = FALSE ) out | I21: Done
A22: KPI-021 | B22: New Account Opens | C22: dim_account | D22: dim_account[account_id]; dim_account[open_date]; dim_account[is_current] | E22: Yes | G22: SELECT COUNT(*) AS new_accounts FROM dim_account WHERE open_date BETWEEN @start_date AND @end_date AND is_current = TRUE | H22: SELECT COUNT(*) AS new_accounts FROM financial_account WHERE CAST(date_account_opened AS DATE) BETWEEN '2026-01-01' AND '2026-01-31' AND is_active=1 | I22: Done
A23: KPI-022 | B23: Closed Accounts | C23: dim_account | D23: dim_account[account_id]; dim_account[close_date] | E23: Yes | G23: SELECT COUNT(*) AS closed_accounts FROM dim_account WHERE close_date BETWEEN @start_date AND @end_date | H23: SELECT COUNT(*) AS closed_accounts FROM financial_account WHERE CAST(date_account_closed AS DATE) BETWEEN '2026-01-01' AND '2026-01-31' | I23: Done
A24: KPI-023 | B24: Total Trade Count | C24: fact_transaction | D24: fact_transaction[txn_type]; fact_transaction[is_cancelled]; fact_transaction[trade_date] | E24: Yes | G24: SELECT COUNT(*) AS trade_count FROM fact_transaction WHERE txn_type IN ('BUY','SELL') AND trade_date BETWEEN @start_date AND @end_date AND is_cancelled = FALSE | H24: SELECT COUNT(*) AS trade_count FROM transactions WHERE transaction_type IN ('buy','sell') AND CAST(transaction_date AS DATE) BETWEEN '2026-01-01' AND '2026-01-31' AND cancel_code = 0 | I24: Done
A25: KPI-024 | B25: Trade Volume ($) | C25: fact_transaction | D25: fact_transaction[gross_amount]; fact_transaction[txn_type]; fact_transaction[is_cancelled] | E25: Yes | G25: SELECT SUM(ABS(t.gross_amount)) AS trade_volume FROM fact_transaction t WHERE t.txn_type IN ('BUY','SELL') AND t.trade_date BETWEEN @start_date AND @end_date AND t.is_cancelled = FALSE | H25: SELECT SUM(ABS(t.amount)) AS trade_volume FROM transactions t WHERE t.transaction_type IN ('buy','sell') AND CAST(t.transaction_date AS DATE) BETWEEN '2026-01-01' AND '2026-01-31' AND t.cancel_code = 0 | I25: Done
A26: KPI-025 | B26: Buy/Sell Ratio | C26: fact_transaction | D26: fact_transaction[gross_amount]; fact_transaction[txn_type]; fact_transaction[is_cancelled] | E26: Yes | G26: SELECT SUM(CASE WHEN txn_type = 'BUY' THEN ABS(gross_amount) ELSE 0 END) / NULLIF(SUM(CASE WHEN txn_type = 'SELL' THEN ABS(gross_amount) ELSE 0 END), 0) AS buy_sell_ratio FROM fact_transaction WHERE txn_type IN ('BUY','SELL') AND trade_date BETWEEN @start_date AND @end_date AND is_cancelled = FALSE | H26: SELECT SUM(CASE WHEN transaction_type = 'buy' THEN ABS(amount) ELSE 0 END) / NULLIF(SUM(CASE WHEN transaction_type = 'sell' THEN ABS(amount) ELSE 0 END), 0) AS buy_sell_ratio FROM transactions WHERE transaction_type IN ('buy','sell') AND CAST(transaction_date AS DATE) BETWEEN '2026-01-01' AND '2026-01-31' AND cancel_code = 0 | I26: Done
A27: KPI-026 | B27: Portfolio Turnover Rate | C27: fact_transaction; fact_position | D27: fact_transaction[gross_amount]; fact_transaction[txn_type]; fact_transaction[is_cancelled]; fact_position[market_value]; fact_position[position_date] | E27: Yes | G27: WITH trade_sides AS ( SELECT SUM(CASE WHEN txn_type = 'BUY' THEN ABS(gross_amount) ELSE 0 END) AS total_buys, SUM(CASE WHEN txn_type = 'SELL' THEN ABS(gross_amount) ELSE 0 END) AS total_sells FROM fact_transaction WHERE txn_type IN ('BUY','SELL') AND trade_date BETWEEN @start_date AND @end_date AND is_cancelled = FALSE ), avg_aum AS ( SELECT AVG(daily_aum) AS avg_aum FROM ( SELECT position_date, SUM(market_value) AS daily_aum FROM fact_position WHERE position_date BETWEEN @start_date AND @end_date GROUP BY position_date ) sub ) SELECT LEAST(total_buys, total_sells) / NULLIF(avg_aum.avg_aum, 0) * (12.0 / @months) * 100 AS turnover_rate FROM trade_sides, avg_aum | I27: Done
A28: KPI-027 | B28: Average Trade Size | C28: fact_transaction | D28: fact_transaction[gross_amount]; fact_transaction[txn_type]; fact_transaction[is_cancelled] | E28: Yes | G28: SELECT SUM(ABS(t.gross_amount)) / NULLIF(COUNT(*), 0) AS avg_trade_size FROM fact_transaction t WHERE t.txn_type IN ('BUY','SELL') AND t.trade_date BETWEEN @start_date AND @end_date AND t.is_cancelled = FALSE | H28: SELECT SUM(ABS(t.amount)) / NULLIF(COUNT(*), 0) AS avg_trade_size FROM transactions t WHERE t.transaction_type IN ('buy','sell') AND CAST(t.transaction_date AS DATE) BETWEEN '2026-01-01' AND '2026-01-31' AND t.cancel_code = 0 | I28: Done
A29: KPI-028 | B29: Commission/Fee per Trade | C29: fact_transaction | D29: fact_transaction[commission]; fact_transaction[fees]; fact_transaction[txn_type]; fact_transaction[is_cancelled] | E29: Yes | G29: SELECT SUM(t.commission + t.fees) / NULLIF(COUNT(*), 0) AS fee_per_trade FROM fact_transaction t WHERE t.txn_type IN ('BUY','SELL') AND t.trade_date BETWEEN @start_date AND @end_date AND t.is_cancelled = FALSE | H29: SELECT SUM(net_commission) / NULLIF(COUNT(distinct trade_id), 0) AS fee_per_trade FROM fa_commission WHERE CAST(t.transaction_date AS DATE) BETWEEN '2026-01-01' AND '2026-01-31' | I29: Done
A30: KPI-029 | B30: Dividend/Interest Income | C30: fact_transaction | D30: fact_transaction[net_amount]; fact_transaction[txn_type]; fact_transaction[is_cancelled] | E30: Yes | G30: SELECT SUM(t.net_amount) AS div_int_income FROM fact_transaction t WHERE t.txn_type IN ('DIVIDEND','INTEREST') AND t.trade_date BETWEEN @start_date AND @end_date AND t.is_cancelled = FALSE | H30: SELECT SUM(t.amount) AS div_int_income FROM transactions t WHERE t.txn_type IN ('DIVIDEND','INTEREST') AND CAST(t.transaction_date AS DATE) BETWEEN '2026-01-01' AND '2026-01-31' AND t.cancel_code = 0 | I30: Done
A31: KPI-030 | B31: Equity Allocation % | C31: fact_position; dim_account | D31: fact_position[market_value]; fact_position[asset_class]; fact_position[position_date]; dim_account[account_status] | E31: Yes | G31: SELECT SUM(CASE WHEN p.asset_class IN ('US_EQUITY','INTL_EQUITY_DM','INTL_EQUITY_EM') THEN p.market_value ELSE 0 END) / NULLIF(SUM(p.market_value), 0) * 100 AS equity_pct FROM fact_position p JOIN dim_account a ON p.canonical_account_id = a.canonical_account_id WHERE p.position_date = CURRENT_DATE AND a.account_status = 'ACTIVE' AND a.is_current = TRUE | H31: SELECT SUM(CASE WHEN s.asset_class IN ('Equity') THEN p.amount ELSE 0 END) / NULLIF(SUM(p.amount), 0) * 100 AS equity_pct FROM positions p JOIN financial_account a ON p.financial_account_id = a.financial_account_id JOIN securities s ON s.cusip = p.cusip WHERE CAST(snapshot_date as DATE) BETWEEN DATEADD(DAY, 1 - DATEPART(WEEKDAY, '2026-01-01'), '2026-01-01') AND DATEADD(DAY, 7 - DATEPART(WEEKDAY, '2026-01-01'), '2026-01-01') AND a.account_status_indicator = 'O' AND a.is_active = 1 | I31: Done
A32: KPI-031 | B32: Fixed Income Allocation % | C32: fact_position; dim_account | D32: fact_position[market_value]; fact_position[asset_class]; fact_position[position_date]; dim_account[account_status] | E32: Yes | G32: SELECT SUM(CASE WHEN p.asset_class IN ('FIXED_INCOME_GOVT','FIXED_INCOME_CORP') THEN p.market_value ELSE 0 END) / NULLIF(SUM(p.market_value), 0) * 100 AS fi_pct FROM fact_position p JOIN dim_account a ON p.canonical_account_id = a.canonical_account_id WHERE p.position_date = CURRENT_DATE AND a.account_status = 'ACTIVE' AND a.is_current = TRUE | H32: SELECT SUM(CASE WHEN s.asset_class IN ('Fixed Income') THEN p.amount ELSE 0 END) / NULLIF(SUM(p.amount), 0) * 100 AS fi_pct FROM positions p JOIN financial_account a ON p.financial_account_id = a.financial_account_id JOIN securities s ON s.cusip = p.cusip WHERE CAST(snapshot_date AS DATE) BETWEEN DATEADD(DAY, 1 - DATEPART(WEEKDAY, '2026-01-01'), '2026-01-01') AND DATEADD(DAY, 7 - DATEPART(WEEKDAY, '2026-01-01'), '2026-01-01') AND a.account_status_indicator = 'O' AND a.is_active = 1 | I32: Done
A33: KPI-032 | B33: Alternative Allocation % | C33: fact_position; dim_account | D33: fact_position[market_value]; fact_position[asset_class]; fact_position[position_date]; dim_account[account_status] | E33: Yes | G33: SELECT SUM(CASE WHEN p.asset_class = 'ALTERNATIVES' THEN p.market_value ELSE 0 END) / NULLIF(SUM(p.market_value), 0) * 100 AS alt_pct FROM fact_position p JOIN dim_account a ON p.canonical_account_id = a.canonical_account_id WHERE p.position_date = CURRENT_DATE AND a.account_status = 'ACTIVE' AND a.is_current = TRUE | H33: SELECT SUM(CASE WHEN s.asset_class = 'Alternative Investments' THEN p.amount ELSE 0 END) / NULLIF(SUM(p.amount), 0) * 100 AS alt_pct FROM positions p JOIN financial_account a ON p.financial_account_id = a.financial_account_id JOIN securities s on s.cusip = p.cusip WHERE CAST(p.snapshot_date AS DATE) BETWEEN DATEADD(DAY, 1 - DATEPART(WEEKDAY, '2026-01-01'), '2026-01-01') AND DATEADD(DAY, 7 - DATEPART(WEEKDAY, '2026-01-01'), '2026-01-01') AND a.account_status_indicator = 'O' AND a.is_active = 1 | I33: Done
A34: KPI-033 | B34: Number of Positions | C34: fact_position; dim_account | D34: fact_position[cusip]; fact_position[position_date]; dim_account[account_id]; dim_account[account_status] | E34: Yes | G34: SELECT a.canonical_account_id, COUNT(DISTINCT p.cusip) AS position_count FROM fact_position p JOIN dim_account a ON p.canonical_account_id = a.canonical_account_id WHERE p.position_date = CURRENT_DATE AND a.account_status = 'ACTIVE' AND a.is_current = TRUE GROUP BY a.canonical_account_id | H34: SELECT a.financial_account_id, COUNT(DISTINCT p.cusip) AS position_count FROM positions p JOIN financial_account a ON p.financial_account_id = a.financial_account_id WHERE CAST(p.snapshot_date AS DATE) BETWEEN DATEADD(DAY, 1 - DATEPART(WEEKDAY, '2026-01-01'), '2026-01-01') AND DATEADD(DAY, 7 - DATEPART(WEEKDAY, '2026-01-01'), '2026-01-01') AND a.account_status_indicator = 'O' AND a.is_active = 1 GROUP BY a.financial_account_id | I34: Done
A35: KPI-034 | B35: Top 10 Concentration % | C35: fact_position; dim_account | D35: fact_position[market_value]; fact_position[cusip]; fact_position[position_date]; dim_account[advisor_id]; dim_account[account_status] | E35: Yes | G35: WITH ranked AS ( SELECT p.cusip, p.market_value, ROW_NUMBER() OVER (ORDER BY p.market_value DESC) AS rn FROM fact_position p WHERE p.position_date = CURRENT_DATE ) SELECT SUM(CASE WHEN rn <= 10 THEN market_value ELSE 0 END) / NULLIF(SUM(market_value), 0) * 100 AS top10_pct FROM ranked | H35: WITH ranked AS ( SELECT p.cusip, p.amount, ROW_NUMBER() OVER (ORDER BY p.amount DESC) AS rn FROM positions p WHERE p.snapshot_date BETWEEN DATEADD(DAY, 1 - DATEPART(WEEKDAY, '2026-01-01'), '2026-01-01') AND DATEADD(DAY, 7 - DATEPART(WEEKDAY, '2026-01-01'), '2026-01-01') ) SELECT SUM(CASE WHEN rn <= 10 THEN amount ELSE 0 END) / NULLIF(SUM(amount), 0) * 100 AS top10_pct FROM ranked | I35: Done
A36: KPI-035 | B36: Single Position Concentration | C36: fact_position | D36: fact_position[market_value]; fact_position[position_date] | E36: Yes | G36: SELECT MAX(p.market_value) / NULLIF(SUM(p.market_value), 0) * 100 AS max_concentration FROM fact_position p WHERE p.position_date = CURRENT_DATE | H36: SELECT MAX(p.amount) / NULLIF(SUM(p.amount), 0) * 100 AS max_concentration, DATEADD(DAY, 1 - DATEPART(WEEKDAY,'2026-01-01'), '2026-01-01') AS start_date, DATEADD(DAY, 7 - DATEPART(WEEKDAY, '2026-01-01'), '2026-01-01') AS end_date FROM positions p WHERE CAST(p.snapshot_date AS DATE) BETWEEN DATEADD(DAY, 1 - DATEPART(WEEKDAY, '2026-01-01'), '2026-01-01') AND DATEADD(DAY, 7 - DATEPART(WEEKDAY, '2026-01-01'), '2026-01-01'); | I36: Done
A37: KPI-046 | B37: Effective Fee Rate (bps) | C37: fact_billing_event; fact_position; dim_account | D37: fact_billing_event[net_fee]; fact_billing_event[billing_period_start]; fact_billing_event[billing_period_end]; fact_position[market_value]; fact_position[position_date]; dim_account[account_status] | E37: Yes | I37: (with new derived table)
A38: KPI-047 | B38: Revenue per Advisor | C38: fact_billing_event; dim_account; dim_advisor | D38: fact_billing_event[net_fee]; fact_billing_event[billing_period_start]; fact_billing_event[billing_period_end]; dim_account[advisor_id]; dim_account[is_current] | E38: Yes | I38: (with new derived table)
A39: KPI-048 | B39: Revenue per Household | C39: fact_billing_event | D39: fact_billing_event[net_fee]; fact_billing_event[billing_period_start]; fact_billing_event[billing_period_end]; fact_billing_event[household_id] | E39: Yes | I39: (with new derived table)
A40: KPI-050 | B40: High Cash Accounts | C40: fact_cash_balance; fact_position; dim_account | D40: fact_cash_balance[total_cash_equivalent]; fact_cash_balance[balance_date]; fact_position[market_value]; fact_position[position_date]; dim_account[account_id] | E40: Yes | I40: (with new derived table)
A41: KPI-053 | B41: Multi-Custodial Recon Breaks | C41: fact_position | D41: fact_position[account_id]; fact_position[cusip]; fact_position[market_value]; fact_position[source_custodian]; fact_position[position_date] | E41: Yes | I41: (with new derived table)
A42: KPI-057 | B42: Advisor Revenue Rank | C42: fact_billing_event; dim_account; dim_advisor | D42: fact_billing_event[net_fee]; fact_billing_event[billing_period_start]; fact_billing_event[billing_period_end]; dim_account[advisor_id]; dim_account[is_current] | E42: Yes | I42: (with new derived table)
A43: KPI-015 | B43: Pending Cash Activity | C43: fact_cash_balance | D43: fact_cash_balance[pending_amount]; fact_cash_balance[settlement_status]; fact_cash_balance[balance_date] | E43: No | F43: Due to 2 columns 'fact_cash_balance[pending_amount]', 'fact_cash_balance[settlement_status]' | I43: Data Available/Calculation Required
A44: KPI-037 | B44: International Exposure % | C44: fact_position; dim_security | D44: fact_position[market_value]; fact_position[cusip]; fact_position[position_date]; dim_security[country] | E44: No | F44: Due to 1 column 'dim_security[country]' | I44: Data Available/Calculation Required
A45: KPI-038 | B45: Unrealized Gain/Loss | C45: fact_position; dim_account | D45: fact_position[unrealized_gain_loss]; fact_position[position_date]; dim_account[account_status]; dim_account[is_current] | E45: No | F45: Due to 1 column 'fact_position[unrealized_gain_loss]' | I45: Data Available/Calculation Required
A46: KPI-040 | B46: Winners vs Losers Count | C46: fact_position | D46: fact_position[unrealized_gain_loss]; fact_position[position_date] | E46: No | F46: Due to 1 column 'fact_position[unrealized_gain_loss]' | I46: Data Available/Calculation Required
A47: KPI-043 | B47: Tax Loss Harvest Opportunity | C47: fact_position; dim_account | D47: fact_position[unrealized_gain_loss]; fact_position[position_date]; dim_account[tax_status]; dim_account[account_status]; dim_account[is_current] | E47: No | F47: Due to 1 column 'fact_position[unrealized_gain_loss]' | I47: Data Available/Calculation Required
